Workbook

Sheet ОТЧЕТ 2026
B2: ОПЕРАТИВНАЯ ИНФОРМАЦИЯ ПО СБОРУ ГОРОШКА (СЕЗОН 2026 г.)
B19: ИЮНЬ
B20: Пн | C20: Вт | D20: Ср | E20: Чт | F20: Пт | G20: Сб | H20: Вс
B21: 1 | C21: =B21+1 -> 2 | D21: =C21+1 -> 3 | E21: =D21+1 -> 4 | F21: =E21+1 -> 5 | G21: =F21+1 -> 6 | H21: =G21+1 -> 7
B22: =H21+1 -> 8 | C22: =B22+1 -> 9 | D22: =C22+1 -> 10 | E22: =D22+1 -> 11 | F22: =E22+1 -> 12 | G22: =F22+1 -> 13 | H22: =G22+1 -> 14
B23: =H22+1 -> 15 | C23: =B23+1 -> 16 | D23: =C23+1 -> 17 | E23: =D23+1 -> 18 | F23: =E23+1 -> 19 | G23: =F23+1 -> 20 | H23: =G23+1 -> 21
B24: =H23+1 -> 22 | C24: =B24+1 -> 23 | D24: =C24+1 -> 24 | E24: =D24+1 -> 25 | F24: =E24+1 -> 26 | G24: =F24+1 -> 27 | H24: =G24+1 -> 28
B25: =H24+1 -> 29 | C25: =B25+1 -> 30
B26: ИЮЛЬ
D27: =1 -> 1 | E27: =D27+1 -> 2 | F27: =E27+1 -> 3 | G27: =F27+1 -> 4 | H27: =G27+1 -> 5
B28: =H27+1 -> 6 | C28: =B28+1 -> 7 | D28: =C28+1 -> 8 | E28: =D28+1 -> 9 | F28: =E28+1 -> 10 | G28: =F28+1 -> 11 | H28: =G28+1 -> 12
B29: =H28+1 -> 13 | C29: =B29+1 -> 14 | D29: =C29+1 -> 15 | E29: =D29+1 -> 16 | F29: =E29+1 -> 17 | G29: =F29+1 -> 18 | H29: =G29+1 -> 19
B31: День уборки - | E31: 7

Sheet Подробности1
A1: Сведения о Площадь уборки, га - Регистратор.Номенклатура: Авола, Поле: А-3, Дата отчета: 6/9/2026, Культура: ГРК (богара)
A3: Показатель | B3: Количество | C3: Значение финометра | D3: Регистратор.Номер | E3: Регистратор.Дата | F3: Регистратор.Вес брутто | G3: Регистратор.Вес нетто | H3: Регистратор.Вес тары | I3: Регистратор.Вес чистый | J3: Регистратор.Контрагент | K3: Регистратор.Номенклатура | L3: Регистратор.Комбайнеры.Поле.Наименование | M3: Регистратор.Водитель | N3: Регистратор.Время прибытия | O3: Регистратор.Время убытия | P3: Регистратор.Комбайнеры.Комбайнер.Наименование | Q3: Регистратор.Номера талонов | R3: Регистратор.Номер машины | S3: Регистратор.Номер прицепа | T3: Поле | U3: Сорт уточн | V3: Площадь уборки, га | W3: Культура | X3: Орошение | Y3: Смена | Z3: Дата отчета | AA3: Продажа | AB3: Примечание | AC3: Финометр | AD3: Характеристика | AE3: № акта | AF3: Дата акта | AG3: Вх № | AH3: Степень зрелости вспом
C4: 50 | D4: 157 | G4: 7110 | I4: 5510.3 | J4: ГРИН РЭЙ КУБАНЬ ООО | K4: Авола | M4: Ревенко Андрей Вячеславович | R4: А781РР | T4: А-3 | U4: Авола | W4: ГРК (богара) | X4: богара | Y4: 6 | Z4: 46182 | AC4: 40-52 | AD4: Высший | AE4: 103 | AF4: 46182 | AH4: 50
C5: 50 | D5: 156 | G5: 13160 | I5: 9935.8 | J5: ГРИН РЭЙ КУБАНЬ ООО | K5: Авола | M5: Сероштан Станислав Викторович | R5: Е758РЕ | T5: А-3 | U5: Авола | W5: ГРК (богара) | X5: богара | Y5: 6 | Z5: 46182 | AC5: 40-52 | AD5: Высший | AE5: 102 | AF5: 46182 | AH5: 50
C6: 48 | D6: 155 | G6: 13230 | I6: 9988.7 | J6: ГРИН РЭЙ КУБАНЬ ООО | K6: Авола | M6: Емец Р.А. | R6: У315НХ | T6: А-3 | U6: Авола | W6: ГРК (богара) | X6: богара | Y6: 6 | Z6: 46182 | AC6: 40-52 | AD6: Высший | AE6: 101 | AF6: 46182 | AH6: 48

Sheet Свод 2026
A1: Уборка гороха овощного в 2026 году на | C1: 46182
E3: Данные
A4: Культура | B4: Дата отчета | C4: Поле | D4: Регистратор.Номенклатура | E4: Площадь уборки, га | F4: Физический вес, кг | G4: Зачетный вес, кг | H4: в т.ч. Продажа, кг
A5: ГРК (богара) | B5: 46176 | C5: А-4/1 | D5: Тиара | E5: 36 | F5: 191510 | G5: 151574.5
B6: 46177 | C6: А-4/1 | D6: Тиара | E6: 20 | F6: 111250 | G6: 90266.7
C7: А-3 | D7: Авола | E7: 2 | F7: 6120 | G7: 4039.2
B8: 46179 | C8: А-4/1 | D8: Тиара | E8: 42 | F8: 244270 | G8: 195974.1
C9: А-22/1 | D9: Тиара | E9: 5 | F9: 24650 | G9: 20918.3
B10: 46180 | C10: А-4/1 | D10: Тиара | E10: 13 | F10: 61380 | G10: 49780.1
C11: А-3 | D11: Авола | E11: 30 | F11: 160930 | G11: 130624.7
B12: 46181 | C12: А-3 | D12: Авола | E12: 41 | F12: 246500 | G12: 202267.4
B13: 46182 | C13: А-3 | D13: Авола | E13: 6 | F13: 33500 | G13: 25434.8
C14: А-22/1 | D14: Увертюра | E14: 31 | F14: 206840 | G14: 180195.1 | H14: 32930
C15: А-23 | D15: Увертюра | E15: 9 | F15: 69350 | G15: 64079.6 | H15: 26130
A16: Итог Результат | E16: 235 | F16: 1356300 | G16: 1115154.5 | H16: 59060

Sheet Структура 2026 
A2: Структура посевных площадей
A4: Отбор: | B4: Год урожая Равно "2026 г." И Участок не используется Равно "Нет"
A6: Год урожая | D6: Площадь общая | E6: Площадь сева
A7: Подразделение
A8: Культура
A9: Поле
A10: 2026 г. | D10: 8282.66 | E10: 8282.66
A11: 2. Растениеводство (20) | D11: 5345 | E11: 5345
A12: Кукуруза на зерно | D12: 237 | E12: 237
A13: А-102/1 | D13: 5 | E13: 5
A14: А-103/1 | D14: 35 | E14: 35
A15: А-108/3 | D15: 9 | E15: 9
A16: А-109/1 | D16: 18 | E16: 18
A17: А-11 | D17: 17 | E17: 17
A18: А-110/1 | D18: 7 | E18: 7
A19: А-68/1 | D19: 77 | E19: 77
A20: А-84/1 | D20: 69 | E20: 69
A21: Подсолнечник | D21: 910 | E21: 910
... A165: Итого | D165: 8282.66 | E165: 8282.66

Sheet Сев 2026
D3: Значения
A4: Поле | B4: Номенклатура | C4: Сорт | D4: Площадь сева, га | E4: Всего внесено, ед. изм. | F4: Площадь обработанная, га
A5: А-104/1 | B5: Семена гороха ( п.е.) | C5: Женева 100 т.с. | D5: 11 | E5: 16 | F5: 1.5
B6: Семена гороха овощного протравленные | C6: Тристар 100 тыс.с (лот D0021 15 T25-3033ST) | D6: 11 | E6: 20 | F6: 1.5
B7: Семена гороха овощного протравленные (кг) | C7: Патриот ЭС | D7: 11 | E7: 2000 | F7: 8
A8: А-104/1 Итог | D8: 11 | E8: 2036 | F8: 11 | H8: =D8-F8 -> 0
A9: А-105/1 | B9: Семена гороха ( п.е.) | C9: Женева 100 т.с. | D9: 56 | E9: 20 | F9: 1.5
B10: Семена гороха овощного протравленные | C10: Авола 100 тыс.с (лот D0021 15 K25-6011ST) | D10: 56 | E10: 285 | F10: 24
C11: Авола 100 тыс.с (лот D0021 15 K25-6012ST) | D11: 56 | E11: 353 | F11: 30.5
A12: А-105/1 Итог | D12: 56 | E12: 658 | F12: 56 | H12: =D12-F12 -> 0
A13: А-111/1 | B13: Семена гороха овощного протравленные | C13: Авола 100 тыс.с (лот Kl1038104) | D13: 14 | E13: 177 | F13: 14
A14: А-111/1 Итог | D14: 14 | E14: 177 | F14: 14 | H14: =D14-F14 -> 0
A15: А-112/1 | B15: Семена гороха овощного протравленные | C15: Авола 100 тыс.с (лот Kl1038104) | D15: 40 | E15: 126 | F15: 10
C16: Тристар 100 тыс.с (лот ES1038103) | D16: 40 | E16: 390 | F16: 30
A17: А-112/1 Итог | D17: 40 | E17: 516 | F17: 40 | H17: =D17-F17 -> 0
A18: А-114 | B18: Семена гороха ( п.е.) | C18: Женева 100 т.с. | D18: 4 | E18: 52 | F18: 4
A19: А-114 Итог | D19: 4 | E19: 52 | F19: 4 | H19: =D19-F19 -> 0
A20: А-115/1 | B20: Семена гороха овощного протравленные | C20: Тристар 100 тыс.с (лот D0021 15 T25-3033ST) | D20: 63 | E20: 220 | F20: 21
C21: Тристар 100 тыс.с (лот ES1038103) | D21: 63 | E21: 515 | F21: 42
A22: А-115/1 Итог | D22: 63 | E22: 735 | F22: 63 | H22: =D22-F22 -> 0
A23: А-116/1 | B23: Семена гороха овощного протравленные | C23: Фаворит 100 т.с.(партия Н-Х/4402) | D23: 47 | E23: 160 | F23: 47 | J23: семенной участок
C24: Фаворит 100 т.с.(партия Н-Х/5126) | D24: 47 | E24: 377 | F24: 36
C25: Фаворит 100 т.с.(партия Н-Х/5128) | D25: 47 | E25: 120 | F25: 11
A26: А-116/1 Итог | D26: 47 | E26: 657 | F26: 94 | H26: =D26-F26 -> -47
A27: А-22/1 | B27: Семена гороха ( п.е.) | C27: Увертюра 100 000 | D27: 36 | E27: 426 | F27: 31
B28: Семена гороха овощного протравленные | C28: Тиара 100 т.с.(партия Н-Х/5120) | D28: 36 | E28: 90 | F28: 5
A29: А-22/1 Итог | D29: 36 | E29: 516 | F29: 36 | H29: =D29-F29 -> 0
A30: А-23 | B30: Семена гороха ( п.е.) | C30: Увертюра 100 000 | D30: 41 | E30: 274 | F30: 20
B31: Семена гороха овощного протравленные | C31: Фаворит 100 т.с.(партия Н-Х/5121) | D31: 41 | E31: 289 | F31: 21
A32: А-23 Итог | D32: 41 | E32: 563 | F32: 41 | H32: =D32-F32 -> 0
A33: А-24/1 | B33: Семена гороха овощного протравленные | C33: Фаворит 100 т.с.(партия Н-Х/5121) | D33: 39 | E33: 523 | F33: 39
A34: А-24/1 Итог | D34: 39 | E34: 523 | F34: 39 | H34: =D34-F34 -> 0
A35: А-3 | B35: Семена гороха овощного протравленные | C35: Авола 100 тыс.с (лот D0021 15 K25-6011ST) | D35: 79 | E35: 270 | F35: 34
C36: Авола 100 тыс.с (лот Kl1038104) | D36: 79 | E36: 359 | F36: 45
B37: Семена гороха овощного протравленные (кг) | C37: Преладо | D37: 79 | E37: 8410 | F37: 79 | J37: подсев
A38: А-3 Итог | D38: 79 | E38: 9039 | F38: 158 | H38: =D38-F38 -> -79
A39: А-38 | B39: Семена гороха овощного протравленные | C39: Авола 100 тыс.с (лот Kl1038104) | D39: 38 | E39: 302 | F39: 38
B40: Семена гороха овощного протравленные (кг) | C40: Преладо | D40: 38 | E40: 4040 | F40: 38 | J40: подсев
A41: А-38 Итог | D41: 38 | E41: 4342 | F41: 76 | H41: =D41-F41 -> -38
A42: А-4/1 | B42: Семена гороха овощного протравленные | C42: Тиара 100 т.с.(партия Н-Х/5116) | D42: 111 | E42: 700 | F42: 62
C43: Тиара 100 т.с.(партия Н-Х/5119) | D43: 111 | E43: 560 | F43: 39
C44: Тиара 100 т.с.(партия Н-Х/5120) | D44: 111 | E44: 180 | F44: 10
A45: А-4/1 Итог | D45: 111 | E45: 1440 | F45: 111 | H45: =D45-F45 -> 0
A46: А-5/1 | B46: Семена гороха овощного протравленные | C46: Авола 100 тыс.с (лот D0021 15 K25-6011ST) | D46: 63 | E46: 503 | F46: 63
B47: Семена гороха овощного протравленные (кг) | C47: Преладо | D47: 63 | E47: 6700 | F47: 63 | J47: подсев
A48: А-5/1 Итог | D48: 63 | E48: 7203 | F48: 126 | H48: =D48-F48 -> -63
A49: А-76/3 | B49: Семена гороха овощного протравленные | C49: Авола 100 тыс.с (лот Kl1038104) | D49: 41 | E49: 325 | F49: 41
B50: Семена гороха овощного протравленные (кг) | C50: Преладо | D50: 41 | E50: 4360 | F50: 41 | J50: подсев
A51: А-76/3 Итог | D51: 41 | E51: 4685 | F51: 82 | H51: =D51-F51 -> -41
A52: А-76/5 | B52: Семена гороха овощного протравленные | C52: Авола 100 тыс.с (лот Kl1038104) | D52: 14 | E52: 111 | F52: 14
B53: Семена гороха овощного протравленные (кг) | C53: Преладо | D53: 14 | E53: 1490 | F53: 14 | J53: подсев
A54: А-76/5 Итог | D54: 14 | E54: 1601 | F54: 28 | H54: =D54-F54 -> -14
A55: А-83/1 | B55: Семена гороха овощного протравленные | C55: Фаворит 100 т.с.(партия Н-Х/5121) | D55: 24 | E55: 296 | F55: 24
A56: А-83/1 Итог | D56: 24 | E56: 296 | F56: 24 | H56: =D56-F56 -> 0
A57: А-83/2 | B57: Семена гороха овощного протравленные | C57: Авола 100 тыс.с (лот D0021 15 K25-6011ST) | D57: 57 | E57: 202 | F57: 17.3
C58: Авола 100 тыс.с (лот D0021 15 K25-6012ST) | D58: 57 | E58: 487 | F58: 34.7
C59: Фаворит 100 т.с.(партия Н-Х/5121) | D59: 57 | E59: 62 | F59: 5
A60: А-83/2 Итог | D60: 57 | E60: 751 | F60: 57 | H60: =D60-F60 -> 0
A61: Общий итог | D61: 48.315789 | E61: 35790 | F61: 1060

Sheet Данные 2026
K1: протянуть формулу на след день
A2: 1.1 | B2: Выборка по КА, орошению | D2: 5 | I2: 8
A3: Валовый сбор | D3: Выполнение плана по сбору | E3: ПЛАН, т | F3: ФАКТ, т | G3: Исполнение плана, % | I3: Ежедневные показатели | K3: Сбор, т | L3: Значение спелости | M3: Финометр
A4: ПЛАН, т | B4: =C59 -> 9535.8 | D4: ГРК (богара) | E4: =C55 -> 3890 | F4: =D55 -> 1356.3 | G4: =IFERROR(F4/E4, ) -> 0.34866324 | I4: 1 | J4: 46176 | K4: =IFERROR(SUMIF('Реестр уборки 2026'!Z:Z,J4,'Реестр уборки 2026'!G:G)/1000, ) -> 191.51 | L4: =IFERROR(AVERAGEIF('Реестр уборки 2026'!Z:Z,'Данные 2026'!J4,'Реестр уборки 2026'!C:C),) -> 52.285714 | M4: нет данных
A5: ФАКТ, т | B5: =D59 -> 1356.3 | D5: ГРК (полив) | E5: =C56 -> 2100 | F5: =D56 -> 0 | G5: =IFERROR(F5/E5, ) -> 0 | I5: 2 | J5: =J4+1 -> 46177 | K5: =IFERROR(SUMIF('Реестр уборки 2026'!Z:Z,J5,'Реестр уборки 2026'!G:G)/1000, ) -> 117.37 | L5: =IFERROR(AVERAGEIF('Реестр уборки 2026'!Z:Z,'Данные 2026'!J5,'Реестр уборки 2026'!C:C),) -> 52 | M5: нет данных
A6: Исполнение плана, % | B6: =E59 -> 0.14223243 | D6: Агролидер (полив) | E6: =C57 -> 1345 | F6: =D57 -> 0 | G6: =IFERROR(F6/E6, ) -> 0 | I6: 3 | J6: =J5+1 -> 46178 | M6: нет данных
D7: Колос (полив) | E7: =C58 -> 2200.8 | F7: =D58 -> 0 | G7: =IFERROR(F7/E7, ) -> 0 | I7: 4 | J7: =J6+1 -> 46179 | K7: =IFERROR(SUMIF('Реестр уборки 2026'!Z:Z,J7,'Реестр уборки 2026'!G:G)/1000, ) -> 268.92 | L7: =IFERROR(AVERAGEIF('Реестр уборки 2026'!Z:Z,'Данные 2026'!J7,'Реестр уборки 2026'!C:C),) -> 47.826087 | M7: нет данных
A8: 1.2 | I8: 5 | J8: =J7+1 -> 46180 | K8: =IFERROR(SUMIF('Реестр уборки 2026'!Z:Z,J8,'Реестр уборки 2026'!G:G)/1000, ) -> 222.31 | L8: =IFERROR(AVERAGEIF('Реестр уборки 2026'!Z:Z,'Данные 2026'!J8,'Реестр уборки 2026'!C:C),) -> 51.2 | M8: нет данных
A9: Зачетный вес | I9: 6 | J9: =J8+1 -> 46181 | K9: =IFERROR(SUMIF('Реестр уборки 2026'!Z:Z,J9,'Реестр уборки 2026'!G:G)/1000, ) -> 246.5 | L9: =IFERROR(AVERAGEIF('Реестр уборки 2026'!Z:Z,'Данные 2026'!J9,'Реестр уборки 2026'!C:C),) -> 49.55 | M9: нет данных
A10: ПЛАН, т | I10: 7 | J10: =J9+1 -> 46182 | K10: =IFERROR(SUMIF('Реестр уборки 2026'!Z:Z,J10,'Реестр уборки 2026'!G:G)/1000, ) -> 309.69 | L10: =AVERAGEIF('Реестр уборки 2026'!Z88:Z109,'Данные 2026'!J10,'Реестр уборки 2026'!C88:C109) -> 53.272727 | M10: нет данных
A11: ФАКТ, т | I11: 8 | J11: =J10+1 -> 46183 | M11: нет данных
E12: =SUM(E4:E11) -> 9535.8 | F12: =SUM(F4:F11) -> 1356.3 | G12: =IFERROR(F12/E12, ) -> 0.14223243 | I12: 9 | J12: =J11+1 -> 46184 | M12: нет данных
A13: 2 | D13: 6 | I13: 10 | J13: =J12+1 -> 46185 | M13: нет данных
A14: Площадь уборки | D14: Выполнение плана по сбору | F14: Урожайность, т/га | G14: Вал, т | I14: 11 | J14: =J13+1 -> 46186 | M14: нет данных
A15: ПЛАН, га | B15: =F59 -> 1907.16 | D15: 2019 | F15: 3.3 | G15: 6813 | I15: 12 | J15: =J14+1 -> 46187 | M15: нет данных
A16: ФАКТ, га | B16: =G59 -> 235 | D16: 2020 | F16: 4.6 | G16: 12761 | I16: 13 | J16: =J15+1 -> 46188 | M16: нет данных
A17: Остаток, га | B17: =B15-B16 -> 1672.16 | D17: 2021 | F17: 4.2 | G17: 10161 | I17: 14 | J17: =J16+1 -> 46189 | M17: нет данных
A18: Исполнение плана, % | B18: =B16/B15 -> 0.12321987 | D18: 2022 | F18: 3 | G18: 6505 | I18: 15 | J18: =J17+1 -> 46190 | M18: нет данных
A19: Убрали на зерно | D19: 2023 | F19: 5.6 | G19: 6656 | I19: 16 | J19: =J18+1 -> 46191 | M19: нет данных
A20: ОСТАВИЛИ | D20: 2024 | F20: 2.7 | G20: 4371.9 | I20: 17 | J20: =J19+1 -> 46192 | M20: нет данных
A21: 3.1 | D21: 2025 | F21: 4.7835642 | G21: 7098.14 | I21: 18 | J21: =J20+1 -> 46193 | M21: нет данных
A22: Урожайность физ. вес. | D22: 2026 | F22: =B24 -> 5.7714894 | G22: =F12 -> 1356.3 | I22: 19 | J22: =J21+1 -> 46194 | M22: нет данных
A23: ПЛАН, т/га | B23: =IFERROR(B4/B15, ) -> 5 | I23: 20 | J23: =J22+1 -> 46195 | M23: нет данных
A24: ФАКТ, т/га | B24: =IFERROR(B5/B16, ) -> 5.7714894 | I24: 21 | J24: =J23+1 -> 46196 | M24: нет данных
D25: 7 | I25: 22 | J25: =J24+1 -> 46197 | M25: нет данных
A26: 3.2 | D26: Распределение сырья по финометру | F26: Вес, т | G26: Доля, % | I26: 23 | J26: =J25+1 -> 46198 | M26: нет данных
A27: Урожайность зач. вес. | C27: до 40 | D27: до 40 | F27: =SUMIF('Реестр уборки 2026'!AC:AC,Таблица111[[#This Row],[Распределение сырья по финометру]],'Реестр уборки 2026'!G:G)/1000 -> 0 | G27: =IFERROR(F27/$F$33, ) -> 0 | I27: 24 | J27: =J26+1 -> 46199 | M27: нет данных
A28: ПЛАН, т/га | B28: =IFERROR(B10/B15, 0) -> 0 | C28: 40-62 | D28: 40-52 | F28: =SUMIF('Реестр уборки 2026'!AC:AC,Таблица111[[#This Row],[Распределение сырья по финометру]],'Реестр уборки 2026'!G:G)/1000 -> 787.55 | G28: =IFERROR(F28/$F$33, ) -> 0.58066062 | I28: 25 | J28: =J27+1 -> 46200 | M28: нет данных
A29: ФАКТ, т/га | B29: =IFERROR(B11/B16, 0) -> 0 | C29: 63-66 | D29: 53-63 | F29: =SUMIF('Реестр уборки 2026'!AC:AC,Таблица111[[#This Row],[Распределение сырья по финометру]],'Реестр уборки 2026'!G:G)/1000 -> 509.69 | G29: =IFERROR(F29/$F$33, ) -> 0.37579444 | I29: 26 | J29: =J28+1 -> 46201 | M29: нет данных
C30: 67-85 | D30: 64-66 | F30: =SUMIF('Реестр уборки 2026'!AC:AC,Таблица111[[#This Row],[Распределение сырья по финометру]],'Реестр уборки 2026'!G:G)/1000 -> 0 | G30: =IFERROR(F30/$F$33, ) -> 0 | I30: 27 | J30: =J29+1 -> 46202 | M30: нет данных
D31: 67-85 | F31: =SUMIF('Реестр уборки 2026'!AC:AC,Таблица111[[#This Row],[Распределение сырья по финометру]],'Реестр уборки 2026'!G:G)/1000 -> 0 | G31: =IFERROR(F31/$F$33, ) -> 0 | I31: 28 | J31: =J30+1 -> 46203 | M31: нет данных
A32: 4 | D32: нет данных | F32: =SUMIF('Реестр уборки 2026'!AC:AC,Таблица111[[#This Row],[Распределение сырья по финометру]],'Реестр уборки 2026'!G:G)/1000 -> 59.06 | G32: =IFERROR(F32/$F$33, ) -> 0.043544938 | I32: 29 | J32: =J31+1 -> 46204 | M32: нет данных
A33: Информация по сырью | F33: =SUM(F27:F32) -> 1356.3 | G33: =SUM(G27:G32) -> 1 | I33: 30 | J33: =J32+1 -> 46205 | M33: нет данных
A34: Переработка | B34: =B37-B35-B36 -> 1297.24 | I34: 31 | J34: =J33+1 -> 46206 | M34: нет данных
A35: Утилизация | B35: 0 | I35: 32 | J35: =J34+1 -> 46207 | M35: нет данных
A36: Реализация | B36: =59060/1000 -> 59.06 | C36: 0 | D36: - реализовано по документам отгрузки (зач вес) | I36: 33 | J36: =J35+1 -> 46208 | M36: нет данных
A37: Собственное сырье | B37: =F12 -> 1356.3 | I37: 34 | J37: =J36+1 -> 46209 | M37: нет данных
A38: Закупка | B38: 0 | I38: 35 | J38: =J37+1 -> 46210 | M38: нет данных
I39: 36 | J39: =J38+1 -> 46211 | M39: нет данных
I40: 37 | J40: =J39+1 -> 46212 | M40: нет данных
I41: 38 | J41: =J40+1 -> 46213 | M41: нет данных
I42: 39 | J42: =J41+1 -> 46214 | M42: нет данных
I43: 40 | J43: =J42+1 -> 46215 | M43: нет данных
I44: 41 | J44: =J43+1 -> 46216 | M44: нет данных
I45: 42 | J45: =J44+1 -> 46217 | M45: нет данных
I46: 43 | J46: =J45+1 -> 46218 | M46: нет данных
I47: 44 | J47: =J46+1 -> 46219 | M47: нет данных
I48: 45 | J48: =J47+1 -> 46220 | M48: нет данных
K49: =SUM(K4:K48) -> 1356.3
A54: Культура | B54: Орошение | C54: ПЛАН, т | D54: ФАКТ, т | E54: Исполнение плана по валу, % | F54: ПЛАН, га | G54: ФАКТ, га | H54: Исполнение плана по площади, % | I54: Урожайность, т/га
A55: ГРК (богара) | B55: богара | C55: =Таблица413[[#This Row],[ПЛАН, га]]*5 -> 3890 | D55: =SUMIF('Реестр уборки 2026'!W:W,Таблица413[[#This Row],[Культура]],'Реестр уборки 2026'!G:G)/1000 -> 1356.3 | E55: =IFERROR(D55/C55, ) -> 0.34866324 | F55: 778 | G55: =SUMIF('Реестр уборки 2026'!W:W,Таблица413[[#This Row],[Культура]],'Реестр уборки 2026'!V:V) -> 235 | H55: =IFERROR(G55/F55, ) -> 0.30205656 | I55: =IFERROR(Таблица413[[#This Row],[ФАКТ, т]]/Таблица413[[#This Row],[ФАКТ, га]],) -> 5.7714894
A56: ГРК (полив) | B56: полив | C56: 2100 | D56: =SUMIF('Реестр уборки 2026'!W:W,Таблица413[[#This Row],[Культура]],'Реестр уборки 2026'!G:G)/1000 -> 0 | E56: =IFERROR(D56/C56, ) -> 0 | F56: 420 | G56: =SUMIF('Реестр уборки 2026'!W:W,Таблица413[[#This Row],[Культура]],'Реестр уборки 2026'!V:V) -> 0 | H56: =IFERROR(G56/F56, ) -> 0 | I56: =IFERROR(Таблица413[[#This Row],[ФАКТ, т]]/Таблица413[[#This Row],[ФАКТ, га]],) -> 0
A57: Агролидер (полив) | B57: полив | C57: 1345 | D57: =SUMIF('Реестр уборки 2026'!W:W,Таблица413[[#This Row],[Культура]],'Реестр уборки 2026'!G:G)/1000 -> 0 | E57: =IFERROR(D57/C57, ) -> 0 | F57: 269 | G57: =SUMIF('Реестр уборки 2026'!W:W,Таблица413[[#This Row],[Культура]],'Реестр уборки 2026'!V:V) -> 0 | H57: =IFERROR(G57/F57, ) -> 0 | I57: =IFERROR(Таблица413[[#This Row],[ФАКТ, т]]/Таблица413[[#This Row],[ФАКТ, га]],) -> 0
A58: Колос (полив) | B58: полив | C58: 2200.8 | D58: =SUMIF('Реестр уборки 2026'!W:W,Таблица413[[#This Row],[Культура]],'Реестр уборки 2026'!G:G)/1000 -> 0 | E58: =IFERROR(D58/C58, ) -> 0 | F58: 440.16 | G58: =SUMIF('Реестр уборки 2026'!W:W,Таблица413[[#This Row],[Культура]],'Реестр уборки 2026'!V:V) -> 0 | H58: =IFERROR(G58/F58, ) -> 0 | I58: =IFERROR(Таблица413[[#This Row],[ФАКТ, т]]/Таблица413[[#This Row],[ФАКТ, га]],) -> 0
C59: =SUBTOTAL(109,C55:C58) -> 9535.8 | D59: =SUBTOTAL(109,D55:D58) -> 1356.3 | E59: =D59/C59 -> 0.14223243 | F59: =SUBTOTAL(109,F55:F58) -> 1907.16 | G59: =SUBTOTAL(109,G55:G58) -> 235 | H59: =IFERROR(G59/F59, ) -> 0.12321987 | I59: =D59/G59 -> 5.7714894
A63: Культура | B63: ПЛАН, т | C63: ФАКТ, т | D63: ПЛАН, га | E63: ФАКТ, га
A64: Агролидер (полив) | B64: 1345 | C64: 0 | D64: 269 | E64: 0
A65: ГРК (богара) | B65: 3890 | C65: 1356.3 | D65: 778 | E65: 235
A66: ГРК (полив) | B66: 2100 | C66: 0 | D66: 420 | E66: 0
A67: Колос (полив) | B67: 2200.8 | C67: 0 | D67: 440.16 | E67: 0
A68: Итог Результат | B68: 9535.8 | C68: 1356.3 | D68: 1907.16 | E68: 235

Sheet ОТЧЕТ 2025
B2: ОПЕРАТИВНАЯ ИНФОРМАЦИЯ ПО СБОРУ ГОРОШКА (СЕЗОН 2025 г.)
B24: МАЙ
B25: Пн | C25: Вт | D25: Ср | E25: Чт | F25: Пт | G25: Сб | H25: Вс
C26: 45804 | D26: =C26+1 -> 45805 | E26: =D26+1 -> 45806 | F26: =E26+1 -> 45807 | G26: =F26+1 -> 45808
B27: ИЮНЬ
H28: =G26+1 -> 45809
B29: =H28+1 -> 45810 | C29: =B29+1 -> 45811 | D29: =C29+1 -> 45812 | E29: =D29+1 -> 45813 | F29: =E29+1 -> 45814 | G29: =F29+1 -> 45815 | H29: =G29+1 -> 45816
B30: =H29+1 -> 45817 | C30: =B30+1 -> 45818 | D30: =C30+1 -> 45819 | E30: =D30+1 -> 45820 | F30: =E30+1 -> 45821 | G30: =F30+1 -> 45822 | H30: =G30+1 -> 45823
B31: =H30+1 -> 45824 | C31: =B31+1 -> 45825 | D31: =C31+1 -> 45826 | E31: =D31+1 -> 45827 | F31: =E31+1 -> 45828 | G31: =F31+1 -> 45829 | H31: =G31+1 -> 45830
B32: =H31+1 -> 45831 | C32: =B32+1 -> 45832 | D32: =C32+1 -> 45833 | E32: =D32+1 -> 45834 | F32: =E32+1 -> 45835 | G32: =F32+1 -> 45836 | H32: =G32+1 -> 45837
B33: =H32+1 -> 45838
B34: ИЮЛЬ
C35: =B33+1 -> 45839 | D35: =C35+1 -> 45840 | E35: =D35+1 -> 45841 | F35: =E35+1 -> 45842 | G35: =F35+1 -> 45843 | H35: =G35+1 -> 45844
B36: =H35+1 -> 45845 | C36: =B36+1 -> 45846 | D36: =C36+1 -> 45847 | E36: =D36+1 -> 45848 | F36: =E36+1 -> 45849 | G36: =F36+1 -> 45850 | H36: =G36+1 -> 45851
B38: День уборки - | E38: 45

Sheet ОТЧЕТ 2024
B2: ОПЕРАТИВНАЯ ИНФОРМАЦИЯ ПО СБОРУ ГОРОШКА (СЕЗОН 2024 г.)
B21: МАЙ
B22: Пн | C22: Вт | D22: Ср | E22: Чт | F22: Пт | G22: Сб | H22: Вс
F23: 45429 | G23: 45430 | H23: 45431
B24: =H23+1 -> 45432 | C24: =B24+1 -> 45433 | D24: =C24+1 -> 45434 | E24: =D24+1 -> 45435 | F24: =E24+1 -> 45436 | G24: =F24+1 -> 45437 | H24: =G24+1 -> 45438
B25: =H24+1 -> 45439 | C25: =B25+1 -> 45440 | D25: =C25+1 -> 45441 | E25: =D25+1 -> 45442 | F25: =E25+1 -> 45443
B26: ИЮНЬ
G27: 45444 | H27: =G27+1 -> 45445
B28: =H27+1 -> 45446 | C28: =B28+1 -> 45447 | D28: =C28+1 -> 45448 | E28: =D28+1 -> 45449 | F28: =E28+1 -> 45450 | G28: =F28+1 -> 45451 | H28: =G28+1 -> 45452
B29: =H28+1 -> 45453 | C29: =B29+1 -> 45454 | D29: =C29+1 -> 45455 | E29: =D29+1 -> 45456 | F29: =E29+1 -> 45457 | G29: =F29+1 -> 45458 | H29: =G29+1 -> 45459
B30: =H29+1 -> 45460 | C30: =B30+1 -> 45461 | D30: =C30+1 -> 45462 | E30: =D30+1 -> 45463 | F30: =E30+1 -> 45464 | G30: =F30+1 -> 45465 | H30: =G30+1 -> 45466
B31: =H30+1 -> 45467 | C31: =B31+1 -> 45468 | D31: =C31+1 -> 45469 | E31: =D31+1 -> 45470 | F31: =E31+1 -> 45471 | G31: =F31+1 -> 45472 | H31: =G31+1 -> 45473
B32: ИЮЛЬ
B33: =H31+1 -> 45474 | C33: =B33+1 -> 45475 | D33: =C33+1 -> 45476 | E33: =D33+1 -> 45477 | F33: =E33+1 -> 45478 | G33: =F33+1 -> 45479 | H33: =G33+1 -> 45480
B34: =H33+1 -> 45481 | C34: =B34+1 -> 45482 | D34: =C34+1 -> 45483 | E34: =D34+1 -> 45484 | F34: =E34+1 -> 45485 | G34: =F34+1 -> 45486 | H34: =G34+1 -> 45487
B35: =H34+1 -> 45488 | C35: =B35+1 -> 45489 | D35: =C35+1 -> 45490 | E35: =D35+1 -> 45491 | F35: =E35+1 -> 45492 | G35: =F35+1 -> 45493 | H35: =G35+1 -> 45494
B36: =H35+1 -> 45495 | C36: =B36+1 -> 45496 | D36: =C36+1 -> 45497 | E36: =D36+1 -> 45498 | F36: =E36+1 -> 45499 | G36: =F36+1 -> 45500 | H36: =G36+1 -> 45501
B37: =H36+1 -> 45502 | C37: =B37+1 -> 45503 | D37: =C37+1 -> 45504

Sheet Данные 2025
A2: 1.1 | B2: Выборка по КА, орошению | D2: 5 | I2: 8
A3: Валовый сбор | D3: Выполнение плана по сбору | E3: ПЛАН, т | F3: ФАКТ, т | G3: Исполнение плана, % | I3: Ежедневные показатели | K3: Сбор, т | L3: Значение спелости | M3: Финометр
A4: ПЛАН, т | B4: =C63 -> 6798.045 | D4: Учхоз Кубань (богара) | E4: 1157.4 | F4: =D55 -> 1320.13 | G4: =IFERROR(F4/E4, ) -> 1.1405996 | I4: 1 | J4: 45804 | K4: =SUMIF('Реестр уборки 2025'!Z:Z,J4,'Реестр уборки 2025'!G:G)/1000 -> 71.35 | L4: =IFERROR(AVERAGEIF('Реестр уборки 2025'!Z:Z,'Данные 2025'!J4,'Реестр уборки 2025'!C:C),) -> 41.333333 | M4: 40-52
A5: ФАКТ, т | B5: =D63 -> 7098.14 | D5: ГРК собственные семена (богара) | E5: 910 | F5: =D56 -> 503.65 | G5: =IFERROR(F5/E5, ) -> 0.55346154 | I5: 2 | J5: 45805 | K5: =SUMIF('Реестр уборки 2025'!Z:Z,J5,'Реестр уборки 2025'!G:G)/1000 -> 98.78 | L5: =IFERROR(AVERAGEIF('Реестр уборки 2025'!Z:Z,'Данные 2025'!J5,'Реестр уборки 2025'!C:C),) -> 44 | M5: 40-52
A6: Исполнение плана, % | B6: =E63 -> 1.0441443 | D6: ГРК демо (богара) | E6: 136.5 | F6: =D57 -> 91.8 | G6: =IFERROR(F6/E6, ) -> 0.67252747 | I6: 3 | J6: 45806 | K6: =SUMIF('Реестр уборки 2025'!Z:Z,J6,'Реестр уборки 2025'!G:G)/1000 -> 10.74 | L6: =IFERROR(AVERAGEIF('Реестр уборки 2025'!Z:Z,'Данные 2025'!J6,'Реестр уборки 2025'!C:C),) -> 42.5 | M6: 40-52
D7: ГРК (богара) | E7: 936.2 | F7: =D58 -> 769.25 | G7: =IFERROR(F7/E7, ) -> 0.82167272 | I7: 4 | J7: 45807
A8: 1.2 | D8: Братковский (полив) | E8: 765 | F8: =D59 -> 842.08 | G8: =IFERROR(F8/E8, ) -> 1.1007582 | I8: 5 | J8: 45808 | K8: =SUMIF('Реестр уборки 2025'!Z:Z,J8,'Реестр уборки 2025'!G:G)/1000 -> 55.61 | L8: =IFERROR(AVERAGEIF('Реестр уборки 2025'!Z:Z,'Данные 2025'!J8,'Реестр уборки 2025'!C:C),) -> 45.625 | M8: 40-52
A9: Зачетный вес | D9: Братковский закупка (полив) | E9: 522.325 | F9: =D60 -> 561.3 | G9: =IFERROR(F9/E9, ) -> 1.0746183 | I9: 6 | J9: 45809 | K9: =SUMIF('Реестр уборки 2025'!Z:Z,J9,'Реестр уборки 2025'!G:G)/1000 -> 206.19 | L9: =IFERROR(AVERAGEIF('Реестр уборки 2025'!Z:Z,'Данные 2025'!J9,'Реестр уборки 2025'!C:C),) -> 51.588235 | M9: 40-52
A10: ПЛАН, т | D10: Агролидер (полив) | E10: 586.5 | F10: =D61 -> 1017.73 | G10: =IFERROR(F10/E10, ) -> 1.73526 | I10: 7 | J10: 45810 | K10: =SUMIF('Реестр уборки 2025'!Z:Z,J10,'Реестр уборки 2025'!G:G)/1000 -> 198.3 | L10: =IFERROR(AVERAGEIF('Реестр уборки 2025'!Z:Z,'Данные 2025'!J10,'Реестр уборки 2025'!C:C),) -> 52.9375 | M10: 53-63
A11: ФАКТ, т | D11: Колос (полив) | E11: 1784.12 | F11: =D62 -> 1992.2 | G11: =IFERROR(F11/E11, ) -> 1.1166289 | I11: 8 | J11: 45811 | K11: =SUMIF('Реестр уборки 2025'!Z:Z,J11,'Реестр уборки 2025'!G:G)/1000 -> 285.91 | L11: =IFERROR(AVERAGEIF('Реестр уборки 2025'!Z:Z,'Данные 2025'!J11,'Реестр уборки 2025'!C:C),) -> 54.666667 | M11: 53-63
E12: =SUM(E4:E11) -> 6798.045 | F12: =SUM(F4:F11) -> 7098.14 | G12: =IFERROR(F12/E12, ) -> 1.0441443 | I12: 9 | J12: 45812 | K12: =SUMIF('Реестр уборки 2025'!Z:Z,J12,'Реестр уборки 2025'!G:G)/1000 -> 339.79 | L12: =IFERROR(AVERAGEIF('Реестр уборки 2025'!Z:Z,'Данные 2025'!J12,'Реестр уборки 2025'!C:C),) -> 57.666667 | M12: 53-63
A13: 2 | D13: 6 | I13: 10 | J13: 45813 | K13: =SUMIF('Реестр уборки 2025'!Z:Z,J13,'Реестр уборки 2025'!G:G)/1000 -> 240.45 | L13: =IFERROR(AVERAGEIF('Реестр уборки 2025'!Z:Z,'Данные 2025'!J13,'Реестр уборки 2025'!C:C),) -> 53.473684 | M13: 53-63
A14: Площадь уборки | D14: Выполнение плана по сбору | F14: Урожайность, т/га | G14: Вал, т | I14: 11 | J14: 45814 | K14: =SUMIF('Реестр уборки 2025'!Z:Z,J14,'Реестр уборки 2025'!G:G)/1000 -> 417.43 | L14: =IFERROR(AVERAGEIF('Реестр уборки 2025'!Z:Z,'Данные 2025'!J14,'Реестр уборки 2025'!C:C),) -> 57.228571 | M14: 53-63
A15: ПЛАН, га | B15: =F63 -> 1675.8 | D15: 2019 | F15: 3.3 | G15: 6813 | I15: 12 | J15: 45815 | K15: =SUMIF('Реестр уборки 2025'!Z:Z,J15,'Реестр уборки 2025'!G:G)/1000 -> 163.35 | L15: =IFERROR(AVERAGEIF('Реестр уборки 2025'!Z:Z,'Данные 2025'!J15,'Реестр уборки 2025'!C:C),) -> 60.933333 | M15: 53-63
A16: ФАКТ, га | B16: =G63 -> 1483.8601 | D16: 2020 | F16: 4.6 | G16: 12761 | I16: 13 | J16: 45816 | K16: =SUMIF('Реестр уборки 2025'!Z:Z,J16,'Реестр уборки 2025'!G:G)/1000 -> 233.26 | L16: =IFERROR(AVERAGEIF('Реестр уборки 2025'!Z:Z,'Данные 2025'!J16,'Реестр уборки 2025'!C:C),) -> 60.869565 | M16: 53-63
A17: Остаток, га | B17: =B15-B16 -> 191.93991 | D17: 2021 | F17: 4.2 | G17: 10161 | I17: 14 | J17: 45817 | K17: =SUMIF('Реестр уборки 2025'!Z:Z,J17,'Реестр уборки 2025'!G:G)/1000 -> 100.73 | L17: =IFERROR(AVERAGEIF('Реестр уборки 2025'!Z:Z,'Данные 2025'!J17,'Реестр уборки 2025'!C:C),) -> 68.1 | M17: 67-85
A18: Исполнение плана, % | B18: =B16/B15 -> 0.88546371 | D18: 2022 | F18: 3 | G18: 6505 | I18: 15 | J18: 45818 | K18: =SUMIF('Реестр уборки 2025'!Z:Z,J18,'Реестр уборки 2025'!G:G)/1000 -> 243.58 | L18: =IFERROR(AVERAGEIF('Реестр уборки 2025'!Z:Z,'Данные 2025'!J18,'Реестр уборки 2025'!C:C),) -> 62.541667 | M18: 53-63
A19: Убрали на зерно | B19: 71 | D19: 2023 | F19: 5.6 | G19: 6656 | I19: 16 | J19: 45819 | K19: =SUMIF('Реестр уборки 2025'!Z:Z,J19,'Реестр уборки 2025'!G:G)/1000 -> 127.99 | L19: =IFERROR(AVERAGEIF('Реестр уборки 2025'!Z:Z,'Данные 2025'!J19,'Реестр уборки 2025'!C:C),) -> 65.090909 | M19: 64-66
A20: ОСТАВИЛИ | B20: 120.96957 | D20: 2024 | F20: 2.7 | G20: 4371.9 | I20: 17 | J20: 45820 | K20: =SUMIF('Реестр уборки 2025'!Z:Z,J20,'Реестр уборки 2025'!G:G)/1000 -> 302.41 | L20: =IFERROR(AVERAGEIF('Реестр уборки 2025'!Z:Z,'Данные 2025'!J20,'Реестр уборки 2025'!C:C),) -> 54.217391 | M20: 53-63
A21: 3.1 | D21: 2025 | F21: =B24 -> 4.7835642 | G21: =F12 -> 7098.14 | I21: 18 | J21: 45821 | K21: =SUMIF('Реестр уборки 2025'!Z:Z,J21,'Реестр уборки 2025'!G:G)/1000 -> 251.82 | L21: =IFERROR(AVERAGEIF('Реестр уборки 2025'!Z:Z,'Данные 2025'!J21,'Реестр уборки 2025'!C:C),) -> 53.583333 | M21: 53-63
A22: Урожайность физ. вес. | I22: 19 | J22: 45822 | K22: =SUMIF('Реестр уборки 2025'!Z:Z,J22,'Реестр уборки 2025'!G:G)/1000 -> 260.19 | L22: =IFERROR(AVERAGEIF('Реестр уборки 2025'!Z:Z,'Данные 2025'!J22,'Реестр уборки 2025'!C:C),) -> 63.15 | M22: 53-63
A23: ПЛАН, т/га | B23: =IFERROR(B4/B15, ) -> 4.0565968 | I23: 20 | J23: 45823 | K23: =SUMIF('Реестр уборки 2025'!Z:Z,J23,'Реестр уборки 2025'!G:G)/1000 -> 251.63 | L23: =IFERROR(AVERAGEIF('Реестр уборки 2025'!Z:Z,'Данные 2025'!J23,'Реестр уборки 2025'!C:C),) -> 67.095238 | M23: 67-85
A24: ФАКТ, т/га | B24: =IFERROR(B5/B16, ) -> 4.7835642 | I24: 21 | J24: 45824 | K24: =SUMIF('Реестр уборки 2025'!Z:Z,J24,'Реестр уборки 2025'!G:G)/1000 -> 182.08 | L24: =IFERROR(AVERAGEIF('Реестр уборки 2025'!Z:Z,'Данные 2025'!J24,'Реестр уборки 2025'!C:C),) -> 61.375 | M24: 53-63
D25: 7 | I25: 22 | J25: 45825 | K25: =SUMIF('Реестр уборки 2025'!Z:Z,J25,'Реестр уборки 2025'!G:G)/1000 -> 231.15 | L25: =IFERROR(AVERAGEIF('Реестр уборки 2025'!Z:Z,'Данные 2025'!J25,'Реестр уборки 2025'!C:C),) -> 58.117647 | M25: 53-63
A26: 3.2 | D26: Распределение сырья по финометру | F26: Вес, т | G26: Доля, % | I26: 23 | J26: 45826 | K26: =SUMIF('Реестр уборки 2025'!Z:Z,J26,'Реестр уборки 2025'!G:G)/1000 -> 157.45 | L26: =IFERROR(AVERAGEIF('Реестр уборки 2025'!Z:Z,'Данные 2025'!J26,'Реестр уборки 2025'!C:C),) -> 55.5 | M26: 53-63
A27: Урожайность зач. вес. | C27: до 40 | D27: до 40 | F27: =SUMIF('Реестр уборки 2025'!AC:AC,Таблица1[[#This Row],[Распределение сырья по финометру]],'Реестр уборки 2025'!G:G)/1000 -> 15.6 | G27: =IFERROR(F27/$F$33, ) -> 0.0021977588 | I27: 24 | J27: 45827 | K27: =SUMIF('Реестр уборки 2025'!Z:Z,J27,'Реестр уборки 2025'!G:G)/1000 -> 304.92 | L27: =IFERROR(AVERAGEIF('Реестр уборки 2025'!Z:Z,'Данные 2025'!J27,'Реестр уборки 2025'!C:C),) -> 62.826087 | M27: 53-63
A28: ПЛАН, т/га | B28: =IFERROR(B10/B15, 0) -> 0 | C28: 40-62 | D28: 40-52 | F28: =SUMIF('Реестр уборки 2025'!AC:AC,Таблица1[[#This Row],[Распределение сырья по финометру]],'Реестр уборки 2025'!G:G)/1000 -> 1875.175 | G28: =IFERROR(F28/$F$33, ) -> 0.26417836 | I28: 25 | J28: 45828 | K28: =SUMIF('Реестр уборки 2025'!Z:Z,J28,'Реестр уборки 2025'!G:G)/1000 -> 252.94 | L28: =IFERROR(AVERAGEIF('Реестр уборки 2025'!Z:Z,'Данные 2025'!J28,'Реестр уборки 2025'!C:C),) -> 64.526316 | M28: 64-66
A29: ФАКТ, т/га | B29: =IFERROR(B11/B16, 0) -> 0 | C29: 63-66 | D29: 53-63 | F29: =SUMIF('Реестр уборки 2025'!AC:AC,Таблица1[[#This Row],[Распределение сырья по финометру]],'Реестр уборки 2025'!G:G)/1000 -> 3153.785 | G29: =IFERROR(F29/$F$33, ) -> 0.44431147 | I29: 26 | J29: 45829 | K29: =SUMIF('Реестр уборки 2025'!Z:Z,J29,'Реестр уборки 2025'!G:G)/1000 -> 123.3 | L29: =IFERROR(AVERAGEIF('Реестр уборки 2025'!Z:Z,'Данные 2025'!J29,'Реестр уборки 2025'!C:C),) -> 60 | M29: 53-63
C30: 67-85 | D30: 64-66 | F30: =SUMIF('Реестр уборки 2025'!AC:AC,Таблица1[[#This Row],[Распределение сырья по финометру]],'Реестр уборки 2025'!G:G)/1000 -> 570.75 | G30: =IFERROR(F30/$F$33, ) -> 0.080408389 | I30: 27 | J30: 45830 | K30: =SUMIF('Реестр уборки 2025'!Z:Z,J30,'Реестр уборки 2025'!G:G)/1000 -> 272.42 | L30: =IFERROR(AVERAGEIF('Реестр уборки 2025'!Z:Z,'Данные 2025'!J30,'Реестр уборки 2025'!C:C),) -> 49.4 | M30: 40-52
D31: 67-85 | F31: =SUMIF('Реестр уборки 2025'!AC:AC,Таблица1[[#This Row],[Распределение сырья по финометру]],'Реестр уборки 2025'!G:G)/1000 -> 1443.44 | G31: =IFERROR(F31/$F$33, ) -> 0.20335468 | I31: 28 | J31: 45831 | K31: =SUMIF('Реестр уборки 2025'!Z:Z,J31,'Реестр уборки 2025'!G:G)/1000 -> 109.28 | L31: =IFERROR(AVERAGEIF('Реестр уборки 2025'!Z:Z,'Данные 2025'!J31,'Реестр уборки 2025'!C:C),) -> 52.875 | M31: 53-63
A32: 4 | D32: нет данных | F32: =SUMIF('Реестр уборки 2025'!AC:AC,Таблица1[[#This Row],[Распределение сырья по финометру]],'Реестр уборки 2025'!G:G)/1000 -> 39.39 | G32: =IFERROR(F32/$F$33, ) -> 0.0055493411 | I32: 29 | J32: 45832 | K32: =SUMIF('Реестр уборки 2025'!Z:Z,J32,'Реестр уборки 2025'!G:G)/1000 -> 200.28 | L32: =IFERROR(AVERAGEIF('Реестр уборки 2025'!Z:Z,'Данные 2025'!J32,'Реестр уборки 2025'!C:C),) -> 49.375 | M32: 40-52
A33: Информация по сырью | F33: =SUM(F27:F32) -> 7098.14 | G33: =SUM(G27:G32) -> 1 | I33: 30 | J33: 45833 | K33: =SUMIF('Реестр уборки 2025'!Z:Z,J33,'Реестр уборки 2025'!G:G)/1000 -> 19.23 | L33: =IFERROR(AVERAGEIF('Реестр уборки 2025'!Z:Z,'Данные 2025'!J33,'Реестр уборки 2025'!C:C),) -> 48.5 | M33: 40-52
A34: Переработка | B34: =B37-B35-B36 -> 6329.53 | I34: 31 | J34: 45834
A35: Утилизация | B35: =(108250+8280+39390)/1000 -> 155.92 | I35: 32 | J35: 45835 | K35: =SUMIF('Реестр уборки 2025'!Z:Z,J35,'Реестр уборки 2025'!G:G)/1000 -> 17.56 | L35: =IFERROR(AVERAGEIF('Реестр уборки 2025'!Z:Z,'Данные 2025'!J35,'Реестр уборки 2025'!C:C),) -> 46 | M35: 40-52
A36: Реализация | B36: 612.69 | C36: 542.3951 | D36: - реализовано по документам отгрузки (ранее было указано в отчете) | I36: 33 | J36: 45836 | K36: =SUMIF('Реестр уборки 2025'!Z:Z,J36,'Реестр уборки 2025'!G:G)/1000 -> 43.19 | L36: =IFERROR(AVERAGEIF('Реестр уборки 2025'!Z:Z,'Данные 2025'!J36,'Реестр уборки 2025'!C:C),) -> 48 | M36: 40-52
A37: Собственное сырье | B37: =F12 -> 7098.14 | I37: 34 | J37: 45837 | K37: =SUMIF('Реестр уборки 2025'!Z:Z,J37,'Реестр уборки 2025'!G:G)/1000 -> 71.97 | L37: =IFERROR(AVERAGEIF('Реестр уборки 2025'!Z:Z,'Данные 2025'!J37,'Реестр уборки 2025'!C:C),) -> 48.444444 | M37: 40-52
A38: Закупка | B38: 0 | C38: не указана закупка Брактовского, так как она была запланирована в конвейере | I38: 35 | J38: 45838 | K38: =SUMIF('Реестр уборки 2025'!Z:Z,J38,'Реестр уборки 2025'!G:G)/1000 -> 25.63 | L38: =IFERROR(AVERAGEIF('Реестр уборки 2025'!Z:Z,'Данные 2025'!J38,'Реестр уборки 2025'!C:C),) -> 52 | M38: 40-52
I39: 36 | J39: 45839 | K39: =SUMIF('Реестр уборки 2025'!Z:Z,J39,'Реестр уборки 2025'!G:G)/1000 -> 176.53 | L39: =IFERROR(AVERAGEIF('Реестр уборки 2025'!Z:Z,'Данные 2025'!J39,'Реестр уборки 2025'!C:C),) -> 54 | M39: 53-63
I40: 37 | J40: 45840 | K40: =SUMIF('Реестр уборки 2025'!Z:Z,J40,'Реестр уборки 2025'!G:G)/1000 -> 192.78 | L40: =IFERROR(AVERAGEIF('Реестр уборки 2025'!Z:Z,'Данные 2025'!J40,'Реестр уборки 2025'!C:C),) -> 52.357143 | M40: 40-52
I41: 38 | J41: 45841 | K41: =SUMIF('Реестр уборки 2025'!Z:Z,J41,'Реестр уборки 2025'!G:G)/1000 -> 204.08 | L41: =IFERROR(AVERAGEIF('Реестр уборки 2025'!Z:Z,'Данные 2025'!J41,'Реестр уборки 2025'!C:C),) -> 55.6875 | M41: 53-63
I42: 39 | J42: 45842 | K42: =SUMIF('Реестр уборки 2025'!Z:Z,J42,'Реестр уборки 2025'!G:G)/1000 -> 147.51 | L42: =IFERROR(AVERAGEIF('Реестр уборки 2025'!Z:Z,'Данные 2025'!J42,'Реестр уборки 2025'!C:C),) -> 61.363636 | M42: 53-63
I43: 40 | J43: 45843 | K43: =SUMIF('Реестр уборки 2025'!Z:Z,J43,'Реестр уборки 2025'!G:G)/1000 -> 163.17 | L43: =IFERROR(AVERAGEIF('Реестр уборки 2025'!Z:Z,'Данные 2025'!J43,'Реестр уборки 2025'!C:C),) -> 61.25 | M43: 53-63
I44: 41 | J44: 45844 | K44: =SUMIF('Реестр уборки 2025'!Z:Z,J44,'Реестр уборки 2025'!G:G)/1000 -> 120.94 | L44: =IFERROR(AVERAGEIF('Реестр уборки 2025'!Z:Z,'Данные 2025'!J44,'Реестр уборки 2025'!C:C),) -> 53.222222 | M44: 53-63
I45: 42 | J45: 45845
I46: 43 | J46: 45846 | K46: =SUMIF('Реестр уборки 2025'!Z:Z,J46,'Реестр уборки 2025'!G:G)/1000 -> 131.84 | L46: =IFERROR(AVERAGEIF('Реестр уборки 2025'!Z:Z,'Данные 2025'!J46,'Реестр уборки 2025'!C:C),) -> 67.1 | M46: 67-85
I47: 44 | J47: 45847 | K47: =SUMIF('Реестр уборки 2025'!Z:Z,J47,'Реестр уборки 2025'!G:G)/1000 -> 63.8 | L47: =IFERROR(AVERAGEIF('Реестр уборки 2025'!Z:Z,'Данные 2025'!J47,'Реестр уборки 2025'!C:C),) -> 71.4 | M47: 67-85
I48: 45 | J48: 45848 | K48: =SUMIF('Реестр уборки 2025'!Z:Z,J48,'Реестр уборки 2025'!G:G)/1000 -> 26.58 | L48: =IFERROR(AVERAGEIF('Реестр уборки 2025'!Z:Z,'Данные 2025'!J48,'Реестр уборки 2025'!C:C),) -> 70.5 | M48: 67-85
K49: =SUM(K4:K48) -> 7098.14
A54: Культура | B54: Орошение | C54: ПЛАН, т | D54: ФАКТ, т | E54: Исполнение плана по валу, % | F54: ПЛАН, га | G54: ФАКТ, га | H54: Исполнение плана по площади, % | I54: Урожайность, т/га
A55: Учхоз Кубань | B55: богара | C55: 1157.4 | D55: =SUMIF('Реестр уборки 2025'!W:W,'Реестр уборки 2025'!$W$3,'Реестр уборки 2025'!G:G)/1000 -> 1320.13 | E55: =IFERROR(D55/C55, ) -> 1.1405996 | F55: 257.2 | G55: =SUMIF('Реестр уборки 2025'!W:W,'Реестр уборки 2025'!$W$3,'Реестр уборки 2025'!V:V) -> 237.2438 | H55: =IFERROR(G55/F55, ) -> 0.92240982 | I55: =Таблица4[[#This Row],[ФАКТ, т]]/Таблица4[[#This Row],[ФАКТ, га]] -> 5.5644446
A56: ГРК собственные семена | B56: богара | C56: 910 | D56: =SUMIF('Реестр уборки 2025'!W:W,'Реестр уборки 2025'!$W$4,'Реестр уборки 2025'!G:G)/1000 -> 503.65 | E56: =IFERROR(D56/C56, ) -> 0.55346154 | F56: 260 | G56: =SUMIF('Реестр уборки 2025'!W:W,'Реестр уборки 2025'!$W$4,'Реестр уборки 2025'!V:V) -> 183.41255 | H56: =IFERROR(G56/F56, ) -> 0.70543288 | I56: =Таблица4[[#This Row],[ФАКТ, т]]/Таблица4[[#This Row],[ФАКТ, га]] -> 2.7459953
A57: ГРК демо | B57: богара | C57: 136.5 | D57: =SUMIF('Реестр уборки 2025'!W:W,'Реестр уборки 2025'!$W$181,'Реестр уборки 2025'!G:G)/1000 -> 91.8 | E57: =IFERROR(D57/C57, ) -> 0.67252747 | F57: 39 | G57: =SUMIF('Реестр уборки 2025'!W:W,'Реестр уборки 2025'!$W$181,'Реестр уборки 2025'!V:V) -> 31 | H57: =IFERROR(G57/F57, ) -> 0.79487179 | I57: =Таблица4[[#This Row],[ФАКТ, т]]/Таблица4[[#This Row],[ФАКТ, га]] -> 2.9612903
A58: ГРК | B58: богара | C58: 936.2 | D58: =SUMIF('Реестр уборки 2025'!W:W,'Реестр уборки 2025'!$W$86,'Реестр уборки 2025'!G:G)/1000 -> 769.25 | E58: =IFERROR(D58/C58, ) -> 0.82167272 | F58: 302 | G58: =SUMIF('Реестр уборки 2025'!W:W,'Реестр уборки 2025'!$W$109,'Реестр уборки 2025'!V:V) -> 246.59801 | H58: =IFERROR(G58/F58, ) -> 0.81654971 | I58: =Таблица4[[#This Row],[ФАКТ, т]]/Таблица4[[#This Row],[ФАКТ, га]] -> 3.1194493
A59: Братковский | B59: полив | C59: 765 | D59: =SUMIF('Реестр уборки 2025'!W:W,'Реестр уборки 2025'!$W$225,'Реестр уборки 2025'!G:G)/1000 -> 842.08 | E59: =IFERROR(D59/C59, ) -> 1.1007582 | F59: 180 | G59: =SUMIF('Реестр уборки 2025'!W:W,'Реестр уборки 2025'!$W$225,'Реестр уборки 2025'!V:V) -> 147.98974 | H59: =IFERROR(G59/F59, ) -> 0.82216523 | I59: =Таблица4[[#This Row],[ФАКТ, т]]/Таблица4[[#This Row],[ФАКТ, га]] -> 5.6901241
A60: Братковский закупка | B60: полив | C60: 522.325 | D60: =SUMIF('Реестр уборки 2025'!W:W,'Реестр уборки 2025'!$W$247,'Реестр уборки 2025'!G:G)/1000 -> 561.3 | E60: =IFERROR(D60/C60, ) -> 1.0746183 | F60: =122.9-2.9 -> 120 | G60: =SUMIF('Реестр уборки 2025'!W:W,'Реестр уборки 2025'!$W$247,'Реестр уборки 2025'!V:V) -> 120.02629 | H60: =IFERROR(G60/F60, ) -> 1.0002191 | I60: =Таблица4[[#This Row],[ФАКТ, т]]/Таблица4[[#This Row],[ФАКТ, га]] -> 4.6764754
A61: Агролидер | B61: полив | C61: 586.5 | D61: =SUMIF('Реестр уборки 2025'!W:W,'Реестр уборки 2025'!$W$275,'Реестр уборки 2025'!G:G)/1000 -> 1017.73 | E61: =IFERROR(D61/C61, ) -> 1.73526 | F61: 138 | G61: =SUMIF('Реестр уборки 2025'!W:W,'Реестр уборки 2025'!$W$275,'Реестр уборки 2025'!V:V) -> 138 | H61: =IFERROR(G61/F61, ) -> 1 | I61: =Таблица4[[#This Row],[ФАКТ, т]]/Таблица4[[#This Row],[ФАКТ, га]] -> 7.3748551
A62: Колос | B62: полив | C62: 1784.12 | D62: =SUMIF('Реестр уборки 2025'!W:W,'Реестр уборки 2025'!$W$431,'Реестр уборки 2025'!G:G)/1000 -> 1992.2 | E62: =IFERROR(D62/C62, ) -> 1.1166289 | F62: 379.6 | G62: =SUMIF('Реестр уборки 2025'!W:W,'Реестр уборки 2025'!$W$431,'Реестр уборки 2025'!V:V) -> 379.58969 | H62: =IFERROR(G62/F62, ) -> 0.99997283 | I62: =Таблица4[[#This Row],[ФАКТ, т]]/Таблица4[[#This Row],[ФАКТ, га]] -> 5.2482986
C63: =SUBTOTAL(109,C55:C62) -> 6798.045 | D63: =SUBTOTAL(109,D55:D62) -> 7098.14 | E63: =D63/C63 -> 1.0441443 | F63: =SUBTOTAL(109,F55:F62) -> 1675.8 | G63: =SUBTOTAL(109,G55:G62) -> 1483.8601 | H63: =IFERROR(G63/F63, ) -> 0.88546371 | I63: =D63/G63 -> 4.7835642
A66: Заголовки строк | B66: ПЛАН, т | C66: ФАКТ, т | D66: ПЛАН, га | E66: ФАКТ, га
A67: Агролидер | B67: 586.5 | C67: 1017.73 | D67: 138 | E67: 138
A68: Братковский | B68: 765 | C68: 842.08 | D68: 180 | E68: 147.98974
A69: Братковский закупка | B69: 522.325 | C69: 561.3 | D69: 120 | E69: 120.02629
A70: ГРК | B70: 936.2 | C70: 769.25 | D70: 302 | E70: 246.59801
A71: ГРК демо | B71: 136.5 | C71: 91.8 | D71: 39 | E71: 31
A72: ГРК собственные семена | B72: 910 | C72: 503.65 | D72: 260 | E72: 183.41255
A73: Колос | B73: 1784.12 | C73: 1992.2 | D73: 379.6 | E73: 379.58969
A74: Учхоз Кубань | B74: 1157.4 | C74: 1320.13 | D74: 257.2 | E74: 237.2438
A75: Итог Результат | B75: 6798.045 | C75: 7098.14 | D75: 1675.8 | E75: 1483.8601

Sheet СВОД по полям
A1: Контрагент | B1: Полив | C1: Номер поля | D1: Сорт | E1: Площадь сева | F1: Площадь уборки | G1: Остаток площади | H1: Закрытие, % | I1: Урожайность плановая, т/га | J1: Урожайность фактическая, т/га | K1: Валовый сбор плановый, т | L1: Валовый сбор фактический, т | M1: Выполнение плана, %
A2: ООО ГРК | B2: богара | C2: А-17 | D2: Преладо | E2: 48 | F2: =#VALUE! -> #VALUE! | G2: =E2-F2 -> #VALUE! | H2: =IFERROR(F2/E2,"-") -> - | I2: =4*0.9 -> 3.6 | J2: =IFERROR(L2/F2,) -> 0 | K2: =E2*I2 -> 172.8 | L2: =#VALUE! -> #VALUE! | M2: =IFERROR(L2/K2,"-") -> -

Sheet Поступление на завод 
A1: Продажа | B1: (пусто)
E3: Данные
A4: Регистратор.Дата | B4: Культура | C4: Поле | D4: Регистратор.Номенклатура | E4: Физический вес, кг | F4: Зачетный вес, кг
A5: (пусто) | B5: ГРК (богара) | E5: 1297240 | F5: 1056094.5
A6: Итог Результат | E6: 1297240 | F6: 1056094.5

Sheet Поступление на завод по дням
A3: Дата | B3: Физический вес, тонны | C3: Физический вес, кг | D3: Зачетный вес, кг | E3: Дата акта входного контроля | I3: По дате акта входного контроля
A4: 45804 | B4: =C4/1000 -> 29.45 | C4: 29450 | D4: 21740.7 | E4: 45804 | I4: Физический вес, тонны
A5: 45805 | B5: =C5/1000 -> 98.79 | C5: 98790 | D5: 71595.6 | E5: 45805 | I5: 6485.45
A6: 45806 | B6: =C6/1000 -> 52.63 | C6: 52630 | D6: 37492 | E6: 45806
A7: 45807 | B7: =C7/1000 -> 46.31 | C7: 46310 | D7: 33701.5 | E7: 45808
A8: 45808
A9: 45809 | B9: =C9/1000 -> 163.7 | C9: 163700 | D9: 124140.6 | E9: 45809
A10: 45810 | B10: =C10/1000 -> 181.62 | C10: 181620 | D10: 141581.7 | E10: 45810
A11: 45811 | B11: =C11/1000 -> 137.38 | C11: 137380 | D11: 111232.3 | E11: 45811
A12: 45812 | B12: =C12/1000 -> 218.34 | C12: 218340 | D12: 186899.6 | E12: 45812
A13: 45813 | B13: =C13/1000 -> 257.7 | C13: 257700 | D13: 215785.7 | E13: 45813
A14: 45814 | B14: =C14/1000 -> 187.54 | C14: 187540 | D14: 157412.6 | E14: 45814
A15: 45815 | B15: =C15/1000 -> 222.75 | C15: 222750 | D15: 189231 | E15: 45815
A16: 45816 | B16: =C16/1000 -> 244.84 | C16: 244840 | D16: 214198.4 | E16: 45816
A17: 45817 | B17: =C17/1000 -> 152.51 | C17: 152510 | D17: 127138.9 | E17: 45817
A18: 45818 | B18: =C18/1000 -> 185.62 | C18: 185620 | D18: 159943.4 | E18: 45818
A19: 45819 | B19: =C19/1000 -> 159.63 | C19: 159630 | D19: 146763.8 | E19: 45819
A20: 45820 | B20: =C20/1000 -> 269.58 | C20: 269580 | D20: 233118.8 | E20: 45820
... A33: 45833 | B33: =C33/1000 -> 125.43 | C33: 125430 | D33: 104544.2 | E33: 45833
A34: 45834
A35: 45835
A36: 45836 | B36: =C36/1000 -> 60.75 | C36: 60750 | D36: 51333.9 | E36: 45836
A37: 45837 | B37: =C37/1000 -> 69.23 | C37: 69230 | D37: 60600.6 | E37: 45837
A38: 45838 | B38: =C38/1000 -> 28.37 | C38: 28370 | D38: 24692.3 | E38: 45838
A39: 45839 | B39: =C39/1000 -> 69.19 | C39: 69190 | D39: 60335.2 | E39: 45839
A40: 45840 | B40: =C40/1000 -> 218.92 | C40: 218920 | D40: 187414.8 | E40: 45840
A41: 45841 | B41: =C41/1000 -> 192.37 | C41: 192370 | D41: 161740.5 | E41: 45841
A42: 45842 | B42: =C42/1000 -> 213.73 | C42: 213730 | D42: 190148.5 | E42: 45842
A43: 45843 | B43: =C43/1000 -> 84.68 | C43: 84680 | D43: 73460.3 | E43: 45843
A44: 45844 | B44: =C44/1000 -> 226.12 | C44: 226120 | D44: 203439.1 | E44: 45844
A45: 45845
A46: 45846 | B46: =C46/1000 -> 40.51 | C46: 40510 | D46: 36604.8 | E46: 45846
A47: 45847 | B47: =C47/1000 -> 143.24 | C47: 143240 | D47: 125850.3 | E47: 45847
A48: 45848 | B48: =C48/1000 -> 38.47 | C48: 38470 | D48: 31337.5 | E48: 45848

Sheet по дням
A1: Продажа | B1: - все -
A3: Регистратор.Дата

Sheet Реестр уборки 2026
A1: Показатель | B1: Количество | C1: Значение финометра | D1: Регистратор.Номер | E1: Регистратор.Дата | F1: Регистратор.Вес брутто | G1: Регистратор.Вес нетто | H1: Регистратор.Вес тары | I1: Регистратор.Вес чистый | J1: Регистратор.Контрагент | K1: Регистратор.Номенклатура | L1: Регистратор.Комбайнеры.Поле.Наименование | M1: Регистратор.Водитель | N1: Регистратор.Время прибытия | O1: Регистратор.Время убытия | P1: Регистратор.Комбайнеры.Комбайнер.Наименование | Q1: Регистратор.Номера талонов | R1: Регистратор.Номер машины | S1: Регистратор.Номер прицепа | T1: Поле | U1: Сорт уточн | V1: Площадь уборки, га | W1: Культура | X1: Орошение | Y1: Смена | Z1: Дата отчета | AA1: Продажа | AB1: Примечание | AC1: Финометр | AD1: Характеристика | AE1: № акта | AF1: Дата акта | AG1: Вх № | AH1: Степень зрелости вспом
A2: Степень зрелости | C2: =Таблица3[[#This Row],[Степень зрелости вспом]] -> 49 | D2: 40 | G2: 16070 | I2: 12936.4 | J2: ГРИН РЭЙ КУБАНЬ ООО | K2: Тиара | M2: Богучарский А. И. | R2: А718ВХ | T2: А-4/1 | U2: =Таблица3[[#This Row],[Регистратор.Номенклатура]] -> Тиара | V2: =36*Таблица3[[#This Row],[Регистратор.Вес нетто]]/191510 -> 3.0208344 | W2: ГРК (богара) | X2: богара | Y2: 1 | Z2: 46176 | AC2: 40-52 | AD2: Высший | AE2: 14 | AF2: 46176 | AH2: =IFERROR(VLOOKUP(Таблица3[[#This Row],[№ акта]],'Степень зрелости 2026'!$H$12:$I$582,2,FALSE()),) -> 49
A3: Степень зрелости | C3: =Таблица3[[#This Row],[Степень зрелости вспом]] -> 53 | D3: 42 | G3: 13670 | I3: 9637.4 | J3: ГРИН РЭЙ КУБАНЬ ООО | K3: Тиара | M3: Сероштан Станислав Викторович | R3: Е758РЕ | T3: А-4/1 | U3: =Таблица3[[#This Row],[Регистратор.Номенклатура]] -> Тиара | V3: =36*Таблица3[[#This Row],[Регистратор.Вес нетто]]/191510 -> 2.569683 | W3: ГРК (богара) | X3: богара | Y3: 1 | Z3: 46176 | AC3: 53-63 | AD3: Высший | AE3: 15 | AF3: 46176 | AH3: =IFERROR(VLOOKUP(Таблица3[[#This Row],[№ акта]],'Степень зрелости 2026'!$H$12:$I$582,2,FALSE()),) -> 53
A4: Степень зрелости | C4: =Таблица3[[#This Row],[Степень зрелости вспом]] -> 50 | D4: 43 | G4: 13610 | I4: 10683.9 | J4: ГРИН РЭЙ КУБАНЬ ООО | K4: Тиара | M4: Богучарский А. И. | R4: А718ВХ | T4: А-4/1 | U4: =Таблица3[[#This Row],[Регистратор.Номенклатура]] -> Тиара | V4: =36*Таблица3[[#This Row],[Регистратор.Вес нетто]]/191510 -> 2.5584043 | W4: ГРК (богара) | X4: богара | Y4: 1 | Z4: 46176 | AC4: 40-52 | AD4: Высший | AE4: 16 | AF4: 46176 | AH4: =IFERROR(VLOOKUP(Таблица3[[#This Row],[№ акта]],'Степень зрелости 2026'!$H$12:$I$582,2,FALSE()),) -> 50
A5: Степень зрелости | C5: =Таблица3[[#This Row],[Степень зрелости вспом]] -> 54 | D5: 48 | G5: 13740 | I5: 10648.5 | J5: ГРИН РЭЙ КУБАНЬ ООО | K5: Тиара | M5: Кудря Евгений | R5: А719ОО | T5: А-4/1 | U5: =Таблица3[[#This Row],[Регистратор.Номенклатура]] -> Тиара | V5: =36*Таблица3[[#This Row],[Регистратор.Вес нетто]]/191510 -> 2.5828416 | W5: ГРК (богара) | X5: богара | Y5: 1 | Z5: 46176 | AC5: 53-63 | AD5: Высший | AE5: 17 | AF5: 46176 | AH5: =IFERROR(VLOOKUP(Таблица3[[#This Row],[№ акта]],'Степень зрелости 2026'!$H$12:$I$582,2,FALSE()),) -> 54
A6: Степень зрелости | C6: =Таблица3[[#This Row],[Степень зрелости вспом]] -> 53 | D6: 49 | G6: 13660 | I6: 10996.3 | J6: ГРИН РЭЙ КУБАНЬ ООО | K6: Тиара | M6: Богучарский А. И. | R6: А718ВХ | T6: А-4/1 | U6: =Таблица3[[#This Row],[Регистратор.Номенклатура]] -> Тиара | V6: =36*Таблица3[[#This Row],[Регистратор.Вес нетто]]/191510 -> 2.5678032 | W6: ГРК (богара) | X6: богара | Y6: 1 | Z6: 46176 | AC6: 53-63 | AD6: Высший | AE6: 18 | AF6: 46176 | AH6: =IFERROR(VLOOKUP(Таблица3[[#This Row],[№ акта]],'Степень зрелости 2026'!$H$12:$I$582,2,FALSE()),) -> 53
A7: Степень зрелости | C7: =Таблица3[[#This Row],[Степень зрелости вспом]] -> 53 | D7: 50 | G7: 13390 | I7: 10645.1 | J7: ГРИН РЭЙ КУБАНЬ ООО | K7: Тиара | M7: Черевко Александр Владимирович | R7: А114МК | T7: А-4/1 | U7: =Таблица3[[#This Row],[Регистратор.Номенклатура]] -> Тиара | V7: =36*Таблица3[[#This Row],[Регистратор.Вес нетто]]/191510 -> 2.5170487 | W7: ГРК (богара) | X7: богара | Y7: 1 | Z7: 46176 | AC7: 53-63 | AD7: Высший | AE7: 19 | AF7: 46176 | AH7: =IFERROR(VLOOKUP(Таблица3[[#This Row],[№ акта]],'Степень зрелости 2026'!$H$12:$I$582,2,FALSE()),) -> 53
A8: Степень зрелости | C8: =Таблица3[[#This Row],[Степень зрелости вспом]] -> 52 | D8: 51 | G8: 13720 | I8: 10907.4 | J8: ГРИН РЭЙ КУБАНЬ ООО | K8: Тиара | M8: Кудря Евгений | R8: А719ОО | T8: А-4/1 | U8: =Таблица3[[#This Row],[Регистратор.Номенклатура]] -> Тиара | V8: =36*Таблица3[[#This Row],[Регистратор.Вес нетто]]/191510 -> 2.579082 | W8: ГРК (богара) | X8: богара | Y8: 1 | Z8: 46176 | AC8: 40-52 | AD8: Высший | AE8: 20 | AF8: 46176 | AH8: =IFERROR(VLOOKUP(Таблица3[[#This Row],[№ акта]],'Степень зрелости 2026'!$H$12:$I$582,2,FALSE()),) -> 52
A9: Степень зрелости | C9: =Таблица3[[#This Row],[Степень зрелости вспом]] -> 52 | D9: 52 | G9: 13740 | I9: 11060.7 | J9: ГРИН РЭЙ КУБАНЬ ООО | K9: Тиара | M9: Богучарский А. И. | R9: А718ВХ | T9: А-4/1 | U9: =Таблица3[[#This Row],[Регистратор.Номенклатура]] -> Тиара | V9: =36*Таблица3[[#This Row],[Регистратор.Вес нетто]]/191510 -> 2.5828416 | W9: ГРК (богара) | X9: богара | Y9: 1 | Z9: 46176 | AC9: 40-52 | AD9: Высший | AE9: 21 | AF9: 46176 | AH9: =IFERROR(VLOOKUP(Таблица3[[#This Row],[№ акта]],'Степень зрелости 2026'!$H$12:$I$582,2,FALSE()),) -> 52
A10: Степень зрелости | C10: =Таблица3[[#This Row],[Степень зрелости вспом]] -> 51 | D10: 53 | G10: 13260 | I10: 10674.3 | J10: ГРИН РЭЙ КУБАНЬ ООО | K10: Тиара | M10: Черевко Александр Владимирович | R10: А114МК | T10: А-4/1 | U10: =Таблица3[[#This Row],[Регистратор.Номенклатура]] -> Тиара | V10: =36*Таблица3[[#This Row],[Регистратор.Вес нетто]]/191510 -> 2.4926114 | W10: ГРК (богара) | X10: богара | Y10: 1 | Z10: 46176 | AC10: 40-52 | AD10: Высший | AE10: 22 | AF10: 46177 | AH10: =IFERROR(VLOOKUP(Таблица3[[#This Row],[№ акта]],'Степень зрелости 2026'!$H$12:$I$582,2,FALSE()),) -> 51
A11: Степень зрелости | C11: =Таблица3[[#This Row],[Степень зрелости вспом]] -> 53 | D11: 54 | G11: 13390 | I11: 10779 | J11: ГРИН РЭЙ КУБАНЬ ООО | K11: Тиара | M11: Кудря Евгений | R11: А719ОО | T11: А-4/1 | U11: =Таблица3[[#This Row],[Регистратор.Номенклатура]] -> Тиара | V11: =36*Таблица3[[#This Row],[Регистратор.Вес нетто]]/191510 -> 2.5170487 | W11: ГРК (богара) | X11: богара | Y11: 1 | Z11: 46176 | AC11: 53-63 | AD11: Высший | AE11: 23 | AF11: 46177 | AH11: =IFERROR(VLOOKUP(Таблица3[[#This Row],[№ акта]],'Степень зрелости 2026'!$H$12:$I$582,2,FALSE()),) -> 53
A12: Степень зрелости | C12: =Таблица3[[#This Row],[Степень зрелости вспом]] -> 55 | D12: 55 | G12: 13270 | I12: 10815.1 | J12: ГРИН РЭЙ КУБАНЬ ООО | K12: Тиара | M12: Богучарский А. И. | R12: А718ВХ | T12: А-4/1 | U12: =Таблица3[[#This Row],[Регистратор.Номенклатура]] -> Тиара | V12: =36*Таблица3[[#This Row],[Регистратор.Вес нетто]]/191510 -> 2.4944911 | W12: ГРК (богара) | X12: богара | Y12: 1 | Z12: 46176 | AC12: 53-63 | AD12: Высший | AE12: 24 | AF12: 46177 | AH12: =IFERROR(VLOOKUP(Таблица3[[#This Row],[№ акта]],'Степень зрелости 2026'!$H$12:$I$582,2,FALSE()),) -> 55
A13: Степень зрелости | C13: =Таблица3[[#This Row],[Степень зрелости вспом]] -> 50 | D13: 56 | G13: 13200 | I13: 10362 | J13: ГРИН РЭЙ КУБАНЬ ООО | K13: Тиара | M13: Черевко Александр Владимирович | R13: А114МК | T13: А-4/1 | U13: =Таблица3[[#This Row],[Регистратор.Номенклатура]] -> Тиара | V13: =36*Таблица3[[#This Row],[Регистратор.Вес нетто]]/191510 -> 2.4813326 | W13: ГРК (богара) | X13: богара | Y13: 1 | Z13: 46176 | AC13: 40-52 | AD13: Высший | AE13: 25 | AF13: 46177 | AH13: =IFERROR(VLOOKUP(Таблица3[[#This Row],[№ акта]],'Степень зрелости 2026'!$H$12:$I$582,2,FALSE()),) -> 50
... A15: Степень зрелости | C15: =Таблица3[[#This Row],[Степень зрелости вспом]] -> 54 | D15: 59 | G15: 13760 | I15: 10939.2 | J15: ГРИН РЭЙ КУБАНЬ ООО | K15: Тиара | M15: Погуляй А.Б. | R15: К403ЕМ | T15: А-4/1 | U15: =Таблица3[[#This Row],[Регистратор.Номенклатура]] -> Тиара | V15: =36*Таблица3[[#This Row],[Регистратор.Вес нетто]]/191510 -> 2.5866012 | W15: ГРК (богара) | X15: богара | Y15: 1 | Z15: 46176 | AC15: 53-63 | AD15: Высший | AE15: 27 | AF15: 46177 | AH15: =IFERROR(VLOOKUP(Таблица3[[#This Row],[№ акта]],'Степень зрелости 2026'!$H$12:$I$582,2,FALSE()),) -> 54
C16: =Таблица3[[#This Row],[Степень зрелости вспом]] -> 55 | D16: 61 | G16: 13570 | I16: 10516.7 | J16: ГРИН РЭЙ КУБАНЬ ООО | K16: Тиара | M16: Деревянко Н.Н. | R16: Р699ОН | T16: А-4/1 | U16: =Таблица3[[#This Row],[Регистратор.Номенклатура]] -> Тиара | V16: =20*Таблица3[[#This Row],[Регистратор.Вес нетто]]/111250 -> 2.4395506 | W16: ГРК (богара) | X16: богара | Y16: 2 | Z16: 46177 | AC16: 53-63 | AD16: Высший | AE16: 28 | AF16: 46177 | AH16: =IFERROR(VLOOKUP(Таблица3[[#This Row],[№ акта]],'Степень зрелости 2026'!$H$12:$I$582,2,FALSE()),) -> 55
C17: =Таблица3[[#This Row],[Степень зрелости вспом]] -> 55 | D17: 63 | G17: 13280 | I17: 10823.2 | J17: ГРИН РЭЙ КУБАНЬ ООО | K17: Тиара | M17: Осипов Александр Николаевич | R17: Е732УС | T17: А-4/1 | U17: =Таблица3[[#This Row],[Регистратор.Номенклатура]] -> Тиара | V17: =20*Таблица3[[#This Row],[Регистратор.Вес нетто]]/111250 -> 2.3874157 | W17: ГРК (богара) | X17: богара | Y17: 2 | Z17: 46177 | AC17: 53-63 | AD17: Высший | AE17: 29 | AF17: 46177 | AH17: =IFERROR(VLOOKUP(Таблица3[[#This Row],[№ акта]],'Степень зрелости 2026'!$H$12:$I$582,2,FALSE()),) -> 55
C18: =Таблица3[[#This Row],[Степень зрелости вспом]] -> 53 | D18: 64 | G18: 13840 | I18: 11418 | J18: ГРИН РЭЙ КУБАНЬ ООО | K18: Тиара | M18: Бербеницкий Сергей Николаевич | R18: С400РР | T18: А-4/1 | U18: =Таблица3[[#This Row],[Регистратор.Номенклатура]] -> Тиара | V18: =20*Таблица3[[#This Row],[Регистратор.Вес нетто]]/111250 -> 2.4880899 | W18: ГРК (богара) | X18: богара | Y18: 2 | Z18: 46177 | AC18: 53-63 | AD18: Высший | AE18: 30 | AF18: 46177 | AH18: =IFERROR(VLOOKUP(Таблица3[[#This Row],[№ акта]],'Степень зрелости 2026'!$H$12:$I$582,2,FALSE()),) -> 53
C19: =Таблица3[[#This Row],[Степень зрелости вспом]] -> 53 | D19: 65 | G19: 14080 | I19: 11334.4 | J19: ГРИН РЭЙ КУБАНЬ ООО | K19: Тиара | M19: Погуляй А.Б. | R19: К403ЕМ | T19: А-4/1 | U19: =Таблица3[[#This Row],[Регистратор.Номенклатура]] -> Тиара | V19: =20*Таблица3[[#This Row],[Регистратор.Вес нетто]]/111250 -> 2.531236 | W19: ГРК (богара) | X19: богара | Y19: 2 | Z19: 46177 | AC19: 53-63 | AD19: Высший | AE19: 31 | AF19: 46177 | AH19: =IFERROR(VLOOKUP(Таблица3[[#This Row],[№ акта]],'Степень зрелости 2026'!$H$12:$I$582,2,FALSE()),) -> 53
C20: =Таблица3[[#This Row],[Степень зрелости вспом]] -> 52 | D20: 66 | G20: 14070 | I20: 11467.1 | J20: ГРИН РЭЙ КУБАНЬ ООО | K20: Тиара | M20: Деревянко Н.Н. | R20: Р699ОН | T20: А-4/1 | U20: =Таблица3[[#This Row],[Регистратор.Номенклатура]] -> Тиара | V20: =20*Таблица3[[#This Row],[Регистратор.Вес нетто]]/111250 -> 2.5294382 | W20: ГРК (богара) | X20: богара | Y20: 2 | Z20: 46177 | AC20: 40-52 | AD20: Высший | AE20: 32 | AF20: 46177 | AH20: =IFERROR(VLOOKUP(Таблица3[[#This Row],[№ акта]],'Степень зрелости 2026'!$H$12:$I$582,2,FALSE()),) -> 52
C21: =Таблица3[[#This Row],[Степень зрелости вспом]] -> 53 | D21: 68 | G21: 14230 | I21: 11739.8 | J21: ГРИН РЭЙ КУБАНЬ ООО | K21: Тиара | M21: Ревенко Андрей Вячеславович | R21: А781РР | T21: А-4/1 | U21: =Таблица3[[#This Row],[Регистратор.Номенклатура]] -> Тиара | V21: =20*Таблица3[[#This Row],[Регистратор.Вес нетто]]/111250 -> 2.5582022 | W21: ГРК (богара) | X21: богара | Y21: 2 | Z21: 46177 | AC21: 53-63 | AD21: Высший | AE21: 33 | AF21: 46177 | AH21: =IFERROR(VLOOKUP(Таблица3[[#This Row],[№ акта]],'Степень зрелости 2026'!$H$12:$I$582,2,FALSE()),) -> 53
C22: =Таблица3[[#This Row],[Степень зрелости вспом]] -> 53 | D22: 70 | G22: 14110 | I22: 11781.8 | J22: ГРИН РЭЙ КУБАНЬ ООО | K22: Тиара | M22: Погуляй А.Б. | R22: К403ЕМ | T22: А-4/1 | U22: =Таблица3[[#This Row],[Регистратор.Номенклатура]] -> Тиара | V22: =20*Таблица3[[#This Row],[Регистратор.Вес нетто]]/111250 -> 2.5366292 | W22: ГРК (богара) | X22: богара | Y22: 2 | Z22: 46177 | AC22: 53-63 | AD22: Высший | AE22: 35 | AF22: 46177 | AH22: =IFERROR(VLOOKUP(Таблица3[[#This Row],[№ акта]],'Степень зрелости 2026'!$H$12:$I$582,2,FALSE()),) -> 53
C23: =Таблица3[[#This Row],[Степень зрелости вспом]] -> 52 | D23: 69 | G23: 14070 | I23: 11185.7 | J23: ГРИН РЭЙ КУБАНЬ ООО | K23: Тиара | M23: Бербеницкий Сергей Николаевич | R23: С400РР | T23: А-4/1 | U23: =Таблица3[[#This Row],[Регистратор.Номенклатура]] -> Тиара | V23: =20*Таблица3[[#This Row],[Регистратор.Вес нетто]]/111250 -> 2.5294382 | W23: ГРК (богара) | X23: богара | Y23: 2 | Z23: 46177 | AC23: 40-52 | AD23: Высший | AE23: 34 | AF23: 46177 | AH23: =IFERROR(VLOOKUP(Таблица3[[#This Row],[№ акта]],'Степень зрелости 2026'!$H$12:$I$582,2,FALSE()),) -> 52
C24: =Таблица3[[#This Row],[Степень зрелости вспом]] -> 42 | D24: 71 | G24: 6120 | I24: 4039.2 | J24: ГРИН РЭЙ КУБАНЬ ООО | K24: Авола | M24: Деревянко Н.Н. | R24: Р699ОН | T24: А-3 | U24: =Таблица3[[#This Row],[Регистратор.Номенклатура]] -> Авола | V24: =2*Таблица3[[#This Row],[Регистратор.Вес нетто]]/6120 -> 2 | W24: ГРК (богара) | X24: богара | Y24: 2 | Z24: 46177 | AC24: 40-52 | AD24: Высший | AE24: 36 | AF24: 46177 | AH24: =IFERROR(VLOOKUP(Таблица3[[#This Row],[№ акта]],'Степень зрелости 2026'!$H$12:$I$582,2,FALSE()),) -> 42
C25: =Таблица3[[#This Row],[Степень зрелости вспом]] -> 49 | D25: 95 | G25: 15500 | I25: 12322.5 | J25: ГРИН РЭЙ КУБАНЬ ООО | K25: Тиара | M25: Погуляй А.Б. | R25: О824ТХ | T25: А-4/1 | U25: =Таблица3[[#This Row],[Регистратор.Номенклатура]] -> Тиара | V25: =42*Таблица3[[#This Row],[Регистратор.Вес нетто]]/244270 -> 2.6650837 | W25: ГРК (богара) | X25: богара | Y25: 3 | Z25: 46179 | AC25: 40-52 | AD25: Высший | AE25: 51 | AF25: 46179 | AH25: =IFERROR(VLOOKUP(Таблица3[[#This Row],[№ акта]],'Степень зрелости 2026'!$H$12:$I$582,2,FALSE()),) -> 49
C26: =Таблица3[[#This Row],[Степень зрелости вспом]] -> 49 | D26: 96 | G26: 13520 | I26: 10342.8 | J26: ГРИН РЭЙ КУБАНЬ ООО | K26: Тиара | M26: Деревянко Н.Н. | R26: Р699ОН | T26: А-4/1 | U26: =Таблица3[[#This Row],[Регистратор.Номенклатура]] -> Тиара | V26: =42*Таблица3[[#This Row],[Регистратор.Вес нетто]]/244270 -> 2.3246408 | W26: ГРК (богара) | X26: богара | Y26: 3 | Z26: 46179 | AC26: 40-52 | AD26: Высший | AE26: 52 | AF26: 46179 | AH26: =IFERROR(VLOOKUP(Таблица3[[#This Row],[№ акта]],'Степень зрелости 2026'!$H$12:$I$582,2,FALSE()),) -> 49
C27: =Таблица3[[#This Row],[Степень зрелости вспом]] -> 48 | D27: 97 | G27: 13550 | I27: 10772.3 | J27: ГРИН РЭЙ КУБАНЬ ООО | K27: Тиара | M27: Бербеницкий Сергей Николаевич | R27: С400РР | T27: А-4/1 | U27: =Таблица3[[#This Row],[Регистратор.Номенклатура]] -> Тиара | V27: =42*Таблица3[[#This Row],[Регистратор.Вес нетто]]/244270 -> 2.329799 | W27: ГРК (богара) | X27: богара | Y27: 3 | Z27: 46179 | AC27: 40-52 | AD27: Высший | AE27: 53 | AF27: 46179 | AH27: =IFERROR(VLOOKUP(Таблица3[[#This Row],[№ акта]],'Степень зрелости 2026'!$H$12:$I$582,2,FALSE()),) -> 48
C28: =Таблица3[[#This Row],[Степень зрелости вспом]] -> 47 | D28: 98 | G28: 4470 | I28: 3687.7 | J28: ГРИН РЭЙ КУБАНЬ ООО | K28: Тиара | M28: Сайко Владимир Николаевич | R28: Т919РВ | T28: А-4/1 | U28: =Таблица3[[#This Row],[Регистратор.Номенклатура]] -> Тиара | V28: =42*Таблица3[[#This Row],[Регистратор.Вес нетто]]/244270 -> 0.76857576 | W28: ГРК (богара) | X28: богара | Y28: 3 | Z28: 46179 | AC28: 40-52 | AD28: Высший | AE28: 54 | AF28: 46179 | AH28: =IFERROR(VLOOKUP(Таблица3[[#This Row],[№ акта]],'Степень зрелости 2026'!$H$12:$I$582,2,FALSE()),) -> 47
C29: =Таблица3[[#This Row],[Степень зрелости вспом]] -> 50 | D29: 76 | G29: 15750 | I29: 13308.8 | J29: ГРИН РЭЙ КУБАНЬ ООО | K29: Тиара | M29: Бербеницкий Сергей Николаевич | R29: С400РР | T29: А-22/1 | U29: =Таблица3[[#This Row],[Регистратор.Номенклатура]] -> Тиара | V29: =5*Таблица3[[#This Row],[Регистратор.Вес нетто]]/24650 -> 3.1947262 | W29: ГРК (богара) | X29: богара | Y29: 3 | Z29: 46179 | AC29: 40-52 | AD29: Высший | AE29: 41 | AF29: 46179 | AH29: =IFERROR(VLOOKUP(Таблица3[[#This Row],[№ акта]],'Степень зрелости 2026'!$H$12:$I$582,2,FALSE()),) -> 50
C30: =Таблица3[[#This Row],[Степень зрелости вспом]] -> 54 | D30: 77 | G30: 8900 | I30: 7609.5 | J30: ГРИН РЭЙ КУБАНЬ ООО | K30: Тиара | M30: Чигрин Н.А. | R30: А819ЕВ | T30: А-22/1 | U30: =Таблица3[[#This Row],[Регистратор.Номенклатура]] -> Тиара | V30: =5*Таблица3[[#This Row],[Регистратор.Вес нетто]]/24650 -> 1.8052738 | W30: ГРК (богара) | X30: богара | Y30: 3 | Z30: 46179 | AC30: 53-63 | AD30: Высший | AE30: 37 | AF30: 46179 | AH30: =IFERROR(VLOOKUP(Таблица3[[#This Row],[№ акта]],'Степень зрелости 2026'!$H$12:$I$582,2,FALSE()),) -> 54
C31: =Таблица3[[#This Row],[Степень зрелости вспом]] -> 46 | D31: 84 | G31: 4550 | I31: 3617.2 | J31: ГРИН РЭЙ КУБАНЬ ООО | K31: Тиара | M31: Сайко Владимир Николаевич | R31: Т919РВ | T31: А-4/1 | U31: =Таблица3[[#This Row],[Регистратор.Номенклатура]] -> Тиара | V31: =42*Таблица3[[#This Row],[Регистратор.Вес нетто]]/244270 -> 0.78233103 | W31: ГРК (богара) | X31: богара | Y31: 3 | Z31: 46179 | AC31: 40-52 | AD31: Высший | AE31: 42 | AF31: 46179 | AH31: =IFERROR(VLOOKUP(Таблица3[[#This Row],[№ акта]],'Степень зрелости 2026'!$H$12:$I$582,2,FALSE()),) -> 46
C32: =Таблица3[[#This Row],[Степень зрелости вспом]] -> 47 | D32: 85 | G32: 13630 | I32: 10835.8 | J32: ГРИН РЭЙ КУБАНЬ ООО | K32: Тиара | M32: Погуляй А.Б. | R32: О824ТХ | T32: А-4/1 | U32: =Таблица3[[#This Row],[Регистратор.Номенклатура]] -> Тиара | V32: =42*Таблица3[[#This Row],[Регистратор.Вес нетто]]/244270 -> 2.3435543 | W32: ГРК (богара) | X32: богара | Y32: 3 | Z32: 46179 | AC32: 40-52 | AD32: Высший | AE32: 43 | AF32: 46179 | AH32: =IFERROR(VLOOKUP(Таблица3[[#This Row],[№ акта]],'Степень зрелости 2026'!$H$12:$I$582,2,FALSE()),) -> 47
C33: =Таблица3[[#This Row],[Степень зрелости вспом]] -> 47 | D33: 86 | G33: 13840 | I33: 10726 | J33: ГРИН РЭЙ КУБАНЬ ООО | K33: Тиара | M33: Деревянко Н.Н. | R33: Р699ОН | T33: А-4/1 | U33: =Таблица3[[#This Row],[Регистратор.Номенклатура]] -> Тиара | V33: =42*Таблица3[[#This Row],[Регистратор.Вес нетто]]/244270 -> 2.3796618 | W33: ГРК (богара) | X33: богара | Y33: 3 | Z33: 46179 | AC33: 40-52 | AD33: Высший | AE33: 44 | AF33: 46179 | AH33: =IFERROR(VLOOKUP(Таблица3[[#This Row],[№ акта]],'Степень зрелости 2026'!$H$12:$I$582,2,FALSE()),) -> 47
C34: =Таблица3[[#This Row],[Степень зрелости вспом]] -> 44 | D34: 87 | G34: 13640 | I34: 10707.4 | J34: ГРИН РЭЙ КУБАНЬ ООО | K34: Тиара | M34: Бербеницкий Сергей Николаевич | R34: С400РР | T34: А-4/1 | U34: =Таблица3[[#This Row],[Регистратор.Номенклатура]] -> Тиара | V34: =42*Таблица3[[#This Row],[Регистратор.Вес нетто]]/244270 -> 2.3452737 | W34: ГРК (богара) | X34: богара | Y34: 3 | Z34: 46179 | AC34: 40-52 | AD34: Высший | AE34: 45 | AF34: 46179 | AH34: =IFERROR(VLOOKUP(Таблица3[[#This Row],[№ акта]],'Степень зрелости 2026'!$H$12:$I$582,2,FALSE()),) -> 44
C35: =Таблица3[[#This Row],[Степень зрелости вспом]] -> 43 | D35: 88 | G35: 4660 | I35: 3658.1 | J35: ГРИН РЭЙ КУБАНЬ ООО | K35: Тиара | M35: Сайко Владимир Николаевич | R35: Т919РВ | T35: А-4/1 | U35: =Таблица3[[#This Row],[Регистратор.Номенклатура]] -> Тиара | V35: =42*Таблица3[[#This Row],[Регистратор.Вес нетто]]/244270 -> 0.80124452 | W35: ГРК (богара) | X35: богара | Y35: 3 | Z35: 46179 | AC35: 40-52 | AD35: Высший | AE35: 46 | AF35: 46179 | AH35: =IFERROR(VLOOKUP(Таблица3[[#This Row],[№ акта]],'Степень зрелости 2026'!$H$12:$I$582,2,FALSE()),) -> 43
C36: =Таблица3[[#This Row],[Степень зрелости вспом]] -> 47 | D36: 89 | G36: 13710 | I36: 10762.4 | J36: ГРИН РЭЙ КУБАНЬ ООО | K36: Тиара | M36: Чигрин Н.А. | R36: А819ЕВ | T36: А-4/1 | U36: =Таблица3[[#This Row],[Регистратор.Номенклатура]] -> Тиара | V36: =42*Таблица3[[#This Row],[Регистратор.Вес нетто]]/244270 -> 2.3573095 | W36: ГРК (богара) | X36: богара | Y36: 3 | Z36: 46179 | AC36: 40-52 | AD36: Высший | AE36: 47 | AF36: 46179 | AH36: =IFERROR(VLOOKUP(Таблица3[[#This Row],[№ акта]],'Степень зрелости 2026'!$H$12:$I$582,2,FALSE()),) -> 47
C37: =Таблица3[[#This Row],[Степень зрелости вспом]] -> 45 | D37: 90 | G37: 14310 | I37: 11233.3 | J37: ГРИН РЭЙ КУБАНЬ ООО | K37: Тиара | M37: Погуляй А.Б. | R37: О824ТХ | T37: А-4/1 | U37: =Таблица3[[#This Row],[Регистратор.Номенклатура]] -> Тиара | V37: =42*Таблица3[[#This Row],[Регистратор.Вес нетто]]/244270 -> 2.4604741 | W37: ГРК (богара) | X37: богара | Y37: 3 | Z37: 46179 | AC37: 40-52 | AD37: Высший | AE37: 48 | AF37: 46179 | AH37: =IFERROR(VLOOKUP(Таблица3[[#This Row],[№ акта]],'Степень зрелости 2026'!$H$12:$I$582,2,FALSE()),) -> 45
C38: =Таблица3[[#This Row],[Степень зрелости вспом]] -> 50 | D38: 91 | G38: 13690 | I38: 10472.9 | J38: ГРИН РЭЙ КУБАНЬ ООО | K38: Тиара | M38: Деревянко Н.Н. | R38: Р699ОН | T38: А-4/1 | U38: =Таблица3[[#This Row],[Регистратор.Номенклатура]] -> Тиара | V38: =42*Таблица3[[#This Row],[Регистратор.Вес нетто]]/244270 -> 2.3538707 | W38: ГРК (богара) | X38: богара | Y38: 3 | Z38: 46179 | AC38: 40-52 | AD38: Высший | AE38: 49 | AF38: 46179 | AH38: =IFERROR(VLOOKUP(Таблица3[[#This Row],[№ акта]],'Степень зрелости 2026'!$H$12:$I$582,2,FALSE()),) -> 50
C39: =Таблица3[[#This Row],[Степень зрелости вспом]] -> 50 | D39: 92 | G39: 13840 | I39: 11002.8 | J39: ГРИН РЭЙ КУБАНЬ ООО | K39: Тиара | M39: Бербеницкий Сергей Николаевич | R39: С400РР | T39: А-4/1 | U39: =Таблица3[[#This Row],[Регистратор.Номенклатура]] -> Тиара | V39: =42*Таблица3[[#This Row],[Регистратор.Вес нетто]]/244270 -> 2.3796618 | W39: ГРК (богара) | X39: богара | Y39: 3 | Z39: 46179 | AC39: 40-52 | AD39: Высший | AE39: 39 | AF39: 46179 | AH39: =IFERROR(VLOOKUP(Таблица3[[#This Row],[№ акта]],'Степень зрелости 2026'!$H$12:$I$582,2,FALSE()),) -> 50
C40: =Таблица3[[#This Row],[Степень зрелости вспом]] -> 53 | D40: 93 | G40: 13630 | I40: 11244.8 | J40: ГРИН РЭЙ КУБАНЬ ООО | K40: Тиара | M40: Чигрин Н.А. | R40: А819ЕВ | T40: А-4/1 | U40: =Таблица3[[#This Row],[Регистратор.Номенклатура]] -> Тиара | V40: =42*Таблица3[[#This Row],[Регистратор.Вес нетто]]/244270 -> 2.3435543 | W40: ГРК (богара) | X40: богара | Y40: 3 | Z40: 46179 | AC40: 53-63 | AD40: Высший | AE40: 38 | AF40: 46179 | AH40: =IFERROR(VLOOKUP(Таблица3[[#This Row],[№ акта]],'Степень зрелости 2026'!$H$12:$I$582,2,FALSE()),) -> 53
C41: =Таблица3[[#This Row],[Степень зрелости вспом]] -> 45 | D41: 94 | G41: 4690 | I41: 3728.5 | J41: ГРИН РЭЙ КУБАНЬ ООО | K41: Тиара | M41: Сайко Владимир Николаевич | R41: Т919РВ | T41: А-4/1 | U41: =Таблица3[[#This Row],[Регистратор.Номенклатура]] -> Тиара | V41: =42*Таблица3[[#This Row],[Регистратор.Вес нетто]]/244270 -> 0.80640275 | W41: ГРК (богара) | X41: богара | Y41: 3 | Z41: 46179 | AC41: 40-52 | AD41: Высший | AE41: 40 | AF41: 46179 | AH41: =IFERROR(VLOOKUP(Таблица3[[#This Row],[№ акта]],'Степень зрелости 2026'!$H$12:$I$582,2,FALSE()),) -> 45
C42: =Таблица3[[#This Row],[Степень зрелости вспом]] -> 49 | D42: 99 | G42: 14560 | I42: 12303.2 | J42: ГРИН РЭЙ КУБАНЬ ООО | K42: Тиара | M42: Чигрин Н.А. | R42: А819ЕВ | T42: А-4/1 | U42: =Таблица3[[#This Row],[Регистратор.Номенклатура]] -> Тиара | V42: =42*Таблица3[[#This Row],[Регистратор.Вес нетто]]/244270 -> 2.5034593 | W42: ГРК (богара) | X42: богара | Y42: 3 | Z42: 46179 | AC42: 40-52 | AD42: Высший | AE42: 55 | AF42: 46179 | AH42: =IFERROR(VLOOKUP(Таблица3[[#This Row],[№ акта]],'Степень зрелости 2026'!$H$12:$I$582,2,FALSE()),) -> 49
... C47: =Таблица3[[#This Row],[Степень зрелости вспом]] -> 50 | D47: 104 | G47: 13540 | I47: 11035.1 | J47: ГРИН РЭЙ КУБАНЬ ООО | K47: Тиара | M47: Чигрин Н.А. | R47: А819ЕВ | T47: А-4/1 | U47: =Таблица3[[#This Row],[Регистратор.Номенклатура]] -> Тиара | V47: =42*Таблица3[[#This Row],[Регистратор.Вес нетто]]/244270 -> 2.3280796 | W47: ГРК (богара) | X47: богара | Y47: 3 | Z47: 46179 | AC47: 40-52 | AD47: Высший | AE47: 60 | AF47: 46180 | AH47: =IFERROR(VLOOKUP(Таблица3[[#This Row],[№ акта]],'Степень зрелости 2026'!$H$12:$I$582,2,FALSE()),) -> 50
C48: =Таблица3[[#This Row],[Степень зрелости вспом]] -> 56 | D48: 107 | G48: 13880 | I48: 11034.6 | J48: ГРИН РЭЙ КУБАНЬ ООО | K48: Тиара | M48: Сероштан Станислав Викторович | R48: Е758РЕ | T48: А-4/1 | U48: =Таблица3[[#This Row],[Регистратор.Номенклатура]] -> Тиара | V48: =13*Таблица3[[#This Row],[Регистратор.Вес нетто]]/61380 -> 2.9397198 | W48: ГРК (богара) | X48: богара | Y48: 4 | Z48: 46180 | AC48: 53-63 | AD48: Высший | AE48: 61 | AF48: 46180 | AH48: =IFERROR(VLOOKUP(Таблица3[[#This Row],[№ акта]],'Степень зрелости 2026'!$H$12:$I$582,2,FALSE()),) -> 56
C49: =Таблица3[[#This Row],[Степень зрелости вспом]] -> 57 | D49: 109 | G49: 4470 | I49: 3866.5 | J49: ГРИН РЭЙ КУБАНЬ ООО | K49: Тиара | M49: Роговской Роман Алексеевич | R49: Т945РВ | T49: А-4/1 | U49: =Таблица3[[#This Row],[Регистратор.Номенклатура]] -> Тиара | V49: =13*Таблица3[[#This Row],[Регистратор.Вес нетто]]/61380 -> 0.94672532 | W49: ГРК (богара) | X49: богара | Y49: 4 | Z49: 46180 | AC49: 53-63 | AD49: Высший | AE49: 62 | AF49: 46180 | AH49: =IFERROR(VLOOKUP(Таблица3[[#This Row],[№ акта]],'Степень зрелости 2026'!$H$12:$I$582,2,FALSE()),) -> 57
C50: =Таблица3[[#This Row],[Степень зрелости вспом]] -> 50 | D50: 111 | G50: 13880 | I50: 11589.8 | J50: ГРИН РЭЙ КУБАНЬ ООО | K50: Тиара | M50: Гуйда Николай Николаевич | R50: А816ЕВ | T50: А-4/1 | U50: =Таблица3[[#This Row],[Регистратор.Номенклатура]] -> Тиара | V50: =13*Таблица3[[#This Row],[Регистратор.Вес нетто]]/61380 -> 2.9397198 | W50: ГРК (богара) | X50: богара | Y50: 4 | Z50: 46180 | AC50: 40-52 | AD50: Высший | AE50: 63 | AF50: 46180 | AH50: =IFERROR(VLOOKUP(Таблица3[[#This Row],[№ акта]],'Степень зрелости 2026'!$H$12:$I$582,2,FALSE()),) -> 50
C51: =Таблица3[[#This Row],[Степень зрелости вспом]] -> 55 | D51: 113 | G51: 11920 | I51: 8403.6 | J51: ГРИН РЭЙ КУБАНЬ ООО | K51: Тиара | M51: Гужва А М. | R51: Т285ВЕ | T51: А-4/1 | U51: =Таблица3[[#This Row],[Регистратор.Номенклатура]] -> Тиара | V51: =13*Таблица3[[#This Row],[Регистратор.Вес нетто]]/61380 -> 2.5246008 | W51: ГРК (богара) | X51: богара | Y51: 4 | Z51: 46180 | AC51: 53-63 | AD51: Высший | AE51: 64 | AF51: 46180 | AH51: =IFERROR(VLOOKUP(Таблица3[[#This Row],[№ акта]],'Степень зрелости 2026'!$H$12:$I$582,2,FALSE()),) -> 55
C52: =Таблица3[[#This Row],[Степень зрелости вспом]] -> 50 | D52: 114 | G52: 1830 | I52: 1564.6 | J52: ГРИН РЭЙ КУБАНЬ ООО | K52: Тиара | M52: Роговской Роман Алексеевич | R52: Т945РВ | T52: А-4/1 | U52: =Таблица3[[#This Row],[Регистратор.Номенклатура]] -> Тиара | V52: =13*Таблица3[[#This Row],[Регистратор.Вес нетто]]/61380 -> 0.38758553 | W52: ГРК (богара) | X52: богара | Y52: 4 | Z52: 46180 | AC52: 40-52 | AD52: Высший | AE52: 65 | AF52: 46180 | AH52: =IFERROR(VLOOKUP(Таблица3[[#This Row],[№ акта]],'Степень зрелости 2026'!$H$12:$I$582,2,FALSE()),) -> 50
C53: =Таблица3[[#This Row],[Степень зрелости вспом]] -> 50 | D53: 115 | G53: 15400 | I53: 13321 | J53: ГРИН РЭЙ КУБАНЬ ООО | K53: Тиара | M53: Жданов Андрей Иванович | R53: С707ОУ | T53: А-4/1 | U53: =Таблица3[[#This Row],[Регистратор.Номенклатура]] -> Тиара | V53: =13*Таблица3[[#This Row],[Регистратор.Вес нетто]]/61380 -> 3.2616487 | W53: ГРК (богара) | X53: богара | Y53: 4 | Z53: 46180 | AC53: 40-52 | AD53: Высший | AE53: 66 | AF53: 46180 | AH53: =IFERROR(VLOOKUP(Таблица3[[#This Row],[№ акта]],'Степень зрелости 2026'!$H$12:$I$582,2,FALSE()),) -> 50
C54: =Таблица3[[#This Row],[Степень зрелости вспом]] -> 52 | D54: 117 | G54: 13400 | I54: 10653 | J54: ГРИН РЭЙ КУБАНЬ ООО | K54: Авола | M54: Сероштан Станислав Викторович | R54: Е758РЕ | T54: А-3 | U54: =Таблица3[[#This Row],[Регистратор.Номенклатура]] -> Авола | V54: =30*Таблица3[[#This Row],[Регистратор.Вес нетто]]/160930 -> 2.4979805 | W54: ГРК (богара) | X54: богара | Y54: 4 | Z54: 46180 | AC54: 40-52 | AD54: Высший | AE54: 67 | AF54: 46180 | AH54: =IFERROR(VLOOKUP(Таблица3[[#This Row],[№ акта]],'Степень зрелости 2026'!$H$12:$I$582,2,FALSE()),) -> 52
C55: =Таблица3[[#This Row],[Степень зрелости вспом]] -> 55 | D55: 118 | G55: 13150 | I55: 10585.7 | J55: ГРИН РЭЙ КУБАНЬ ООО | K55: Авола | M55: Гуйда Николай Николаевич | R55: А816ЕВ | T55: А-3 | U55: =Таблица3[[#This Row],[Регистратор.Номенклатура]] -> Авола | V55: =30*Таблица3[[#This Row],[Регистратор.Вес нетто]]/160930 -> 2.4513764 | W55: ГРК (богара) | X55: богара | Y55: 4 | Z55: 46180 | AC55: 53-63 | AD55: Высший | AE55: 68 | AF55: 46180 | AH55: =IFERROR(VLOOKUP(Таблица3[[#This Row],[№ акта]],'Степень зрелости 2026'!$H$12:$I$582,2,FALSE()),) -> 55
C56: =Таблица3[[#This Row],[Степень зрелости вспом]] -> 48 | D56: 119 | G56: 13450 | I56: 10827.2 | J56: ГРИН РЭЙ КУБАНЬ ООО | K56: Авола | M56: Гужва А М. | R56: Т285ВЕ | T56: А-3 | U56: =Таблица3[[#This Row],[Регистратор.Номенклатура]] -> Авола | V56: =30*Таблица3[[#This Row],[Регистратор.Вес нетто]]/160930 -> 2.5073013 | W56: ГРК (богара) | X56: богара | Y56: 4 | Z56: 46180 | AC56: 40-52 | AD56: Высший | AE56: 69 | AF56: 46180 | AH56: =IFERROR(VLOOKUP(Таблица3[[#This Row],[№ акта]],'Степень зрелости 2026'!$H$12:$I$582,2,FALSE()),) -> 48
C57: =Таблица3[[#This Row],[Степень зрелости вспом]] -> 48 | D57: 120 | G57: 4590 | I57: 3740.8 | J57: ГРИН РЭЙ КУБАНЬ ООО | K57: Авола | M57: Роговской Роман Алексеевич | R57: Т945РВ | T57: А-3 | U57: =Таблица3[[#This Row],[Регистратор.Номенклатура]] -> Авола | V57: =30*Таблица3[[#This Row],[Регистратор.Вес нетто]]/160930 -> 0.85565153 | W57: ГРК (богара) | X57: богара | Y57: 4 | Z57: 46180 | AC57: 40-52 | AD57: Высший | AE57: 70 | AF57: 46180 | AH57: =IFERROR(VLOOKUP(Таблица3[[#This Row],[№ акта]],'Степень зрелости 2026'!$H$12:$I$582,2,FALSE()),) -> 48
C58: =Таблица3[[#This Row],[Степень зрелости вспом]] -> 46 | D58: 121 | G58: 13450 | I58: 10827.2 | J58: ГРИН РЭЙ КУБАНЬ ООО | K58: Авола | M58: Жданов Андрей Иванович | R58: С707ОУ | T58: А-3 | U58: =Таблица3[[#This Row],[Регистратор.Номенклатура]] -> Авола | V58: =30*Таблица3[[#This Row],[Регистратор.Вес нетто]]/160930 -> 2.5073013 | W58: ГРК (богара) | X58: богара | Y58: 4 | Z58: 46180 | AC58: 40-52 | AD58: Высший | AE58: 71 | AF58: 46180 | AH58: =IFERROR(VLOOKUP(Таблица3[[#This Row],[№ акта]],'Степень зрелости 2026'!$H$12:$I$582,2,FALSE()),) -> 46
C59: =Таблица3[[#This Row],[Степень зрелости вспом]] -> 56 | D59: 122 | G59: 13250 | I59: 10997.5 | J59: ГРИН РЭЙ КУБАНЬ ООО | K59: Авола | M59: Сероштан Станислав Викторович | R59: Е758РЕ | T59: А-3 | U59: =Таблица3[[#This Row],[Регистратор.Номенклатура]] -> Авола | V59: =30*Таблица3[[#This Row],[Регистратор.Вес нетто]]/160930 -> 2.470018 | W59: ГРК (богара) | X59: богара | Y59: 4 | Z59: 46180 | AC59: 53-63 | AD59: Высший | AE59: 72 | AF59: 46180 | AH59: =IFERROR(VLOOKUP(Таблица3[[#This Row],[№ акта]],'Степень зрелости 2026'!$H$12:$I$582,2,FALSE()),) -> 56
C60: =Таблица3[[#This Row],[Степень зрелости вспом]] -> 50 | D60: 123 | G60: 13310 | I60: 10714.5 | J60: ГРИН РЭЙ КУБАНЬ ООО | K60: Авола | M60: Гуйда Николай Николаевич | R60: А816ЕВ | T60: А-3 | U60: =Таблица3[[#This Row],[Регистратор.Номенклатура]] -> Авола | V60: =30*Таблица3[[#This Row],[Регистратор.Вес нетто]]/160930 -> 2.481203 | W60: ГРК (богара) | X60: богара | Y60: 4 | Z60: 46180 | AC60: 40-52 | AD60: Высший | AE60: 73 | AF60: 46180 | AH60: =IFERROR(VLOOKUP(Таблица3[[#This Row],[№ акта]],'Степень зрелости 2026'!$H$12:$I$582,2,FALSE()),) -> 50
C61: =Таблица3[[#This Row],[Степень зрелости вспом]] -> 50 | D61: 124 | G61: 13410 | I61: 11130.3 | J61: ГРИН РЭЙ КУБАНЬ ООО | K61: Авола | M61: Гужва А М. | R61: Т285ВЕ | T61: А-3 | U61: =Таблица3[[#This Row],[Регистратор.Номенклатура]] -> Авола | V61: =30*Таблица3[[#This Row],[Регистратор.Вес нетто]]/160930 -> 2.4998447 | W61: ГРК (богара) | X61: богара | Y61: 4 | Z61: 46180 | AC61: 40-52 | AD61: Высший | AE61: 75 | AF61: 46180 | AH61: =IFERROR(VLOOKUP(Таблица3[[#This Row],[№ акта]],'Степень зрелости 2026'!$H$12:$I$582,2,FALSE()),) -> 50
C62: =Таблица3[[#This Row],[Степень зрелости вспом]] -> 48 | D62: 125 | G62: 4500 | I62: 3622.5 | J62: ГРИН РЭЙ КУБАНЬ ООО | K62: Авола | M62: Роговской Роман Алексеевич | R62: Т945РВ | T62: А-3 | U62: =Таблица3[[#This Row],[Регистратор.Номенклатура]] -> Авола | V62: =30*Таблица3[[#This Row],[Регистратор.Вес нетто]]/160930 -> 0.83887404 | W62: ГРК (богара) | X62: богара | Y62: 4 | Z62: 46180 | AC62: 40-52 | AD62: Высший | AE62: 74 | AF62: 46180 | AH62: =IFERROR(VLOOKUP(Таблица3[[#This Row],[№ акта]],'Степень зрелости 2026'!$H$12:$I$582,2,FALSE()),) -> 48
C63: =Таблица3[[#This Row],[Степень зрелости вспом]] -> 53 | D63: 126 | G63: 13450 | I63: 10827.2 | J63: ГРИН РЭЙ КУБАНЬ ООО | K63: Авола | M63: Жданов Андрей Иванович | R63: С707ОУ | T63: А-3 | U63: =Таблица3[[#This Row],[Регистратор.Номенклатура]] -> Авола | V63: =30*Таблица3[[#This Row],[Регистратор.Вес нетто]]/160930 -> 2.5073013 | W63: ГРК (богара) | X63: богара | Y63: 4 | Z63: 46180 | AC63: 53-63 | AD63: Высший | AE63: 76 | AF63: 46181 | AH63: =IFERROR(VLOOKUP(Таблица3[[#This Row],[№ акта]],'Степень зрелости 2026'!$H$12:$I$582,2,FALSE()),) -> 53
C64: =Таблица3[[#This Row],[Степень зрелости вспом]] -> 53 | D64: 127 | G64: 13560 | I64: 11458.2 | J64: ГРИН РЭЙ КУБАНЬ ООО | K64: Авола | M64: Сероштан Станислав Викторович | R64: Е758РЕ | T64: А-3 | U64: =Таблица3[[#This Row],[Регистратор.Номенклатура]] -> Авола | V64: =30*Таблица3[[#This Row],[Регистратор.Вес нетто]]/160930 -> 2.5278071 | W64: ГРК (богара) | X64: богара | Y64: 4 | Z64: 46180 | AC64: 53-63 | AD64: Высший | AE64: 77 | AF64: 46181 | AH64: =IFERROR(VLOOKUP(Таблица3[[#This Row],[№ акта]],'Степень зрелости 2026'!$H$12:$I$582,2,FALSE()),) -> 53
C65: =Таблица3[[#This Row],[Степень зрелости вспом]] -> 48 | D65: 128 | G65: 4510 | I65: 3720.7 | J65: ГРИН РЭЙ КУБАНЬ ООО | K65: Авола | M65: Роговской Роман Алексеевич | R65: Т945РВ | T65: А-3 | U65: =Таблица3[[#This Row],[Регистратор.Номенклатура]] -> Авола | V65: =30*Таблица3[[#This Row],[Регистратор.Вес нетто]]/160930 -> 0.84073821 | W65: ГРК (богара) | X65: богара | Y65: 4 | Z65: 46180 | AC65: 40-52 | AD65: Высший | AE65: 78 | AF65: 46181 | AH65: =IFERROR(VLOOKUP(Таблица3[[#This Row],[№ акта]],'Степень зрелости 2026'!$H$12:$I$582,2,FALSE()),) -> 48
... C67: =Таблица3[[#This Row],[Степень зрелости вспом]] -> 49 | D67: 130 | G67: 13460 | I67: 10700.7 | J67: ГРИН РЭЙ КУБАНЬ ООО | K67: Авола | M67: Гужва А М. | R67: Т285ВЕ | T67: А-3 | U67: =Таблица3[[#This Row],[Регистратор.Номенклатура]] -> Авола | V67: =30*Таблица3[[#This Row],[Регистратор.Вес нетто]]/160930 -> 2.5091655 | W67: ГРК (богара) | X67: богара | Y67: 4 | Z67: 46180 | AC67: 40-52 | AD67: Высший | AE67: 80 | AF67: 46181 | AH67: =IFERROR(VLOOKUP(Таблица3[[#This Row],[№ акта]],'Степень зрелости 2026'!$H$12:$I$582,2,FALSE()),) -> 49
C68: =Таблица3[[#This Row],[Степень зрелости вспом]] -> 47 | D68: 133 | G68: 4540 | I68: 3609.3 | J68: ГРИН РЭЙ КУБАНЬ ООО | K68: Авола | M68: Роговской Роман Алексеевич | R68: Т945РВ | T68: А-3 | U68: =Таблица3[[#This Row],[Регистратор.Номенклатура]] -> Авола | V68: =41*Таблица3[[#This Row],[Регистратор.Вес нетто]]/246500 -> 0.75513185 | W68: ГРК (богара) | X68: богара | Y68: 5 | Z68: 46181 | AC68: 40-52 | AD68: Высший | AE68: 81 | AF68: 46181 | AH68: =IFERROR(VLOOKUP(Таблица3[[#This Row],[№ акта]],'Степень зрелости 2026'!$H$12:$I$582,2,FALSE()),) -> 47
C69: =Таблица3[[#This Row],[Степень зрелости вспом]] -> 49 | D69: 132 | G69: 13580 | I69: 10931.9 | J69: ГРИН РЭЙ КУБАНЬ ООО | K69: Авола | M69: Сероштан Станислав Викторович | R69: Е758РЕ | T69: А-3 | U69: =Таблица3[[#This Row],[Регистратор.Номенклатура]] -> Авола | V69: =41*Таблица3[[#This Row],[Регистратор.Вес нетто]]/246500 -> 2.2587424 | W69: ГРК (богара) | X69: богара | Y69: 5 | Z69: 46181 | AC69: 40-52 | AD69: Высший | AE69: 82 | AF69: 46181 | AH69: =IFERROR(VLOOKUP(Таблица3[[#This Row],[№ акта]],'Степень зрелости 2026'!$H$12:$I$582,2,FALSE()),) -> 49
C70: =Таблица3[[#This Row],[Степень зрелости вспом]] -> 48 | D70: 131 | G70: 13240 | I70: 10790.6 | J70: ГРИН РЭЙ КУБАНЬ ООО | K70: Авола | M70: Жданов Андрей Иванович | R70: С707ОУ | T70: А-3 | U70: =Таблица3[[#This Row],[Регистратор.Номенклатура]] -> Авола | V70: =41*Таблица3[[#This Row],[Регистратор.Вес нетто]]/246500 -> 2.2021907 | W70: ГРК (богара) | X70: богара | Y70: 5 | Z70: 46181 | AC70: 40-52 | AD70: Высший | AE70: 83 | AF70: 46181 | AH70: =IFERROR(VLOOKUP(Таблица3[[#This Row],[№ акта]],'Степень зрелости 2026'!$H$12:$I$582,2,FALSE()),) -> 48
C71: =Таблица3[[#This Row],[Степень зрелости вспом]] -> 47 | D71: 134 | G71: 13410 | I71: 10661 | J71: ГРИН РЭЙ КУБАНЬ ООО | K71: Авола | M71: Ревенко Андрей Вячеславович | R71: А781РР | T71: А-3 | U71: =Таблица3[[#This Row],[Регистратор.Номенклатура]] -> Авола | V71: =41*Таблица3[[#This Row],[Регистратор.Вес нетто]]/246500 -> 2.2304665 | W71: ГРК (богара) | X71: богара | Y71: 5 | Z71: 46181 | AC71: 40-52 | AD71: Высший | AE71: 84 | AF71: 46181 | AH71: =IFERROR(VLOOKUP(Таблица3[[#This Row],[№ акта]],'Степень зрелости 2026'!$H$12:$I$582,2,FALSE()),) -> 47
C72: =Таблица3[[#This Row],[Степень зрелости вспом]] -> 48 | D72: 136 | G72: 13650 | I72: 11124.7 | J72: ГРИН РЭЙ КУБАНЬ ООО | K72: Авола | M72: Извеков Владимир Владимирович | R72: Н378ХЕ | T72: А-3 | U72: =Таблица3[[#This Row],[Регистратор.Номенклатура]] -> Авола | V72: =41*Таблица3[[#This Row],[Регистратор.Вес нетто]]/246500 -> 2.2703854 | W72: ГРК (богара) | X72: богара | Y72: 5 | Z72: 46181 | AC72: 40-52 | AD72: Высший | AE72: 85 | AF72: 46181 | AH72: =IFERROR(VLOOKUP(Таблица3[[#This Row],[№ акта]],'Степень зрелости 2026'!$H$12:$I$582,2,FALSE()),) -> 48
C73: =Таблица3[[#This Row],[Степень зрелости вспом]] -> 48 | D73: 137 | G73: 13630 | I73: 11517.3 | J73: ГРИН РЭЙ КУБАНЬ ООО | K73: Авола | M73: Емец Р.А. | R73: У315НХ | T73: А-3 | U73: =Таблица3[[#This Row],[Регистратор.Номенклатура]] -> Авола | V73: =41*Таблица3[[#This Row],[Регистратор.Вес нетто]]/246500 -> 2.2670588 | W73: ГРК (богара) | X73: богара | Y73: 5 | Z73: 46181 | AC73: 40-52 | AD73: Высший | AE73: 86 | AF73: 46181 | AH73: =IFERROR(VLOOKUP(Таблица3[[#This Row],[№ акта]],'Степень зрелости 2026'!$H$12:$I$582,2,FALSE()),) -> 48
C74: =Таблица3[[#This Row],[Степень зрелости вспом]] -> 49 | D74: 138 | G74: 6730 | I74: 5653.2 | J74: ГРИН РЭЙ КУБАНЬ ООО | K74: Авола | M74: Ревенко Андрей Вячеславович | R74: А781РР | T74: А-3 | U74: =Таблица3[[#This Row],[Регистратор.Номенклатура]] -> Авола | V74: =41*Таблица3[[#This Row],[Регистратор.Вес нетто]]/246500 -> 1.1193915 | W74: ГРК (богара) | X74: богара | Y74: 5 | Z74: 46181 | AC74: 40-52 | AD74: Высший | AE74: 87 | AF74: 46181 | AH74: =IFERROR(VLOOKUP(Таблица3[[#This Row],[№ акта]],'Степень зрелости 2026'!$H$12:$I$582,2,FALSE()),) -> 49
C75: =Таблица3[[#This Row],[Степень зрелости вспом]] -> 49 | D75: 140 | G75: 6820 | I75: 5558.3 | J75: ГРИН РЭЙ КУБАНЬ ООО | K75: Авола | M75: Ревенко Андрей Вячеславович | R75: А781РР | T75: А-3 | U75: =Таблица3[[#This Row],[Регистратор.Номенклатура]] -> Авола | V75: =41*Таблица3[[#This Row],[Регистратор.Вес нетто]]/246500 -> 1.1343611 | W75: ГРК (богара) | X75: богара | Y75: 5 | Z75: 46181 | AC75: 40-52 | AD75: Высший | AE75: 88 | AF75: 46181 | AH75: =IFERROR(VLOOKUP(Таблица3[[#This Row],[№ акта]],'Степень зрелости 2026'!$H$12:$I$582,2,FALSE()),) -> 49
C76: =Таблица3[[#This Row],[Степень зрелости вспом]] -> 50 | D76: 141 | G76: 13350 | I76: 11547.7 | J76: ГРИН РЭЙ КУБАНЬ ООО | K76: Авола | M76: Извеков Владимир Владимирович | R76: Н378ХЕ | T76: А-3 | U76: =Таблица3[[#This Row],[Регистратор.Номенклатура]] -> Авола | V76: =41*Таблица3[[#This Row],[Регистратор.Вес нетто]]/246500 -> 2.2204868 | W76: ГРК (богара) | X76: богара | Y76: 5 | Z76: 46181 | AC76: 40-52 | AD76: Высший | AE76: 89 | AF76: 46181 | AH76: =IFERROR(VLOOKUP(Таблица3[[#This Row],[№ акта]],'Степень зрелости 2026'!$H$12:$I$582,2,FALSE()),) -> 50
C77: =Таблица3[[#This Row],[Степень зрелости вспом]] -> 51 | D77: 143 | G77: 13560 | I77: 10915.8 | J77: ГРИН РЭЙ КУБАНЬ ООО | K77: Авола | M77: Емец Р.А. | R77: У315НХ | T77: А-3 | U77: =Таблица3[[#This Row],[Регистратор.Номенклатура]] -> Авола | V77: =41*Таблица3[[#This Row],[Регистратор.Вес нетто]]/246500 -> 2.2554158 | W77: ГРК (богара) | X77: богара | Y77: 5 | Z77: 46181 | AC77: 40-52 | AD77: Высший | AE77: 90 | AF77: 46181 | AH77: =IFERROR(VLOOKUP(Таблица3[[#This Row],[№ акта]],'Степень зрелости 2026'!$H$12:$I$582,2,FALSE()),) -> 51
C78: =Таблица3[[#This Row],[Степень зрелости вспом]] -> 49 | D78: 144 | G78: 13690 | I78: 11362.7 | J78: ГРИН РЭЙ КУБАНЬ ООО | K78: Авола | M78: Ревенко Андрей Вячеславович | R78: А781РР | T78: А-3 | U78: =Таблица3[[#This Row],[Регистратор.Номенклатура]] -> Авола | V78: =41*Таблица3[[#This Row],[Регистратор.Вес нетто]]/246500 -> 2.2770385 | W78: ГРК (богара) | X78: богара | Y78: 5 | Z78: 46181 | AC78: 40-52 | AD78: Высший | AE78: 91 | AF78: 46181 | AH78: =IFERROR(VLOOKUP(Таблица3[[#This Row],[№ акта]],'Степень зрелости 2026'!$H$12:$I$582,2,FALSE()),) -> 49
C79: =Таблица3[[#This Row],[Степень зрелости вспом]] -> 51 | D79: 149 | G79: 13330 | I79: 10863.9 | J79: ГРИН РЭЙ КУБАНЬ ООО | K79: Авола | M79: Ревенко Андрей Вячеславович | R79: А781РР | T79: А-3 | U79: =Таблица3[[#This Row],[Регистратор.Номенклатура]] -> Авола | V79: =41*Таблица3[[#This Row],[Регистратор.Вес нетто]]/246500 -> 2.2171602 | W79: ГРК (богара) | X79: богара | Y79: 5 | Z79: 46181 | AC79: 40-52 | AD79: Высший | AE79: 95 | AF79: 46181 | AH79: =IFERROR(VLOOKUP(Таблица3[[#This Row],[№ акта]],'Степень зрелости 2026'!$H$12:$I$582,2,FALSE()),) -> 51
... C87: =Таблица3[[#This Row],[Степень зрелости вспом]] -> 50 | D87: 154 | G87: 13510 | I87: 10605.3 | J87: ГРИН РЭЙ КУБАНЬ ООО | K87: Авола | M87: Извеков Владимир Владимирович | R87: Н378ХЕ | T87: А-3 | U87: =Таблица3[[#This Row],[Регистратор.Номенклатура]] -> Авола | V87: =41*Таблица3[[#This Row],[Регистратор.Вес нетто]]/246500 -> 2.2470994 | W87: ГРК (богара) | X87: богара | Y87: 5 | Z87: 46181 | AC87: 40-52 | AD87: Высший | AE87: 100 | AF87: 46182 | AH87: =IFERROR(VLOOKUP(Таблица3[[#This Row],[№ акта]],'Степень зрелости 2026'!$H$12:$I$582,2,FALSE()),) -> 50
C88: =Таблица3[[#This Row],[Степень зрелости вспом]] -> 48 | D88: 155 | G88: 13230 | I88: 9988.7 | J88: ГРИН РЭЙ КУБАНЬ ООО | K88: Авола | M88: Емец Р.А. | R88: У315НХ | T88: А-3 | U88: =Таблица3[[#This Row],[Регистратор.Номенклатура]] -> Авола | V88: =6*Таблица3[[#This Row],[Регистратор.Вес нетто]]/33500 -> 2.3695522 | W88: ГРК (богара) | X88: богара | Y88: 6 | Z88: 46182 | AC88: 40-52 | AD88: Высший | AE88: 101 | AF88: 46182 | AH88: =IFERROR(VLOOKUP(Таблица3[[#This Row],[№ акта]],'Степень зрелости 2026'!$H$12:$I$582,2,FALSE()),) -> 48
C89: =Таблица3[[#This Row],[Степень зрелости вспом]] -> 50 | D89: 156 | G89: 13160 | I89: 9935.8 | J89: ГРИН РЭЙ КУБАНЬ ООО | K89: Авола | M89: Сероштан Станислав Викторович | R89: Е758РЕ | T89: А-3 | U89: =Таблица3[[#This Row],[Регистратор.Номенклатура]] -> Авола | V89: =6*Таблица3[[#This Row],[Регистратор.Вес нетто]]/33500 -> 2.3570149 | W89: ГРК (богара) | X89: богара | Y89: 6 | Z89: 46182 | AC89: 40-52 | AD89: Высший | AE89: 102 | AF89: 46182 | AH89: =IFERROR(VLOOKUP(Таблица3[[#This Row],[№ акта]],'Степень зрелости 2026'!$H$12:$I$582,2,FALSE()),) -> 50
C90: =Таблица3[[#This Row],[Степень зрелости вспом]] -> 50 | D90: 157 | G90: 7110 | I90: 5510.3 | J90: ГРИН РЭЙ КУБАНЬ ООО | K90: Авола | M90: Ревенко Андрей Вячеславович | R90: А781РР | T90: А-3 | U90: =Таблица3[[#This Row],[Регистратор.Номенклатура]] -> Авола | V90: =6*Таблица3[[#This Row],[Регистратор.Вес нетто]]/33500 -> 1.2734328 | W90: ГРК (богара) | X90: богара | Y90: 6 | Z90: 46182 | AC90: 40-52 | AD90: Высший | AE90: 103 | AF90: 46182 | AH90: =IFERROR(VLOOKUP(Таблица3[[#This Row],[№ акта]],'Степень зрелости 2026'!$H$12:$I$582,2,FALSE()),) -> 50
C91: =Таблица3[[#This Row],[Степень зрелости вспом]] -> 51 | D91: 160 | G91: 13400 | I91: 10653 | J91: ГРИН РЭЙ КУБАНЬ ООО | K91: Увертюра | M91: Извеков Владимир Владимирович | R91: Н378ХЕ | T91: А-22/1 | U91: =Таблица3[[#This Row],[Регистратор.Номенклатура]] -> Увертюра | V91: =31*Таблица3[[#This Row],[Регистратор.Вес нетто]]/206840 -> 2.0083156 | W91: ГРК (богара) | X91: богара | Y91: 6 | Z91: 46182 | AC91: 40-52 | AD91: Высший | AE91: 104 | AF91: 46182 | AH91: =IFERROR(VLOOKUP(Таблица3[[#This Row],[№ акта]],'Степень зрелости 2026'!$H$12:$I$582,2,FALSE()),) -> 51
C92: =Таблица3[[#This Row],[Степень зрелости вспом]] -> 53 | D92: 162 | G92: 13010 | I92: 11513.8 | J92: ГРИН РЭЙ КУБАНЬ ООО | K92: Увертюра | M92: Гуйда Николай Николаевич | R92: А816ЕВ | T92: А-22/1 | U92: =Таблица3[[#This Row],[Регистратор.Номенклатура]] -> Увертюра | V92: =31*Таблица3[[#This Row],[Регистратор.Вес нетто]]/206840 -> 1.9498646 | W92: ГРК (богара) | X92: богара | Y92: 6 | Z92: 46182 | AC92: 53-63 | AD92: Высший | AE92: 106 | AF92: 46182 | AH92: =IFERROR(VLOOKUP(Таблица3[[#This Row],[№ акта]],'Степень зрелости 2026'!$H$12:$I$582,2,FALSE()),) -> 53
C93: =Таблица3[[#This Row],[Степень зрелости вспом]] -> 53 | D93: 163 | G93: 13470 | I93: 10978 | J93: ГРИН РЭЙ КУБАНЬ ООО | K93: Увертюра | M93: Рудик Александр Иванович | R93: А309АТ | T93: А-22/1 | U93: =Таблица3[[#This Row],[Регистратор.Номенклатура]] -> Увертюра | V93: =31*Таблица3[[#This Row],[Регистратор.Вес нетто]]/206840 -> 2.0188068 | W93: ГРК (богара) | X93: богара | Y93: 6 | Z93: 46182 | AC93: 53-63 | AD93: Высший | AE93: 107 | AF93: 46182 | AH93: =IFERROR(VLOOKUP(Таблица3[[#This Row],[№ акта]],'Степень зрелости 2026'!$H$12:$I$582,2,FALSE()),) -> 53
C94: =Таблица3[[#This Row],[Степень зрелости вспом]] -> 56 | D94: 167 | G94: 13530 | I94: 10756.3 | J94: ГРИН РЭЙ КУБАНЬ ООО | K94: Увертюра | M94: Ревенко Андрей Вячеславович | R94: А781РР | T94: А-22/1 | U94: =Таблица3[[#This Row],[Регистратор.Номенклатура]] -> Увертюра | V94: =31*Таблица3[[#This Row],[Регистратор.Вес нетто]]/206840 -> 2.0277993 | W94: ГРК (богара) | X94: богара | Y94: 6 | Z94: 46182 | AC94: 53-63 | AD94: Высший | AE94: 108 | AF94: 46182 | AH94: =IFERROR(VLOOKUP(Таблица3[[#This Row],[№ акта]],'Степень зрелости 2026'!$H$12:$I$582,2,FALSE()),) -> 56
C95: =Таблица3[[#This Row],[Степень зрелости вспом]] -> 50 | D95: 161 | G95: 4560 | I95: 3762 | J95: ГРИН РЭЙ КУБАНЬ ООО | K95: Увертюра | M95: Роговской Роман Алексеевич | R95: Т945РВ | T95: А-22/1 | U95: =Таблица3[[#This Row],[Регистратор.Номенклатура]] -> Увертюра | V95: =31*Таблица3[[#This Row],[Регистратор.Вес нетто]]/206840 -> 0.6834268 | W95: ГРК (богара) | X95: богара | Y95: 6 | Z95: 46182 | AC95: 40-52 | AD95: Высший | AE95: 105 | AF95: 46182 | AH95: =IFERROR(VLOOKUP(Таблица3[[#This Row],[№ акта]],'Степень зрелости 2026'!$H$12:$I$582,2,FALSE()),) -> 50
C96: =Таблица3[[#This Row],[Степень зрелости вспом]] -> 54 | D96: 168 | G96: 4090 | I96: 3456.1 | J96: ГРИН РЭЙ КУБАНЬ ООО | K96: Увертюра | M96: Роговской Роман Алексеевич | R96: Т945РВ | T96: А-22/1 | U96: =Таблица3[[#This Row],[Регистратор.Номенклатура]] -> Увертюра | V96: =31*Таблица3[[#This Row],[Регистратор.Вес нетто]]/206840 -> 0.61298588 | W96: ГРК (богара) | X96: богара | Y96: 6 | Z96: 46182 | AC96: 53-63 | AD96: Высший | AE96: 109 | AF96: 46182 | AH96: =IFERROR(VLOOKUP(Таблица3[[#This Row],[№ акта]],'Степень зрелости 2026'!$H$12:$I$582,2,FALSE()),) -> 54
C97: =Таблица3[[#This Row],[Степень зрелости вспом]] -> 54 | D97: 173 | G97: 13100 | I97: 10283.5 | J97: ГРИН РЭЙ КУБАНЬ ООО | K97: Увертюра | M97: Ревенко Андрей Вячеславович | R97: А781РР | T97: А-22/1 | U97: =Таблица3[[#This Row],[Регистратор.Номенклатура]] -> Увертюра | V97: =31*Таблица3[[#This Row],[Регистратор.Вес нетто]]/206840 -> 1.9633533 | W97: ГРК (богара) | X97: богара | Y97: 6 | Z97: 46182 | AC97: 53-63 | AD97: Высший | AE97: 113 | AF97: 46182 | AH97: =IFERROR(VLOOKUP(Таблица3[[#This Row],[№ акта]],'Степень зрелости 2026'!$H$12:$I$582,2,FALSE()),)+54 -> 54
C98: =Таблица3[[#This Row],[Степень зрелости вспом]] -> 56 | D98: 170 | G98: 13410 | I98: 12136.1 | J98: ГРИН РЭЙ КУБАНЬ ООО | K98: Увертюра | M98: Извеков Владимир Владимирович | R98: Н378ХЕ | T98: А-22/1 | U98: =Таблица3[[#This Row],[Регистратор.Номенклатура]] -> Увертюра | V98: =31*Таблица3[[#This Row],[Регистратор.Вес нетто]]/206840 -> 2.0098143 | W98: ГРК (богара) | X98: богара | Y98: 6 | Z98: 46182 | AC98: 53-63 | AD98: Высший | AE98: 110 | AF98: 46182 | AH98: =IFERROR(VLOOKUP(Таблица3[[#This Row],[№ акта]],'Степень зрелости 2026'!$H$12:$I$582,2,FALSE()),) -> 56
C99: =Таблица3[[#This Row],[Степень зрелости вспом]] -> 54 | D99: 171 | G99: 13300 | I99: 11238.5 | J99: ГРИН РЭЙ КУБАНЬ ООО | K99: Увертюра | M99: Гуйда Николай Николаевич | R99: А816ЕВ | T99: А-22/1 | U99: =Таблица3[[#This Row],[Регистратор.Номенклатура]] -> Увертюра | V99: =31*Таблица3[[#This Row],[Регистратор.Вес нетто]]/206840 -> 1.9933282 | W99: ГРК (богара) | X99: богара | Y99: 6 | Z99: 46182 | AC99: 53-63 | AD99: Высший | AE99: 111 | AF99: 46182 | AH99: =IFERROR(VLOOKUP(Таблица3[[#This Row],[№ акта]],'Степень зрелости 2026'!$H$12:$I$582,2,FALSE()),) -> 54
C100: =Таблица3[[#This Row],[Степень зрелости вспом]] -> 51 | D100: 172 | G100: 13070 | I100: 11566.9 | J100: ГРИН РЭЙ КУБАНЬ ООО | K100: Увертюра | M100: Рудик Александр Иванович | R100: А309АТ | T100: А-22/1 | U100: =Таблица3[[#This Row],[Регистратор.Номенклатура]] -> Увертюра | V100: =31*Таблица3[[#This Row],[Регистратор.Вес нетто]]/206840 -> 1.9588571 | W100: ГРК (богара) | X100: богара | Y100: 6 | Z100: 46182 | AC100: 40-52 | AD100: Высший | AE100: 112 | AF100: 46182 | AH100: =IFERROR(VLOOKUP(Таблица3[[#This Row],[№ акта]],'Степень зрелости 2026'!$H$12:$I$582,2,FALSE()),) -> 51
C101: =Таблица3[[#This Row],[Степень зрелости вспом]] -> 54 | D101: 175 | G101: 13270 | I101: 11611.3 | J101: ГРИН РЭЙ КУБАНЬ ООО | K101: Увертюра | M101: Извеков Владимир Владимирович | R101: Н378ХЕ | T101: А-22/1 | U101: =Таблица3[[#This Row],[Регистратор.Номенклатура]] -> Увертюра | V101: =31*Таблица3[[#This Row],[Регистратор.Вес нетто]]/206840 -> 1.9888319 | W101: ГРК (богара) | X101: богара | Y101: 6 | Z101: 46182 | AC101: 53-63 | AD101: Высший | AE101: 115 | AF101: 46182 | AH101: =IFERROR(VLOOKUP(Таблица3[[#This Row],[№ акта]],'Степень зрелости 2026'!$H$12:$I$582,2,FALSE()),)+54 -> 54
C102: =Таблица3[[#This Row],[Степень зрелости вспом]] -> 53 | D102: 174 | G102: 4430 | I102: 3743.4 | J102: ГРИН РЭЙ КУБАНЬ ООО | K102: Увертюра | M102: Роговской Роман Алексеевич | R102: Т945РВ | T102: А-22/1 | U102: =Таблица3[[#This Row],[Регистратор.Номенклатура]] -> Увертюра | V102: =31*Таблица3[[#This Row],[Регистратор.Вес нетто]]/206840 -> 0.66394314 | W102: ГРК (богара) | X102: богара | Y102: 6 | Z102: 46182 | AC102: 53-63 | AD102: Высший | AE102: 114 | AF102: 46182 | AH102: =IFERROR(VLOOKUP(Таблица3[[#This Row],[№ акта]],'Степень зрелости 2026'!$H$12:$I$582,2,FALSE()),) -> 53
C103: =Таблица3[[#This Row],[Степень зрелости вспом]] -> 55 | D103: 178 | G103: 12880 | I103: 11527.6 | J103: ГРИН РЭЙ КУБАНЬ ООО | K103: Увертюра | M103: Гуйда Николай Николаевич | R103: А816ЕВ | T103: А-22/1 | U103: =Таблица3[[#This Row],[Регистратор.Номенклатура]] -> Увертюра | V103: =31*Таблица3[[#This Row],[Регистратор.Вес нетто]]/206840 -> 1.930381 | W103: ГРК (богара) | X103: богара | Y103: 6 | Z103: 46182 | AC103: 53-63 | AD103: Высший | AE103: 116 | AF103: 46182 | AH103: =IFERROR(VLOOKUP(Таблица3[[#This Row],[№ акта]],'Степень зрелости 2026'!$H$12:$I$582,2,FALSE()),)+55 -> 55
C104: =Таблица3[[#This Row],[Степень зрелости вспом]] -> 56 | D104: 179 | G104: 12970 | I104: 10700.3 | J104: ГРИН РЭЙ КУБАНЬ ООО | K104: Увертюра | M104: Рудик Александр Иванович | R104: А309АТ | T104: А-22/1 | U104: =Таблица3[[#This Row],[Регистратор.Номенклатура]] -> Увертюра | V104: =31*Таблица3[[#This Row],[Регистратор.Вес нетто]]/206840 -> 1.9438697 | W104: ГРК (богара) | X104: богара | Y104: 6 | Z104: 46182 | AC104: 53-63 | AD104: Высший | AE104: 117 | AF104: 46182 | AH104: =IFERROR(VLOOKUP(Таблица3[[#This Row],[№ акта]],'Степень зрелости 2026'!$H$12:$I$582,2,FALSE()),)+56 -> 56
C105: =Таблица3[[#This Row],[Степень зрелости вспом]] -> 55 | D105: 180 | G105: 15420 | I105: 13338.3 | J105: ГРИН РЭЙ КУБАНЬ ООО | K105: Увертюра | M105: Ревенко Андрей Вячеславович | R105: А781РР | T105: А-22/1 | U105: =Таблица3[[#This Row],[Регистратор.Номенклатура]] -> Увертюра | V105: =31*Таблица3[[#This Row],[Регистратор.Вес нетто]]/206840 -> 2.3110617 | W105: ГРК (богара) | X105: богара | Y105: 6 | Z105: 46182 | AC105: 53-63 | AD105: Высший | AE105: 118 | AF105: 46182 | AH105: =IFERROR(VLOOKUP(Таблица3[[#This Row],[№ акта]],'Степень зрелости 2026'!$H$12:$I$582,2,FALSE()),)+55 -> 55
C106: =Таблица3[[#This Row],[Степень зрелости вспом]] -> 55 | D106: 181 | G106: 4250 | I106: 3591.2 | J106: ГРИН РЭЙ КУБАНЬ ООО | K106: Увертюра | M106: Роговской Роман Алексеевич | R106: Т945РВ | T106: А-23 | U106: =Таблица3[[#This Row],[Регистратор.Номенклатура]] -> Увертюра | V106: =9*Таблица3[[#This Row],[Регистратор.Вес нетто]]/69350 -> 0.55155011 | W106: ГРК (богара) | X106: богара | Y106: 6 | Z106: 46182 | AC106: 53-63 | AD106: Высший | AE106: 119 | AF106: 46183 | AH106: =IFERROR(VLOOKUP(Таблица3[[#This Row],[№ акта]],'Степень зрелости 2026'!$H$12:$I$582,2,FALSE()),)+55 -> 55
C107: =Таблица3[[#This Row],[Степень зрелости вспом]] -> 56 | D107: 182 | G107: 12980 | I107: 10968.1 | J107: ГРИН РЭЙ КУБАНЬ ООО | K107: Увертюра | M107: Извеков Владимир Владимирович | R107: Н378ХЕ | T107: А-23 | U107: =Таблица3[[#This Row],[Регистратор.Номенклатура]] -> Увертюра | V107: =9*Таблица3[[#This Row],[Регистратор.Вес нетто]]/69350 -> 1.6844989 | W107: ГРК (богара) | X107: богара | Y107: 6 | Z107: 46182 | AC107: 53-63 | AD107: Высший | AE107: 120 | AF107: 46183 | AH107: =IFERROR(VLOOKUP(Таблица3[[#This Row],[№ акта]],'Степень зрелости 2026'!$H$12:$I$582,2,FALSE()),)+56 -> 56
C108: =Таблица3[[#This Row],[Степень зрелости вспом]] -> 54 | D108: 184 | G108: 13060 | I108: 11688.7 | J108: ГРИН РЭЙ КУБАНЬ ООО | K108: Увертюра | M108: Гуйда Николай Николаевич | R108: А816ЕВ | T108: А-23 | U108: =Таблица3[[#This Row],[Регистратор.Номенклатура]] -> Увертюра | V108: =9*Таблица3[[#This Row],[Регистратор.Вес нетто]]/69350 -> 1.694881 | W108: ГРК (богара) | X108: богара | Y108: 6 | Z108: 46182 | AC108: 53-63 | AD108: Высший | AE108: 121 | AF108: 46183 | AH108: =IFERROR(VLOOKUP(Таблица3[[#This Row],[№ акта]],'Степень зрелости 2026'!$H$12:$I$582,2,FALSE()),) -> 54
C109: =Таблица3[[#This Row],[Степень зрелости вспом]] -> 54 | D109: 185 | G109: 12930 | I109: 11701.6 | J109: ГРИН РЭЙ КУБАНЬ ООО | K109: Увертюра | M109: Рудик Александр Иванович | R109: А309АТ | T109: А-23 | U109: =Таблица3[[#This Row],[Регистратор.Номенклатура]] -> Увертюра | V109: =9*Таблица3[[#This Row],[Регистратор.Вес нетто]]/69350 -> 1.6780101 | W109: ГРК (богара) | X109: богара | Y109: 6 | Z109: 46182 | AC109: 53-63 | AD109: Высший | AE109: 122 | AF109: 46183 | AH109: =IFERROR(VLOOKUP(Таблица3[[#This Row],[№ акта]],'Степень зрелости 2026'!$H$12:$I$582,2,FALSE()),) -> 54
C110: =Таблица3[[#This Row],[Степень зрелости вспом]] -> 0 | D110: 119 | G110: 15390 | I110: 15390 | K110: Увертюра | M110: Баранов Николай Александрович | R110: М540АС 93 | T110: А-22/1 | U110: Увертюра | V110: =31*Таблица3[[#This Row],[Регистратор.Вес нетто]]/206840 -> 2.3065655 | W110: ГРК (богара) | X110: богара | Y110: 6 | Z110: 46182 | AA110: =Таблица3[[#This Row],[Регистратор.Вес нетто]] -> 15390 | AB110: ТПК ЮЖНЫЙ ПРОДУКТ ООО | AC110: нет данных
C111: =Таблица3[[#This Row],[Степень зрелости вспом]] -> 0 | D111: 122 | G111: 17540 | I111: 17540 | K111: Увертюра | M111: Алтадуков Заур Баталбиевич | R111: В841АН 01 | T111: А-22/1 | U111: Увертюра | V111: =31*Таблица3[[#This Row],[Регистратор.Вес нетто]]/206840 -> 2.6287952 | W111: ГРК (богара) | X111: богара | Y111: 6 | Z111: 46182 | AA111: =Таблица3[[#This Row],[Регистратор.Вес нетто]] -> 17540 | AB111: ТПК ЮЖНЫЙ ПРОДУКТ ООО | AC111: нет данных
C112: =Таблица3[[#This Row],[Степень зрелости вспом]] -> 0 | D112: 128 | G112: 13030 | I112: 13030 | K112: Увертюра | M112: Магадиев Александр Сайлаувич | R112: У184НО 193 | T112: А-23 | U112: Увертюра | V112: =9*Таблица3[[#This Row],[Регистратор.Вес нетто]]/69350 -> 1.6909877 | W112: ГРК (богара) | X112: богара | Y112: 6 | Z112: 46182 | AA112: =Таблица3[[#This Row],[Регистратор.Вес нетто]] -> 13030 | AB112: ГРАНД-СТАР ООО | AC112: нет данных
C113: =Таблица3[[#This Row],[Степень зрелости вспом]] -> 0 | D113: 129 | G113: 13100 | I113: 13100 | K113: Увертюра | M113: Кулинич Евгений Владимирович | R113: У801СТ 123 | T113: А-23 | U113: Увертюра | V113: =9*Таблица3[[#This Row],[Регистратор.Вес нетто]]/69350 -> 1.7000721 | W113: ГРК (богара) | X113: богара | Y113: 6 | Z113: 46182 | AA113: =Таблица3[[#This Row],[Регистратор.Вес нетто]] -> 13100 | AB113: ГРАНД-СТАР ООО | AC113: нет данных
...

Sheet Реестр уборки 2025
A1: Показатель | B1: Количество | C1: Значение финометра | D1: Регистратор.Номер | E1: Регистратор.Дата | F1: Регистратор.Вес брутто | G1: Регистратор.Вес нетто | H1: Регистратор.Вес тары | I1: Регистратор.Вес чистый | J1: Регистратор.Контрагент | K1: Регистратор.Номенклатура | L1: Регистратор.Комбайнеры.Поле.Наименование | M1: Регистратор.Водитель | N1: Регистратор.Время прибытия | O1: Регистратор.Время убытия | P1: Регистратор.Комбайнеры.Комбайнер.Наименование | Q1: Регистратор.Номера талонов | R1: Регистратор.Номер машины | S1: Регистратор.Номер прицепа | T1: Поле | U1: Сорт уточн | V1: Площадь уборки, га | W1: Культура | X1: Орошение | Y1: Смена | Z1: Дата отчета | AA1: Продажа | AB1: Примечание | AC1: Финометр | AD1: Характеристика | AE1: № акта | AF1: Дата акта | AG1: Вх № | AH1: Степень зрелости вспом | AI1: Поле до корр | AJ1: Сорт до корр | AK1: Культура до корр | AL1: Площадь уборки до корр | AM1: Отличие | AN1: Разница по площади | AP1: Из итогового отчета | AQ1: Акт | AR1: Поле | AS1: Площадь, га | AT1: Культура
A2: Степень зрелости | B2: 9803.9 | C2: 40 | D2: 44 | E2: 45804 | F2: 27380 | G2: 13430 | H2: 13950 | I2: 9803.9 | J2: Кубань УОХ | K2: Преладо | L2: 2/4 | M2: Сайко Василий Викторович | N2: 10:51:42 | O2: 11:42:14 | Q2: 402,002,202,502,001,201 | R2: А816ЕВ | S2: ЕС2898 | T2: 2/4 | U2: =Таблица310[[#This Row],[Регистратор.Номенклатура]] -> Преладо | V2: =18*Таблица310[[#This Row],[Регистратор.Вес нетто]]/69300 -> 3.4883117 | W2: Учхоз Кубань (богара) | X2: богара | Y2: 1 | Z2: 45804 | AC2: 40-52 | AD2: высший | AE2: 44 | AF2: 45804 | AG2: 65889 | AH2: =VLOOKUP(Таблица310[[#This Row],[№ акта]],'Степень зрелости 2025'!$H$13:$I$583,2,FALSE()) -> 40 | AI2: =VLOOKUP(Таблица310[[#This Row],[№ акта]],$AQ$1:$AT$594,2,FALSE()) -> 2/4 | AJ2: =Таблица310[[#This Row],[Регистратор.Номенклатура]] -> Преладо | AK2: =VLOOKUP(Таблица310[[#This Row],[№ акта]],$AQ$1:$AT$594,4,FALSE()) -> Учхоз Кубань (богара) | AL2: =VLOOKUP(Таблица310[[#This Row],[№ акта]],$AQ$1:$AT$594,3,FALSE()) -> 3.4883117 | AM2: =IF(Таблица310[[#This Row],[Площадь уборки, га]]=Таблица310[[#This Row],[Площадь уборки до корр]],"нет","да") -> нет | AN2: =Таблица310[[#This Row],[Площадь уборки до корр]]-Таблица310[[#This Row],[Площадь уборки, га]] -> 0 | AQ2: 44 | AR2: 2/4 | AS2: 3.4883117 | AT2: Учхоз Кубань (богара)
A3: Степень зрелости | B3: 10337.8 | C3: 42 | D3: 45 | E3: 45804 | F3: 28260 | G3: 13970 | H3: 14290 | I3: 10337.8 | J3: Кубань УОХ | K3: Преладо | L3: 2/4 | M3: Чигрин Н.А. | N3: 17:13:45 | O3: 18:08:52 | Q3: 101,301,403,102,302,404 | R3: А819ЕВ | S3: ЕС2899 | T3: 2/4 | U3: =Таблица310[[#This Row],[Регистратор.Номенклатура]] -> Преладо | V3: =18*Таблица310[[#This Row],[Регистратор.Вес нетто]]/69300 -> 3.6285714 | W3: Учхоз Кубань (богара) | X3: богара | Y3: 1 | Z3: 45804 | AC3: 40-52 | AD3: высший | AE3: 45 | AF3: 45804 | AG3: 65901 | AH3: =VLOOKUP(Таблица310[[#This Row],[№ акта]],'Степень зрелости 2025'!$H$13:$I$583,2,FALSE()) -> 42 | AI3: =VLOOKUP(Таблица310[[#This Row],[№ акта]],$AQ$1:$AT$594,2,FALSE()) -> 2/4 | AJ3: =Таблица310[[#This Row],[Регистратор.Номенклатура]] -> Преладо | AK3: =VLOOKUP(Таблица310[[#This Row],[№ акта]],$AQ$1:$AT$594,4,FALSE()) -> Учхоз Кубань (богара) | AL3: =VLOOKUP(Таблица310[[#This Row],[№ акта]],$AQ$1:$AT$594,3,FALSE()) -> 3.6285714 | AM3: =IF(Таблица310[[#This Row],[Площадь уборки, га]]=Таблица310[[#This Row],[Площадь уборки до корр]],"нет","да") -> нет | AN3: =Таблица310[[#This Row],[Площадь уборки до корр]]-Таблица310[[#This Row],[Площадь уборки, га]] -> 0 | AQ3: 45 | AR3: 2/4 | AS3: 3.6285714 | AT3: Учхоз Кубань (богара)
A4: Степень зрелости | B4: 1599 | C4: 37 | D4: 46 | E4: 45804 | F4: 11320 | G4: 2050 | H4: 9270 | I4: 1599 | J4: Грин Рэй Кубань ООО (Овощеводство) | K4: Оскар | L4: А-44 | M4: Сайко Василий Викторович | N4: 18:12:14 | O4: 19:40:31 | Q4: 701 | R4: А816ЕВ | T4: А-44 | U4: =Таблица310[[#This Row],[Регистратор.Номенклатура]] -> Оскар | V4: 1 | W4: ГРК собственные семена (богара) | X4: богара | Y4: 1 | Z4: 45804 | AC4: до 40 | AD4: высший | AE4: 46 | AF4: 45804 | AG4: 1 | AH4: =VLOOKUP(Таблица310[[#This Row],[№ акта]],'Степень зрелости 2025'!$H$13:$I$583,2,FALSE()) -> 37 | AI4: =VLOOKUP(Таблица310[[#This Row],[№ акта]],$AQ$1:$AT$594,2,FALSE()) -> А-44 | AJ4: =Таблица310[[#This Row],[Регистратор.Номенклатура]] -> Оскар | AK4: =VLOOKUP(Таблица310[[#This Row],[№ акта]],$AQ$1:$AT$594,4,FALSE()) -> ГРК собственные семена (богара) | AL4: =VLOOKUP(Таблица310[[#This Row],[№ акта]],$AQ$1:$AT$594,3,FALSE()) -> 1 | AM4: =IF(Таблица310[[#This Row],[Площадь уборки, га]]=Таблица310[[#This Row],[Площадь уборки до корр]],"нет","да") -> нет | AN4: =Таблица310[[#This Row],[Площадь уборки до корр]]-Таблица310[[#This Row],[Площадь уборки, га]] -> 0 | AQ4: 46 | AR4: А-44 | AS4: 1 | AT4: ГРК собственные семена (богара)
A5: Степень зрелости | B5: =Таблица310[[#This Row],[Регистратор.Вес чистый]] -> 11040 | C5: 43 | D5: 47 | E5: 45805 | F5: 27680 | G5: 13800 | H5: 13880 | I5: 11040 | J5: Кубань УОХ | K5: Преладо | L5: 2/4 | M5: Богучарский А. И. | R5: Е404УС | T5: 2/4 | U5: =Таблица310[[#This Row],[Регистратор.Номенклатура]] -> Преладо | V5: =18*Таблица310[[#This Row],[Регистратор.Вес нетто]]/69300 -> 3.5844156 | W5: Учхоз Кубань (богара) | X5: богара | Y5: 1 | Z5: 45804 | AC5: 40-52 | AD5: высший | AE5: 47 | AF5: 45805 | AG5: 65902 | AH5: =VLOOKUP(Таблица310[[#This Row],[№ акта]],'Степень зрелости 2025'!$H$13:$I$583,2,FALSE()) -> #N/A | AI5: =VLOOKUP(Таблица310[[#This Row],[№ акта]],$AQ$1:$AT$594,2,FALSE()) -> 2/4 | AJ5: =Таблица310[[#This Row],[Регистратор.Номенклатура]] -> Преладо | AK5: =VLOOKUP(Таблица310[[#This Row],[№ акта]],$AQ$1:$AT$594,4,FALSE()) -> Учхоз Кубань (богара) | AL5: =VLOOKUP(Таблица310[[#This Row],[№ акта]],$AQ$1:$AT$594,3,FALSE()) -> 3.5844156 | AM5: =IF(Таблица310[[#This Row],[Площадь уборки, га]]=Таблица310[[#This Row],[Площадь уборки до корр]],"нет","да") -> нет | AN5: =Таблица310[[#This Row],[Площадь уборки до корр]]-Таблица310[[#This Row],[Площадь уборки, га]] -> 0 | AQ5: 47 | AR5: 2/4 | AS5: 3.5844156 | AT5: Учхоз Кубань (богара)
A6: Степень зрелости | B6: 11099.5 | C6: 41 | D6: 48 | E6: 45805 | F6: 34970 | G6: 14050 | H6: 20920 | I6: 11099.5 | J6: Кубань УОХ | K6: Преладо | L6: 2/4 | M6: Мудрак Вадим Васильевич | N6: 11:31:14 | O6: 12:47:57 | Q6: 204,003,408,203,407,105 | R6: Х514ОК | S6: ЕУ4356 | T6: 2/4 | U6: =Таблица310[[#This Row],[Регистратор.Номенклатура]] -> Преладо | V6: =18*Таблица310[[#This Row],[Регистратор.Вес нетто]]/69300 -> 3.6493506 | W6: Учхоз Кубань (богара) | X6: богара | Y6: 1 | Z6: 45804 | AC6: 40-52 | AD6: высший | AE6: 48 | AF6: 45805 | AG6: 65903 | AH6: =VLOOKUP(Таблица310[[#This Row],[№ акта]],'Степень зрелости 2025'!$H$13:$I$583,2,FALSE()) -> 41 | AI6: =VLOOKUP(Таблица310[[#This Row],[№ акта]],$AQ$1:$AT$594,2,FALSE()) -> 2/4 | AJ6: =Таблица310[[#This Row],[Регистратор.Номенклатура]] -> Преладо | AK6: =VLOOKUP(Таблица310[[#This Row],[№ акта]],$AQ$1:$AT$594,4,FALSE()) -> Учхоз Кубань (богара) | AL6: =VLOOKUP(Таблица310[[#This Row],[№ акта]],$AQ$1:$AT$594,3,FALSE()) -> 3.6493506 | AM6: =IF(Таблица310[[#This Row],[Площадь уборки, га]]=Таблица310[[#This Row],[Площадь уборки до корр]],"нет","да") -> нет | AN6: =Таблица310[[#This Row],[Площадь уборки до корр]]-Таблица310[[#This Row],[Площадь уборки, га]] -> 0 | AQ6: 48 | AR6: 2/4 | AS6: 3.6493506 | AT6: Учхоз Кубань (богара)
A7: Степень зрелости | B7: 9624.2 | C7: 45 | D7: 52 | E7: 45805 | F7: 28940 | G7: 14050 | H7: 14890 | I7: 9624.2 | J7: Кубань УОХ | K7: Преладо | L7: 2/4 | M7: Егоян Артем Владимирович | N7: 13:56:01 | O7: 14:52:07 | Q7: 005,206,500,004,409,205 | R7: А701СН | S7: ЕН9185 | T7: 2/4 | U7: =Таблица310[[#This Row],[Регистратор.Номенклатура]] -> Преладо | V7: =18*Таблица310[[#This Row],[Регистратор.Вес нетто]]/69300 -> 3.6493506 | W7: Учхоз Кубань (богара) | X7: богара | Y7: 1 | Z7: 45804 | AC7: 40-52 | AD7: высший | AE7: 52 | AF7: 45805 | AG7: 65904 | AH7: =VLOOKUP(Таблица310[[#This Row],[№ акта]],'Степень зрелости 2025'!$H$13:$I$583,2,FALSE()) -> 45 | AI7: =VLOOKUP(Таблица310[[#This Row],[№ акта]],$AQ$1:$AT$594,2,FALSE()) -> 2/4 | AJ7: =Таблица310[[#This Row],[Регистратор.Номенклатура]] -> Преладо | AK7: =VLOOKUP(Таблица310[[#This Row],[№ акта]],$AQ$1:$AT$594,4,FALSE()) -> Учхоз Кубань (богара) | AL7: =VLOOKUP(Таблица310[[#This Row],[№ акта]],$AQ$1:$AT$594,3,FALSE()) -> 3.6493506 | AM7: =IF(Таблица310[[#This Row],[Площадь уборки, га]]=Таблица310[[#This Row],[Площадь уборки до корр]],"нет","да") -> нет | AN7: =Таблица310[[#This Row],[Площадь уборки до корр]]-Таблица310[[#This Row],[Площадь уборки, га]] -> 0 | AQ7: 52 | AR7: 2/4 | AS7: 3.6493506 | AT7: Учхоз Кубань (богара)
A8: Степень зрелости | B8: 9713.3 | C8: 45 | D8: 53 | E8: 45805 | F8: 38160 | G8: 14180 | H8: 24140 | I8: 9713.3 | J8: Кубань УОХ | K8: Преладо | L8: 2/4 | M8: Мудрак Игорь Вадимович | N8: 15:13:11 | O8: 16:09:25 | Q8: 208,007,410,006,411,207 | R8: С198УЕ | S8: ЕУ4355 | T8: 2/4 | U8: =Таблица310[[#This Row],[Регистратор.Номенклатура]] -> Преладо | V8: =27*Таблица310[[#This Row],[Регистратор.Вес нетто]]/98620 -> 3.882174 | W8: Учхоз Кубань (богара) | X8: богара | Y8: 2 | Z8: 45805 | AC8: 40-52 | AD8: высший | AE8: 53 | AF8: 45805 | AG8: 65905 | AH8: =VLOOKUP(Таблица310[[#This Row],[№ акта]],'Степень зрелости 2025'!$H$13:$I$583,2,FALSE()) -> 45 | AI8: =VLOOKUP(Таблица310[[#This Row],[№ акта]],$AQ$1:$AT$594,2,FALSE()) -> 2/4 | AJ8: =Таблица310[[#This Row],[Регистратор.Номенклатура]] -> Преладо | AK8: =VLOOKUP(Таблица310[[#This Row],[№ акта]],$AQ$1:$AT$594,4,FALSE()) -> Учхоз Кубань (богара) | AL8: =VLOOKUP(Таблица310[[#This Row],[№ акта]],$AQ$1:$AT$594,3,FALSE()) -> 3.882174 | AM8: =IF(Таблица310[[#This Row],[Площадь уборки, га]]=Таблица310[[#This Row],[Площадь уборки до корр]],"нет","да") -> нет | AN8: =Таблица310[[#This Row],[Площадь уборки до корр]]-Таблица310[[#This Row],[Площадь уборки, га]] -> 0 | AQ8: 53 | AR8: 2/4 | AS8: 3.882174 | AT8: Учхоз Кубань (богара)
A9: Степень зрелости | B9: 9806.4 | C9: 44 | D9: 54 | E9: 45805 | F9: 29800 | G9: 14110 | H9: 15690 | I9: 9806.4 | J9: Кубань УОХ | K9: Преладо | L9: 2/4 | M9: Пугачев Сергей Викторович | N9: 17:34:52 | O9: 18:31:53 | Q9: 210,008,413,209,412,009 | R9: Р258УХ | S9: МО9466 | T9: 2/4 | U9: =Таблица310[[#This Row],[Регистратор.Номенклатура]] -> Преладо | V9: =27*Таблица310[[#This Row],[Регистратор.Вес нетто]]/98620 -> 3.8630095 | W9: Учхоз Кубань (богара) | X9: богара | Y9: 2 | Z9: 45805 | AC9: 40-52 | AD9: высший | AE9: 54 | AF9: 45805 | AG9: 65907 | AH9: =VLOOKUP(Таблица310[[#This Row],[№ акта]],'Степень зрелости 2025'!$H$13:$I$583,2,FALSE()) -> 44 | AI9: =VLOOKUP(Таблица310[[#This Row],[№ акта]],$AQ$1:$AT$594,2,FALSE()) -> 2/4 | AJ9: =Таблица310[[#This Row],[Регистратор.Номенклатура]] -> Преладо | AK9: =VLOOKUP(Таблица310[[#This Row],[№ акта]],$AQ$1:$AT$594,4,FALSE()) -> Учхоз Кубань (богара) | AL9: =VLOOKUP(Таблица310[[#This Row],[№ акта]],$AQ$1:$AT$594,3,FALSE()) -> 3.8630095 | AM9: =IF(Таблица310[[#This Row],[Площадь уборки, га]]=Таблица310[[#This Row],[Площадь уборки до корр]],"нет","да") -> нет | AN9: =Таблица310[[#This Row],[Площадь уборки до корр]]-Таблица310[[#This Row],[Площадь уборки, га]] -> 0 | AQ9: 54 | AR9: 2/4 | AS9: 3.8630095 | AT9: Учхоз Кубань (богара)
A10: Степень зрелости | B10: 10519.7 | C10: 44 | D10: 55 | E10: 45805 | F10: 29560 | G10: 14510 | H10: 15050 | I10: 10519.7 | J10: Кубань УОХ | K10: Преладо | L10: 2/4 | M10: Никитась Сергей Анатольевич | N10: 19:59:17 | O10: 21:40:42 | Q10: 012,011,415,211,414,010 | R10: К570ЕО | S10: ЕС6735 | T10: 2/4 | U10: =Таблица310[[#This Row],[Регистратор.Номенклатура]] -> Преладо | V10: =27*Таблица310[[#This Row],[Регистратор.Вес нетто]]/98620 -> 3.9725208 | W10: Учхоз Кубань (богара) | X10: богара | Y10: 2 | Z10: 45805 | AC10: 40-52 | AD10: высший | AE10: 55 | AF10: 45805 | AG10: 65906 | AH10: =VLOOKUP(Таблица310[[#This Row],[№ акта]],'Степень зрелости 2025'!$H$13:$I$583,2,FALSE()) -> 44 | AI10: =VLOOKUP(Таблица310[[#This Row],[№ акта]],$AQ$1:$AT$594,2,FALSE()) -> 2/4 | AJ10: =Таблица310[[#This Row],[Регистратор.Номенклатура]] -> Преладо | AK10: =VLOOKUP(Таблица310[[#This Row],[№ акта]],$AQ$1:$AT$594,4,FALSE()) -> Учхоз Кубань (богара) | AL10: =VLOOKUP(Таблица310[[#This Row],[№ акта]],$AQ$1:$AT$594,3,FALSE()) -> 3.9725208 | AM10: =IF(Таблица310[[#This Row],[Площадь уборки, га]]=Таблица310[[#This Row],[Площадь уборки до корр]],"нет","да") -> нет | AN10: =Таблица310[[#This Row],[Площадь уборки до корр]]-Таблица310[[#This Row],[Площадь уборки, га]] -> 0 | AQ10: 55 | AR10: 2/4 | AS10: 3.9725208 | AT10: Учхоз Кубань (богара)
A11: Степень зрелости | B11: 9792.5 | C11: 43 | D11: 56 | E11: 45805 | F11: 28960 | G11: 14090 | H11: 14870 | I11: 9792.5 | J11: Кубань УОХ | K11: Преладо | L11: 2/4 | M11: Кулик О В | N11: 22:28:12 | O11: 23:13:11 | Q11: 014,213,416,212,417,013 | R11: К403ЕМ | S11: ЕС6095 | T11: 2/4 | U11: =Таблица310[[#This Row],[Регистратор.Номенклатура]] -> Преладо | V11: =27*Таблица310[[#This Row],[Регистратор.Вес нетто]]/98620 -> 3.857534 | W11: Учхоз Кубань (богара) | X11: богара | Y11: 2 | Z11: 45805 | AC11: 40-52 | AD11: высший | AE11: 56 | AF11: 45805 | AG11: 65908 | AH11: =VLOOKUP(Таблица310[[#This Row],[№ акта]],'Степень зрелости 2025'!$H$13:$I$583,2,FALSE()) -> 43 | AI11: =VLOOKUP(Таблица310[[#This Row],[№ акта]],$AQ$1:$AT$594,2,FALSE()) -> 2/4 | AJ11: =Таблица310[[#This Row],[Регистратор.Номенклатура]] -> Преладо | AK11: =VLOOKUP(Таблица310[[#This Row],[№ акта]],$AQ$1:$AT$594,4,FALSE()) -> Учхоз Кубань (богара) | AL11: =VLOOKUP(Таблица310[[#This Row],[№ акта]],$AQ$1:$AT$594,3,FALSE()) -> 3.857534 | AM11: =IF(Таблица310[[#This Row],[Площадь уборки, га]]=Таблица310[[#This Row],[Площадь уборки до корр]],"нет","да") -> нет | AN11: =Таблица310[[#This Row],[Площадь уборки до корр]]-Таблица310[[#This Row],[Площадь уборки, га]] -> 0 | AQ11: 56 | AR11: 2/4 | AS11: 3.857534 | AT11: Учхоз Кубань (богара)
A12: Степень зрелости | B12: 9588 | C12: 42 | D12: 57 | E12: 45806 | F12: 28680 | G12: 14100 | H12: 14580 | I12: 9588 | J12: Кубань УОХ | K12: Преладо | L12: 2/4 | M12: Сероштан Станислав Викторович | N12: 23:57:00 | O12: 1:11:23 | Q12: 216,016,215,015,418,214 | R12: Е758РЕ | S12: ЕХ4191 | T12: 2/4 | U12: =Таблица310[[#This Row],[Регистратор.Номенклатура]] -> Преладо | V12: =27*Таблица310[[#This Row],[Регистратор.Вес нетто]]/98620 -> 3.8602718 | W12: Учхоз Кубань (богара) | X12: богара | Y12: 2 | Z12: 45805 | AC12: 40-52 | AD12: высший | AE12: 57 | AF12: 45806 | AG12: 65909 | AH12: =VLOOKUP(Таблица310[[#This Row],[№ акта]],'Степень зрелости 2025'!$H$13:$I$583,2,FALSE()) -> 42 | AI12: =VLOOKUP(Таблица310[[#This Row],[№ акта]],$AQ$1:$AT$594,2,FALSE()) -> 2/4 | AJ12: =Таблица310[[#This Row],[Регистратор.Номенклатура]] -> Преладо | AK12: =VLOOKUP(Таблица310[[#This Row],[№ акта]],$AQ$1:$AT$594,4,FALSE()) -> Учхоз Кубань (богара) | AL12: =VLOOKUP(Таблица310[[#This Row],[№ акта]],$AQ$1:$AT$594,3,FALSE()) -> 3.8602718 | AM12: =IF(Таблица310[[#This Row],[Площадь уборки, га]]=Таблица310[[#This Row],[Площадь уборки до корр]],"нет","да") -> нет | AN12: =Таблица310[[#This Row],[Площадь уборки до корр]]-Таблица310[[#This Row],[Площадь уборки, га]] -> 0 | AQ12: 57 | AR12: 2/4 | AS12: 3.8602718 | AT12: Учхоз Кубань (богара)
A13: Степень зрелости | B13: 10150 | C13: 45 | D13: 58 | E13: 45806 | F13: 28830 | G13: 14000 | H13: 14830 | I13: 10150 | J13: Кубань УОХ | K13: Преладо | L13: 2/4 | M13: Фомин Николай Григорьевич | N13: 2:11:42 | O13: 2:55:07 | Q13: 218,018,420,419,217,017 | R13: А731ВА | S13: МО8130 | T13: 2/4 | U13: =Таблица310[[#This Row],[Регистратор.Номенклатура]] -> Преладо | V13: =27*Таблица310[[#This Row],[Регистратор.Вес нетто]]/98620 -> 3.8328939 | W13: Учхоз Кубань (богара) | X13: богара | Y13: 2 | Z13: 45805 | AC13: 40-52 | AD13: высший | AE13: 58 | AF13: 45806 | AG13: 65910 | AH13: =VLOOKUP(Таблица310[[#This Row],[№ акта]],'Степень зрелости 2025'!$H$13:$I$583,2,FALSE()) -> 45 | AI13: =VLOOKUP(Таблица310[[#This Row],[№ акта]],$AQ$1:$AT$594,2,FALSE()) -> 2/4 | AJ13: =Таблица310[[#This Row],[Регистратор.Номенклатура]] -> Преладо | AK13: =VLOOKUP(Таблица310[[#This Row],[№ акта]],$AQ$1:$AT$594,4,FALSE()) -> Учхоз Кубань (богара) | AL13: =VLOOKUP(Таблица310[[#This Row],[№ акта]],$AQ$1:$AT$594,3,FALSE()) -> 3.8328939 | AM13: =IF(Таблица310[[#This Row],[Площадь уборки, га]]=Таблица310[[#This Row],[Площадь уборки до корр]],"нет","да") -> нет | AN13: =Таблица310[[#This Row],[Площадь уборки до корр]]-Таблица310[[#This Row],[Площадь уборки, га]] -> 0 | AQ13: 58 | AR13: 2/4 | AS13: 3.8328939 | AT13: Учхоз Кубань (богара)
A14: Степень зрелости | B14: 9653 | C14: 45 | D14: 59 | E14: 45806 | F14: 29110 | G14: 13790 | H14: 15320 | I14: 9653 | J14: Кубань УОХ | K14: Преладо | L14: 2/4 | M14: Игольницын Сергей Владимирович | N14: 3:30:03 | O14: 5:27:33 | Q14: 020,220,422,019,421,219 | R14: В780ТТ | S14: МС8607 | T14: 2/4 | U14: =Таблица310[[#This Row],[Регистратор.Номенклатура]] -> Преладо | V14: =27*Таблица310[[#This Row],[Регистратор.Вес нетто]]/98620 -> 3.7754005 | W14: Учхоз Кубань (богара) | X14: богара | Y14: 2 | Z14: 45805 | AC14: 40-52 | AD14: высший | AE14: 59 | AF14: 45806 | AG14: 65911 | AH14: =VLOOKUP(Таблица310[[#This Row],[№ акта]],'Степень зрелости 2025'!$H$13:$I$583,2,FALSE()) -> 45 | AI14: =VLOOKUP(Таблица310[[#This Row],[№ акта]],$AQ$1:$AT$594,2,FALSE()) -> 2/4 | AJ14: =Таблица310[[#This Row],[Регистратор.Номенклатура]] -> Преладо | AK14: =VLOOKUP(Таблица310[[#This Row],[№ акта]],$AQ$1:$AT$594,4,FALSE()) -> Учхоз Кубань (богара) | AL14: =VLOOKUP(Таблица310[[#This Row],[№ акта]],$AQ$1:$AT$594,3,FALSE()) -> 3.7754005 | AM14: =IF(Таблица310[[#This Row],[Площадь уборки, га]]=Таблица310[[#This Row],[Площадь уборки до корр]],"нет","да") -> нет | AN14: =Таблица310[[#This Row],[Площадь уборки до корр]]-Таблица310[[#This Row],[Площадь уборки, га]] -> 0 | AQ14: 59 | AR14: 2/4 | AS14: 3.7754005 | AT14: Учхоз Кубань (богара)
A15: Степень зрелости | B15: 3080.6 | C15: 41 | D15: 72 | E15: 45806 | F15: 13930 | G15: 4220 | H15: 9710 | I15: 3080.6 | J15: Грин Рэй Кубань ООО (Овощеводство) | K15: Оскар | L15: А-44 | M15: Игольницын Сергей Владимирович | N15: 15:30:03 | O15: 15:50:01 | Q15: 702.703 | R15: В780ТТ | S15: МС8607 | T15: А-44 | U15: =Таблица310[[#This Row],[Регистратор.Номенклатура]] -> Оскар | V15: =5*Таблица310[[#This Row],[Регистратор.Вес нетто]]/10740 -> 1.9646182 | W15: ГРК собственные семена (богара) | X15: богара | Y15: 2 | Z15: 45806 | AC15: 40-52 | AD15: высший | AE15: 72 | AF15: 45806 | AG15: 2 | AH15: =VLOOKUP(Таблица310[[#This Row],[№ акта]],'Степень зрелости 2025'!$H$13:$I$583,2,FALSE()) -> 41 | AI15: =VLOOKUP(Таблица310[[#This Row],[№ акта]],$AQ$1:$AT$594,2,FALSE()) -> А-44 | AJ15: =Таблица310[[#This Row],[Регистратор.Номенклатура]] -> Оскар | AK15: =VLOOKUP(Таблица310[[#This Row],[№ акта]],$AQ$1:$AT$594,4,FALSE()) -> ГРК собственные семена (богара) | AL15: =VLOOKUP(Таблица310[[#This Row],[№ акта]],$AQ$1:$AT$594,3,FALSE()) -> 1.9646182 | AM15: =IF(Таблица310[[#This Row],[Площадь уборки, га]]=Таблица310[[#This Row],[Площадь уборки до корр]],"нет","да") -> нет | AN15: =Таблица310[[#This Row],[Площадь уборки до корр]]-Таблица310[[#This Row],[Площадь уборки, га]] -> 0 | AQ15: 72 | AR15: А-44 | AS15: 1.9646182 | AT15: ГРК собственные семена (богара)
A16: Степень зрелости | B16: 5020.4 | C16: 44 | D16: 73 | E16: 45806 | F16: 21910 | G16: 6520 | H16: 15390 | I16: 5020.4 | J16: Грин Рэй Кубань ООО (Овощеводство) | K16: Оскар | L16: А-44 | M16: Игольницын Сергей Владимирович | N16: 19:59:17 | O16: 20:21:39 | Q16: 704,801,705 | R16: В780ТТ | S16: МС8607 | T16: А-44 | U16: =Таблица310[[#This Row],[Регистратор.Номенклатура]] -> Оскар | V16: =5*Таблица310[[#This Row],[Регистратор.Вес нетто]]/10740 -> 3.0353818 | W16: ГРК собственные семена (богара) | X16: богара | Y16: 2 | Z16: 45806 | AC16: 40-52 | AD16: высший | AE16: 73 | AF16: 45806 | AG16: 3 | AH16: =VLOOKUP(Таблица310[[#This Row],[№ акта]],'Степень зрелости 2025'!$H$13:$I$583,2,FALSE()) -> 44 | AI16: =VLOOKUP(Таблица310[[#This Row],[№ акта]],$AQ$1:$AT$594,2,FALSE()) -> А-44 | AJ16: =Таблица310[[#This Row],[Регистратор.Номенклатура]] -> Оскар | AK16: =VLOOKUP(Таблица310[[#This Row],[№ акта]],$AQ$1:$AT$594,4,FALSE()) -> ГРК собственные семена (богара) | AL16: =VLOOKUP(Таблица310[[#This Row],[№ акта]],$AQ$1:$AT$594,3,FALSE()) -> 3.0353818 | AM16: =IF(Таблица310[[#This Row],[Площадь уборки, га]]=Таблица310[[#This Row],[Площадь уборки до корр]],"нет","да") -> нет | AN16: =Таблица310[[#This Row],[Площадь уборки до корр]]-Таблица310[[#This Row],[Площадь уборки, га]] -> 0 | AQ16: 73 | AR16: А-44 | AS16: 3.0353818 | AT16: ГРК собственные семена (богара)
A17: Степень зрелости | B17: 3306.9 | C17: 43 | D17: 74 | E17: 45808 | F17: 14120 | G17: 4380 | H17: 9740 | I17: 3306.9 | J17: Грин Рэй Кубань ООО (Овощеводство) | K17: Оскар | L17: А-44 | M17: Чигрин Н.А. | N17: 8:40:44 | O17: 8:50:06 | Q17: 706.901 | R17: А819ЕВ | S17: ЕС2899 | T17: А-44 | U17: =Таблица310[[#This Row],[Регистратор.Номенклатура]] -> Оскар | V17: =30*Таблица310[[#This Row],[Регистратор.Вес нетто]]/55610 -> 2.3628844 | W17: ГРК собственные семена (богара) | X17: богара | Y17: 3 | Z17: 45808 | AC17: 40-52 | AD17: высший | AE17: 74 | AF17: 45808 | AG17: 4 | AH17: =VLOOKUP(Таблица310[[#This Row],[№ акта]],'Степень зрелости 2025'!$H$13:$I$583,2,FALSE()) -> 43 | AI17: =VLOOKUP(Таблица310[[#This Row],[№ акта]],$AQ$1:$AT$594,2,FALSE()) -> А-44 | AJ17: =Таблица310[[#This Row],[Регистратор.Номенклатура]] -> Оскар | AK17: =VLOOKUP(Таблица310[[#This Row],[№ акта]],$AQ$1:$AT$594,4,FALSE()) -> ГРК собственные семена (богара) | AL17: =VLOOKUP(Таблица310[[#This Row],[№ акта]],$AQ$1:$AT$594,3,FALSE()) -> 2.3628844 | AM17: =IF(Таблица310[[#This Row],[Площадь уборки, га]]=Таблица310[[#This Row],[Площадь уборки до корр]],"нет","да") -> нет | AN17: =Таблица310[[#This Row],[Площадь уборки до корр]]-Таблица310[[#This Row],[Площадь уборки, га]] -> 0 | AQ17: 74 | AR17: А-44 | AS17: 2.3628844 | AT17: ГРК собственные семена (богара)
A18: Степень зрелости | B18: 3557.2 | C18: 42 | D18: 75 | E18: 45808 | F18: 14320 | G18: 4590 | H18: 9730 | I18: 3557.2 | J18: Грин Рэй Кубань ООО (Овощеводство) | K18: Оскар | L18: А-44 | M18: Чигрин Н.А. | N18: 9:40:06 | O18: 9:51:07 | Q18: 707.902 | R18: А819ЕВ | S18: ЕС2899 | T18: А-44 | U18: =Таблица310[[#This Row],[Регистратор.Номенклатура]] -> Оскар | V18: =30*Таблица310[[#This Row],[Регистратор.Вес нетто]]/55610 -> 2.4761734 | W18: ГРК собственные семена (богара) | X18: богара | Y18: 3 | Z18: 45808 | AC18: 40-52 | AD18: высший | AE18: 75 | AF18: 45808 | AG18: 5 | AH18: =VLOOKUP(Таблица310[[#This Row],[№ акта]],'Степень зрелости 2025'!$H$13:$I$583,2,FALSE()) -> 42 | AI18: =VLOOKUP(Таблица310[[#This Row],[№ акта]],$AQ$1:$AT$594,2,FALSE()) -> А-44 | AJ18: =Таблица310[[#This Row],[Регистратор.Номенклатура]] -> Оскар | AK18: =VLOOKUP(Таблица310[[#This Row],[№ акта]],$AQ$1:$AT$594,4,FALSE()) -> ГРК собственные семена (богара) | AL18: =VLOOKUP(Таблица310[[#This Row],[№ акта]],$AQ$1:$AT$594,3,FALSE()) -> 2.4761734 | AM18: =IF(Таблица310[[#This Row],[Площадь уборки, га]]=Таблица310[[#This Row],[Площадь уборки до корр]],"нет","да") -> нет | AN18: =Таблица310[[#This Row],[Площадь уборки до корр]]-Таблица310[[#This Row],[Площадь уборки, га]] -> 0 | AQ18: 75 | AR18: А-44 | AS18: 2.4761734 | AT18: ГРК собственные семена (богара)
A19: Степень зрелости | B19: 6263.4 | C19: 45 | D19: 76 | E19: 45808 | F19: 23120 | G19: 8760 | H19: 14360 | I19: 6263.4 | J19: Грин Рэй Кубань ООО (Овощеводство) | K19: Оскар | L19: А-44 | M19: Чигрин Н.А. | N19: 11:45:06 | O19: 12:01:00 | Q19: 709,904,708,903 | R19: А819ЕВ | S19: ЕС2899 | T19: А-44 | U19: =Таблица310[[#This Row],[Регистратор.Номенклатура]] -> Оскар | V19: =30*Таблица310[[#This Row],[Регистратор.Вес нетто]]/55610 -> 4.7257687 | W19: ГРК собственные семена (богара) | X19: богара | Y19: 3 | Z19: 45808 | AC19: 40-52 | AD19: высший | AE19: 76 | AF19: 45808 | AG19: 6 | AH19: =VLOOKUP(Таблица310[[#This Row],[№ акта]],'Степень зрелости 2025'!$H$13:$I$583,2,FALSE()) -> 45 | AI19: =VLOOKUP(Таблица310[[#This Row],[№ акта]],$AQ$1:$AT$594,2,FALSE()) -> А-44 | AJ19: =Таблица310[[#This Row],[Регистратор.Номенклатура]] -> Оскар | AK19: =VLOOKUP(Таблица310[[#This Row],[№ акта]],$AQ$1:$AT$594,4,FALSE()) -> ГРК собственные семена (богара) | AL19: =VLOOKUP(Таблица310[[#This Row],[№ акта]],$AQ$1:$AT$594,3,FALSE()) -> 4.7257687 | AM19: =IF(Таблица310[[#This Row],[Площадь уборки, га]]=Таблица310[[#This Row],[Площадь уборки до корр]],"нет","да") -> нет | AN19: =Таблица310[[#This Row],[Площадь уборки до корр]]-Таблица310[[#This Row],[Площадь уборки, га]] -> 0 | AQ19: 76 | AR19: А-44 | AS19: 4.7257687 | AT19: ГРК собственные семена (богара)
A20: Степень зрелости | B20: =Таблица310[[#This Row],[Регистратор.Вес чистый]] -> 3291.3 | C20: 45 | D20: 77 | E20: 45808 | F20: 14470 | G20: 4770 | H20: 9700 | I20: 3291.3 | J20: Грин Рэй Кубань ООО (Овощеводство) | K20: Оскар | L20: А-44 | M20: Чигрин Н.А. | R20: А819ЕВ | T20: А-44 | U20: =Таблица310[[#This Row],[Регистратор.Номенклатура]] -> Оскар | V20: =30*Таблица310[[#This Row],[Регистратор.Вес нетто]]/55610 -> 2.5732782 | W20: ГРК собственные семена (богара) | X20: богара | Y20: 3 | Z20: 45808 | AC20: 40-52 | AD20: высший | AE20: 77 | AF20: 45808 | AG20: 7 | AH20: =VLOOKUP(Таблица310[[#This Row],[№ акта]],'Степень зрелости 2025'!$H$13:$I$583,2,FALSE()) -> 45 | AI20: =VLOOKUP(Таблица310[[#This Row],[№ акта]],$AQ$1:$AT$594,2,FALSE()) -> А-44 | AJ20: =Таблица310[[#This Row],[Регистратор.Номенклатура]] -> Оскар | AK20: =VLOOKUP(Таблица310[[#This Row],[№ акта]],$AQ$1:$AT$594,4,FALSE()) -> ГРК собственные семена (богара) | AL20: =VLOOKUP(Таблица310[[#This Row],[№ акта]],$AQ$1:$AT$594,3,FALSE()) -> 2.5732782 | AM20: =IF(Таблица310[[#This Row],[Площадь уборки, га]]=Таблица310[[#This Row],[Площадь уборки до корр]],"нет","да") -> нет | AN20: =Таблица310[[#This Row],[Площадь уборки до корр]]-Таблица310[[#This Row],[Площадь уборки, га]] -> 0 | AQ20: 77 | AR20: А-44 | AS20: 2.5732782 | AT20: ГРК собственные семена (богара)
A21: Степень зрелости | B21: 2981.5 | C21: 45 | D21: 78 | E21: 45808 | F21: 14140 | G21: 4450 | H21: 9690 | I21: 2981.5 | J21: Грин Рэй Кубань ООО (Овощеводство) | K21: Оскар | L21: А-44 | M21: Чигрин Н.А. | N21: 16:08:24 | O21: 16:18:09 | Q21: 710.907 | R21: А819ЕВ | S21: ЕС2899 | T21: А-44 | U21: =Таблица310[[#This Row],[Регистратор.Номенклатура]] -> Оскар | V21: =30*Таблица310[[#This Row],[Регистратор.Вес нетто]]/55610 -> 2.4006474 | W21: ГРК собственные семена (богара) | X21: богара | Y21: 3 | Z21: 45808 | AC21: 40-52 | AD21: высший | AE21: 78 | AF21: 45808 | AG21: 8 | AH21: =VLOOKUP(Таблица310[[#This Row],[№ акта]],'Степень зрелости 2025'!$H$13:$I$583,2,FALSE()) -> 45 | AI21: =VLOOKUP(Таблица310[[#This Row],[№ акта]],$AQ$1:$AT$594,2,FALSE()) -> А-44 | AJ21: =Таблица310[[#This Row],[Регистратор.Номенклатура]] -> Оскар | AK21: =VLOOKUP(Таблица310[[#This Row],[№ акта]],$AQ$1:$AT$594,4,FALSE()) -> ГРК собственные семена (богара) | AL21: =VLOOKUP(Таблица310[[#This Row],[№ акта]],$AQ$1:$AT$594,3,FALSE()) -> 2.4006474 | AM21: =IF(Таблица310[[#This Row],[Площадь уборки, га]]=Таблица310[[#This Row],[Площадь уборки до корр]],"нет","да") -> нет | AN21: =Таблица310[[#This Row],[Площадь уборки до корр]]-Таблица310[[#This Row],[Площадь уборки, га]] -> 0 | AQ21: 78 | AR21: А-44 | AS21: 2.4006474 | AT21: ГРК собственные семена (богара)
A22: Степень зрелости | B22: 7171 | C22: 46 | D22: 79 | E22: 45808 | F22: 24430 | G22: 10100 | H22: 14330 | I22: 7171 | J22: Грин Рэй Кубань ООО (Овощеводство) | K22: Оскар | L22: А-44 | M22: Чигрин Н.А. | N22: 19:04:44 | O22: 19:18:58 | Q22: 711,908,712,909,713 | R22: А819ЕВ | S22: ЕС2899 | T22: А-44 | U22: =Таблица310[[#This Row],[Регистратор.Номенклатура]] -> Оскар | V22: =30*Таблица310[[#This Row],[Регистратор.Вес нетто]]/55610 -> 5.4486603 | W22: ГРК собственные семена (богара) | X22: богара | Y22: 3 | Z22: 45808 | AC22: 40-52 | AD22: высший | AE22: 79 | AF22: 45808 | AG22: 9 | AH22: =VLOOKUP(Таблица310[[#This Row],[№ акта]],'Степень зрелости 2025'!$H$13:$I$583,2,FALSE()) -> 46 | AI22: =VLOOKUP(Таблица310[[#This Row],[№ акта]],$AQ$1:$AT$594,2,FALSE()) -> А-44 | AJ22: =Таблица310[[#This Row],[Регистратор.Номенклатура]] -> Оскар | AK22: =VLOOKUP(Таблица310[[#This Row],[№ акта]],$AQ$1:$AT$594,4,FALSE()) -> ГРК собственные семена (богара) | AL22: =VLOOKUP(Таблица310[[#This Row],[№ акта]],$AQ$1:$AT$594,3,FALSE()) -> 5.4486603 | AM22: =IF(Таблица310[[#This Row],[Площадь уборки, га]]=Таблица310[[#This Row],[Площадь уборки до корр]],"нет","да") -> нет | AN22: =Таблица310[[#This Row],[Площадь уборки до корр]]-Таблица310[[#This Row],[Площадь уборки, га]] -> 0 | AQ22: 79 | AR22: А-44 | AS22: 5.4486603 | AT22: ГРК собственные семена (богара)
A23: Степень зрелости | B23: 7130.2 | C23: 50 | D23: 80 | E23: 45808 | F23: 23580 | G23: 9260 | H23: 14320 | I23: 7130.2 | J23: Грин Рэй Кубань ООО (Овощеводство) | K23: Оскар | L23: А-44 | M23: Чигрин Н.А. | N23: 21:56:51 | O23: 22:29:34 | Q23: 716,715,910,714 | R23: А819ЕВ | S23: ЕС2899 | T23: А-44 | U23: =Таблица310[[#This Row],[Регистратор.Номенклатура]] -> Оскар | V23: =30*Таблица310[[#This Row],[Регистратор.Вес нетто]]/55610 -> 4.9955044 | W23: ГРК собственные семена (богара) | X23: богара | Y23: 3 | Z23: 45808 | AC23: 40-52 | AD23: высший | AE23: 80 | AF23: 45808 | AG23: 10 | AH23: =VLOOKUP(Таблица310[[#This Row],[№ акта]],'Степень зрелости 2025'!$H$13:$I$583,2,FALSE()) -> 50 | AI23: =VLOOKUP(Таблица310[[#This Row],[№ акта]],$AQ$1:$AT$594,2,FALSE()) -> А-44 | AJ23: =Таблица310[[#This Row],[Регистратор.Номенклатура]] -> Оскар | AK23: =VLOOKUP(Таблица310[[#This Row],[№ акта]],$AQ$1:$AT$594,4,FALSE()) -> ГРК собственные семена (богара) | AL23: =VLOOKUP(Таблица310[[#This Row],[№ акта]],$AQ$1:$AT$594,3,FALSE()) -> 4.9955044 | AM23: =IF(Таблица310[[#This Row],[Площадь уборки, га]]=Таблица310[[#This Row],[Площадь уборки до корр]],"нет","да") -> нет | AN23: =Таблица310[[#This Row],[Площадь уборки до корр]]-Таблица310[[#This Row],[Площадь уборки, га]] -> 0 | AQ23: 80 | AR23: А-44 | AS23: 4.9955044 | AT23: ГРК собственные семена (богара)
A24: Степень зрелости | B24: 6789 | C24: 49 | D24: 81 | E24: 45809 | F24: 23620 | G24: 9300 | H24: 14320 | I24: 6789 | J24: Грин Рэй Кубань ООО (Овощеводство) | K24: Оскар | L24: А-44 | M24: Чигрин Н.А. | N24: 1:08:40 | O24: 1:34:12 | Q24: 912,718,717,911 | R24: А819ЕВ | T24: А-44 | U24: =Таблица310[[#This Row],[Регистратор.Номенклатура]] -> Оскар | V24: =30*Таблица310[[#This Row],[Регистратор.Вес нетто]]/55610 -> 5.0170833 | W24: ГРК собственные семена (богара) | X24: богара | Y24: 3 | Z24: 45808 | AC24: 40-52 | AD24: высший | AE24: 81 | AF24: 45809 | AG24: 11 | AH24: =VLOOKUP(Таблица310[[#This Row],[№ акта]],'Степень зрелости 2025'!$H$13:$I$583,2,FALSE()) -> 49 | AI24: =VLOOKUP(Таблица310[[#This Row],[№ акта]],$AQ$1:$AT$594,2,FALSE()) -> А-44 | AJ24: =Таблица310[[#This Row],[Регистратор.Номенклатура]] -> Оскар | AK24: =VLOOKUP(Таблица310[[#This Row],[№ акта]],$AQ$1:$AT$594,4,FALSE()) -> ГРК собственные семена (богара) | AL24: =VLOOKUP(Таблица310[[#This Row],[№ акта]],$AQ$1:$AT$594,3,FALSE()) -> 5.0170833 | AM24: =IF(Таблица310[[#This Row],[Площадь уборки, га]]=Таблица310[[#This Row],[Площадь уборки до корр]],"нет","да") -> нет | AN24: =Таблица310[[#This Row],[Площадь уборки до корр]]-Таблица310[[#This Row],[Площадь уборки, га]] -> 0 | AQ24: 81 | AR24: А-44 | AS24: 5.0170833 | AT24: ГРК собственные семена (богара)
A25: Степень зрелости | B25: 6688.8 | C25: 49 | D25: 82 | E25: 45809 | F25: 23600 | G25: 9290 | H25: 14310 | I25: 6688.8 | J25: Грин Рэй Кубань ООО (Овощеводство) | K25: Оскар | L25: А-44 | M25: Чигрин Н.А. | N25: 4:24:42 | O25: 4:45:36 | Q25: 721,913,720,719 | R25: А819ЕВ | S25: ЕС2899 | T25: А-44 | U25: =Таблица310[[#This Row],[Регистратор.Номенклатура]] -> Оскар | V25: =26*Таблица310[[#This Row],[Регистратор.Вес нетто]]/69140 -> 3.4934915 | W25: ГРК собственные семена (богара) | X25: богара | Y25: 4 | Z25: 45809 | AC25: 40-52 | AD25: высший | AE25: 82 | AF25: 45809 | AG25: 12 | AH25: =VLOOKUP(Таблица310[[#This Row],[№ акта]],'Степень зрелости 2025'!$H$13:$I$583,2,FALSE()) -> 49 | AI25: =VLOOKUP(Таблица310[[#This Row],[№ акта]],$AQ$1:$AT$594,2,FALSE()) -> А-44 | AJ25: =Таблица310[[#This Row],[Регистратор.Номенклатура]] -> Оскар | AK25: =VLOOKUP(Таблица310[[#This Row],[№ акта]],$AQ$1:$AT$594,4,FALSE()) -> ГРК собственные семена (богара) | AL25: =VLOOKUP(Таблица310[[#This Row],[№ акта]],$AQ$1:$AT$594,3,FALSE()) -> 3.4934915 | AM25: =IF(Таблица310[[#This Row],[Площадь уборки, га]]=Таблица310[[#This Row],[Площадь уборки до корр]],"нет","да") -> нет | AN25: =Таблица310[[#This Row],[Площадь уборки до корр]]-Таблица310[[#This Row],[Площадь уборки, га]] -> 0 | AQ25: 82 | AR25: А-44 | AS25: 3.4934915 | AT25: ГРК собственные семена (богара)
A26: Степень зрелости | B26: 7212.7 | C26: 50 | D26: 83 | E26: 45809 | F26: 23430 | G26: 9130 | H26: 14300 | I26: 7212.7 | J26: Грин Рэй Кубань ООО (Овощеводство) | K26: Оскар | L26: А-44 | M26: Чигрин Н.А. | N26: 7:14:08 | O26: 7:33:01 | Q26: 724,723,914,722 | R26: А819ЕВ | S26: ЕС2899 | T26: А-44 | U26: =Таблица310[[#This Row],[Регистратор.Номенклатура]] -> Оскар | V26: =26*Таблица310[[#This Row],[Регистратор.Вес нетто]]/69140 -> 3.4333237 | W26: ГРК собственные семена (богара) | X26: богара | Y26: 4 | Z26: 45809 | AC26: 40-52 | AD26: высший | AE26: 83 | AF26: 45809 | AG26: 13 | AH26: =VLOOKUP(Таблица310[[#This Row],[№ акта]],'Степень зрелости 2025'!$H$13:$I$583,2,FALSE()) -> 50 | AI26: =VLOOKUP(Таблица310[[#This Row],[№ акта]],$AQ$1:$AT$594,2,FALSE()) -> А-44 | AJ26: =Таблица310[[#This Row],[Регистратор.Номенклатура]] -> Оскар | AK26: =VLOOKUP(Таблица310[[#This Row],[№ акта]],$AQ$1:$AT$594,4,FALSE()) -> ГРК собственные семена (богара) | AL26: =VLOOKUP(Таблица310[[#This Row],[№ акта]],$AQ$1:$AT$594,3,FALSE()) -> 3.4333237 | AM26: =IF(Таблица310[[#This Row],[Площадь уборки, га]]=Таблица310[[#This Row],[Площадь уборки до корр]],"нет","да") -> нет | AN26: =Таблица310[[#This Row],[Площадь уборки до корр]]-Таблица310[[#This Row],[Площадь уборки, га]] -> 0 | AQ26: 83 | AR26: А-44 | AS26: 3.4333237 | AT26: ГРК собственные семена (богара)
A27: Степень зрелости | B27: 3182 | C27: 50 | D27: 84 | E27: 45809 | F27: 18150 | G27: 4300 | H27: 13850 | I27: 3182 | J27: Грин Рэй Кубань ООО (Овощеводство) | K27: Оскар | L27: А-44 | M27: Богучарский А. И. | N27: 11:06:34 | O27: 11:24:07 | Q27: 725.726 | R27: Е404УС | T27: А-44 | U27: =Таблица310[[#This Row],[Регистратор.Номенклатура]] -> Оскар | V27: =26*Таблица310[[#This Row],[Регистратор.Вес нетто]]/69140 -> 1.617009 | W27: ГРК собственные семена (богара) | X27: богара | Y27: 4 | Z27: 45809 | AC27: 40-52 | AD27: высший | AE27: 84 | AF27: 45809 | AG27: 14 | AH27: =VLOOKUP(Таблица310[[#This Row],[№ акта]],'Степень зрелости 2025'!$H$13:$I$583,2,FALSE()) -> 50 | AI27: =VLOOKUP(Таблица310[[#This Row],[№ акта]],$AQ$1:$AT$594,2,FALSE()) -> А-44 | AJ27: =Таблица310[[#This Row],[Регистратор.Номенклатура]] -> Оскар | AK27: =VLOOKUP(Таблица310[[#This Row],[№ акта]],$AQ$1:$AT$594,4,FALSE()) -> ГРК собственные семена (богара) | AL27: =VLOOKUP(Таблица310[[#This Row],[№ акта]],$AQ$1:$AT$594,3,FALSE()) -> 1.617009 | AM27: =IF(Таблица310[[#This Row],[Площадь уборки, га]]=Таблица310[[#This Row],[Площадь уборки до корр]],"нет","да") -> нет | AN27: =Таблица310[[#This Row],[Площадь уборки до корр]]-Таблица310[[#This Row],[Площадь уборки, га]] -> 0 | AQ27: 84 | AR27: А-44 | AS27: 1.617009 | AT27: ГРК собственные семена (богара)
A28: Степень зрелости | B28: 6361.8 | C28: 48 | D28: 85 | E28: 45809 | F28: 23060 | G28: 9220 | H28: 13840 | I28: 6361.8 | J28: Грин Рэй Кубань ООО (Овощеводство) | K28: Оскар | L28: А-44 | M28: Богучарский А. И. | N28: 13:36:43 | O28: 13:59:42 | Q28: 916,728,915,727 | R28: Е404УС | T28: А-44 | U28: =Таблица310[[#This Row],[Регистратор.Номенклатура]] -> Оскар | V28: =26*Таблица310[[#This Row],[Регистратор.Вес нетто]]/69140 -> 3.4671681 | W28: ГРК собственные семена (богара) | X28: богара | Y28: 4 | Z28: 45809 | AC28: 40-52 | AD28: высший | AE28: 85 | AF28: 45809 | AG28: 15 | AH28: =VLOOKUP(Таблица310[[#This Row],[№ акта]],'Степень зрелости 2025'!$H$13:$I$583,2,FALSE()) -> 48 | AI28: =VLOOKUP(Таблица310[[#This Row],[№ акта]],$AQ$1:$AT$594,2,FALSE()) -> А-44 | AJ28: =Таблица310[[#This Row],[Регистратор.Номенклатура]] -> Оскар | AK28: =VLOOKUP(Таблица310[[#This Row],[№ акта]],$AQ$1:$AT$594,4,FALSE()) -> ГРК собственные семена (богара) | AL28: =VLOOKUP(Таблица310[[#This Row],[№ акта]],$AQ$1:$AT$594,3,FALSE()) -> 3.4671681 | AM28: =IF(Таблица310[[#This Row],[Площадь уборки, га]]=Таблица310[[#This Row],[Площадь уборки до корр]],"нет","да") -> нет | AN28: =Таблица310[[#This Row],[Площадь уборки до корр]]-Таблица310[[#This Row],[Площадь уборки, га]] -> 0 | AQ28: 85 | AR28: А-44 | AS28: 3.4671681 | AT28: ГРК собственные семена (богара)
A29: Степень зрелости | B29: 11319 | C29: 56 | D29: 86 | E29: 45809 | F29: 28520 | G29: 13720 | H29: 14800 | I29: 11319 | J29: Кубань УОХ | K29: Преладо | L29: 2/4 | M29: Титаренко Максим Сергеевич | N29: 15:33:08 | O29: 16:14:05 | Q29: 022,222,424,021,221,423 | R29: О398ХО | T29: 2/4 | U29: =Таблица310[[#This Row],[Регистратор.Номенклатура]] -> Преладо | V29: =27*Таблица310[[#This Row],[Регистратор.Вес нетто]]/137050 -> 2.7029551 | W29: Учхоз Кубань (богара) | X29: богара | Y29: 3 | Z29: 45809 | AC29: 53-63 | AD29: высший | AE29: 86 | AF29: 45809 | AG29: 65912 | AH29: =VLOOKUP(Таблица310[[#This Row],[№ акта]],'Степень зрелости 2025'!$H$13:$I$583,2,FALSE()) -> 56 | AI29: =VLOOKUP(Таблица310[[#This Row],[№ акта]],$AQ$1:$AT$594,2,FALSE()) -> 2/4 | AJ29: =Таблица310[[#This Row],[Регистратор.Номенклатура]] -> Преладо | AK29: =VLOOKUP(Таблица310[[#This Row],[№ акта]],$AQ$1:$AT$594,4,FALSE()) -> Учхоз Кубань (богара) | AL29: =VLOOKUP(Таблица310[[#This Row],[№ акта]],$AQ$1:$AT$594,3,FALSE()) -> 2.7029551 | AM29: =IF(Таблица310[[#This Row],[Площадь уборки, га]]=Таблица310[[#This Row],[Площадь уборки до корр]],"нет","да") -> нет | AN29: =Таблица310[[#This Row],[Площадь уборки до корр]]-Таблица310[[#This Row],[Площадь уборки, га]] -> 0 | AQ29: 86 | AR29: 2/4 | AS29: 2.7029551 | AT29: Учхоз Кубань (богара)
A30: Степень зрелости | B30: =Таблица310[[#This Row],[Регистратор.Вес чистый]] -> 10166.4 | C30: 53 | D30: 87 | E30: 45809 | F30: 27950 | G30: 14120 | H30: 13830 | I30: 10166.4 | J30: Грин Рэй Кубань ООО (Овощеводство) | K30: Оскар | L30: А-44 | M30: Богучарский А. И. | R30: Е404УС | T30: А-44 | U30: =Таблица310[[#This Row],[Регистратор.Номенклатура]] -> Оскар | V30: =26*Таблица310[[#This Row],[Регистратор.Вес нетто]]/69140 -> 5.3098062 | W30: ГРК собственные семена (богара) | X30: богара | Y30: 4 | Z30: 45809 | AC30: 53-63 | AD30: высший | AE30: 87 | AF30: 45809 | AG30: 16 | AH30: =VLOOKUP(Таблица310[[#This Row],[№ акта]],'Степень зрелости 2025'!$H$13:$I$583,2,FALSE()) -> 53 | AI30: =VLOOKUP(Таблица310[[#This Row],[№ акта]],$AQ$1:$AT$594,2,FALSE()) -> А-44 | AJ30: =Таблица310[[#This Row],[Регистратор.Номенклатура]] -> Оскар | AK30: =VLOOKUP(Таблица310[[#This Row],[№ акта]],$AQ$1:$AT$594,4,FALSE()) -> ГРК собственные семена (богара) | AL30: =VLOOKUP(Таблица310[[#This Row],[№ акта]],$AQ$1:$AT$594,3,FALSE()) -> 5.3098062 | AM30: =IF(Таблица310[[#This Row],[Площадь уборки, га]]=Таблица310[[#This Row],[Площадь уборки до корр]],"нет","да") -> нет | AN30: =Таблица310[[#This Row],[Площадь уборки до корр]]-Таблица310[[#This Row],[Площадь уборки, га]] -> 0 | AQ30: 87 | AR30: А-44 | AS30: 5.3098062 | AT30: ГРК собственные семена (богара)
A31: Степень зрелости | B31: 10631.4 | C31: 55 | D31: 88 | E31: 45809 | F31: 27720 | G31: 13630 | H31: 14090 | I31: 10631.4 | J31: Кубань УОХ | K31: Преладо | L31: 2/4 | M31: Сайко Василий Викторович | N31: 16:48:47 | O31: 17:54:07 | Q31: 426,224,024,023,425,223 | R31: А816ЕВ | T31: 2/4 | U31: =Таблица310[[#This Row],[Регистратор.Номенклатура]] -> Преладо | V31: =27*Таблица310[[#This Row],[Регистратор.Вес нетто]]/137050 -> 2.6852244 | W31: Учхоз Кубань (богара) | X31: богара | Y31: 3 | Z31: 45809 | AC31: 53-63 | AD31: высший | AE31: 88 | AF31: 45809 | AG31: 65914 | AH31: =VLOOKUP(Таблица310[[#This Row],[№ акта]],'Степень зрелости 2025'!$H$13:$I$583,2,FALSE()) -> 55 | AI31: =VLOOKUP(Таблица310[[#This Row],[№ акта]],$AQ$1:$AT$594,2,FALSE()) -> 2/4 | AJ31: =Таблица310[[#This Row],[Регистратор.Номенклатура]] -> Преладо | AK31: =VLOOKUP(Таблица310[[#This Row],[№ акта]],$AQ$1:$AT$594,4,FALSE()) -> Учхоз Кубань (богара) | AL31: =VLOOKUP(Таблица310[[#This Row],[№ акта]],$AQ$1:$AT$594,3,FALSE()) -> 2.6852244 | AM31: =IF(Таблица310[[#This Row],[Площадь уборки, га]]=Таблица310[[#This Row],[Площадь уборки до корр]],"нет","да") -> нет | AN31: =Таблица310[[#This Row],[Площадь уборки до корр]]-Таблица310[[#This Row],[Площадь уборки, га]] -> 0 | AQ31: 88 | AR31: 2/4 | AS31: 2.6852244 | AT31: Учхоз Кубань (богара)
A32: Степень зрелости | B32: 10665 | C32: 52 | D32: 89 | E32: 45809 | F32: 29140 | G32: 13500 | H32: 15640 | I32: 10665 | J32: Кубань УОХ | K32: Преладо | L32: 2/4 | M32: Грищенко Александр Александрович | N32: 18:02:55 | O32: 19:22:56 | Q32: 428,226,026,427,225,025 | R32: К416ТН | T32: 2/4 | U32: =Таблица310[[#This Row],[Регистратор.Номенклатура]] -> Преладо | V32: =27*Таблица310[[#This Row],[Регистратор.Вес нетто]]/137050 -> 2.6596133 | W32: Учхоз Кубань (богара) | X32: богара | Y32: 3 | Z32: 45809 | AC32: 40-52 | AD32: высший | AE32: 89 | AF32: 45809 | AG32: 65915 | AH32: =VLOOKUP(Таблица310[[#This Row],[№ акта]],'Степень зрелости 2025'!$H$13:$I$583,2,FALSE()) -> 52 | AI32: =VLOOKUP(Таблица310[[#This Row],[№ акта]],$AQ$1:$AT$594,2,FALSE()) -> 2/4 | AJ32: =Таблица310[[#This Row],[Регистратор.Номенклатура]] -> Преладо | AK32: =VLOOKUP(Таблица310[[#This Row],[№ акта]],$AQ$1:$AT$594,4,FALSE()) -> Учхоз Кубань (богара) | AL32: =VLOOKUP(Таблица310[[#This Row],[№ акта]],$AQ$1:$AT$594,3,FALSE()) -> 2.6596133 | AM32: =IF(Таблица310[[#This Row],[Площадь уборки, га]]=Таблица310[[#This Row],[Площадь уборки до корр]],"нет","да") -> нет | AN32: =Таблица310[[#This Row],[Площадь уборки до корр]]-Таблица310[[#This Row],[Площадь уборки, га]] -> 0 | AQ32: 89 | AR32: 2/4 | AS32: 2.6596133 | AT32: Учхоз Кубань (богара)
A33: Степень зрелости | B33: 11478.9 | C33: 51 | D33: 90 | E33: 45809 | F33: 28320 | G33: 13830 | H33: 14490 | I33: 11478.9 | J33: Кубань УОХ | K33: Преладо | L33: 2/4 | M33: Черевко Александр Владимирович | N33: 19:05:41 | O33: 23:20:46 | Q33: 027,227,429,028,228,430 | R33: А114МК | T33: 2/4 | U33: =Таблица310[[#This Row],[Регистратор.Номенклатура]] -> Преладо | V33: =27*Таблица310[[#This Row],[Регистратор.Вес нетто]]/137050 -> 2.724626 | W33: Учхоз Кубань (богара) | X33: богара | Y33: 3 | Z33: 45809 | AC33: 40-52 | AD33: высший | AE33: 90 | AF33: 45809 | AG33: 65916 | AH33: =VLOOKUP(Таблица310[[#This Row],[№ акта]],'Степень зрелости 2025'!$H$13:$I$583,2,FALSE()) -> 51 | AI33: =VLOOKUP(Таблица310[[#This Row],[№ акта]],$AQ$1:$AT$594,2,FALSE()) -> 2/4 | AJ33: =Таблица310[[#This Row],[Регистратор.Номенклатура]] -> Преладо | AK33: =VLOOKUP(Таблица310[[#This Row],[№ акта]],$AQ$1:$AT$594,4,FALSE()) -> Учхоз Кубань (богара) | AL33: =VLOOKUP(Таблица310[[#This Row],[№ акта]],$AQ$1:$AT$594,3,FALSE()) -> 2.724626 | AM33: =IF(Таблица310[[#This Row],[Площадь уборки, га]]=Таблица310[[#This Row],[Площадь уборки до корр]],"нет","да") -> нет | AN33: =Таблица310[[#This Row],[Площадь уборки до корр]]-Таблица310[[#This Row],[Площадь уборки, га]] -> 0 | AQ33: 90 | AR33: 2/4 | AS33: 2.724626 | AT33: Учхоз Кубань (богара)
A34: Степень зрелости | B34: 10826.4 | C34: 50 | D34: 91 | E34: 45809 | F34: 29030 | G34: 13880 | H34: 15150 | I34: 10826.4 | J34: Кубань УОХ | K34: Преладо | L34: 2/4 | M34: Извеков Владимир Владимирович | N34: 21:02:53 | O34: 23:48:44 | Q34: 029,431,229,030,230,031 | R34: Н378ХЕ | S34: ЕР7829 | T34: 2/4 | U34: =Таблица310[[#This Row],[Регистратор.Номенклатура]] -> Преладо | V34: =27*Таблица310[[#This Row],[Регистратор.Вес нетто]]/137050 -> 2.7344765 | W34: Учхоз Кубань (богара) | X34: богара | Y34: 3 | Z34: 45809 | AC34: 40-52 | AD34: высший | AE34: 91 | AF34: 45809 | AG34: 65917 | AH34: =VLOOKUP(Таблица310[[#This Row],[№ акта]],'Степень зрелости 2025'!$H$13:$I$583,2,FALSE()) -> 50 | AI34: =VLOOKUP(Таблица310[[#This Row],[№ акта]],$AQ$1:$AT$594,2,FALSE()) -> 2/4 | AJ34: =Таблица310[[#This Row],[Регистратор.Номенклатура]] -> Преладо | AK34: =VLOOKUP(Таблица310[[#This Row],[№ акта]],$AQ$1:$AT$594,4,FALSE()) -> Учхоз Кубань (богара) | AL34: =VLOOKUP(Таблица310[[#This Row],[№ акта]],$AQ$1:$AT$594,3,FALSE()) -> 2.7344765 | AM34: =IF(Таблица310[[#This Row],[Площадь уборки, га]]=Таблица310[[#This Row],[Площадь уборки до корр]],"нет","да") -> нет | AN34: =Таблица310[[#This Row],[Площадь уборки до корр]]-Таблица310[[#This Row],[Площадь уборки, га]] -> 0 | AQ34: 91 | AR34: 2/4 | AS34: 2.7344765 | AT34: Учхоз Кубань (богара)
A35: Степень зрелости | B35: 10052.1 | C35: 51 | D35: 92 | E35: 45809 | F35: 29310 | G35: 13770 | H35: 15540 | I35: 10052.1 | J35: Кубань УОХ | K35: Преладо | L35: 2/4 | M35: Емец Р.А. | N35: 22:29:35 | O35: 2:09:09 | Q35: 032,231,432,232,033,433 | R35: У315НХ | T35: 2/4 | U35: =Таблица310[[#This Row],[Регистратор.Номенклатура]] -> Преладо | V35: =27*Таблица310[[#This Row],[Регистратор.Вес нетто]]/137050 -> 2.7128055 | W35: Учхоз Кубань (богара) | X35: богара | Y35: 3 | Z35: 45809 | AC35: 40-52 | AD35: высший | AE35: 92 | AF35: 45809 | AG35: 65918 | AH35: =VLOOKUP(Таблица310[[#This Row],[№ акта]],'Степень зрелости 2025'!$H$13:$I$583,2,FALSE()) -> 51 | AI35: =VLOOKUP(Таблица310[[#This Row],[№ акта]],$AQ$1:$AT$594,2,FALSE()) -> 2/4 | AJ35: =Таблица310[[#This Row],[Регистратор.Номенклатура]] -> Преладо | AK35: =VLOOKUP(Таблица310[[#This Row],[№ акта]],$AQ$1:$AT$594,4,FALSE()) -> Учхоз Кубань (богара) | AL35: =VLOOKUP(Таблица310[[#This Row],[№ акта]],$AQ$1:$AT$594,3,FALSE()) -> 2.7128055 | AM35: =IF(Таблица310[[#This Row],[Площадь уборки, га]]=Таблица310[[#This Row],[Площадь уборки до корр]],"нет","да") -> нет | AN35: =Таблица310[[#This Row],[Площадь уборки до корр]]-Таблица310[[#This Row],[Площадь уборки, га]] -> 0 | AQ35: 92 | AR35: 2/4 | AS35: 2.7128055 | AT35: Учхоз Кубань (богара)
A36: Степень зрелости | B36: 8514.6 | C36: 51 | D36: 93 | E36: 45809 | F36: 26540 | G36: 12340 | H36: 14200 | I36: 8514.6 | J36: Грин Рэй Кубань ООО (Овощеводство) | K36: Оскар | L36: А-44 | M36: Сайко Василий Викторович | N36: 21:52:22 | O36: 3:27:11 | Q36: 921,730,922,731,923,732 | R36: А816ЕВ | T36: А-44 | U36: =Таблица310[[#This Row],[Регистратор.Номенклатура]] -> Оскар | V36: =26*Таблица310[[#This Row],[Регистратор.Вес нетто]]/69140 -> 4.6404397 | W36: ГРК собственные семена (богара) | X36: богара | Y36: 4 | Z36: 45809 | AC36: 40-52 | AD36: высший | AE36: 93 | AF36: 45809 | AG36: 17 | AH36: =VLOOKUP(Таблица310[[#This Row],[№ акта]],'Степень зрелости 2025'!$H$13:$I$583,2,FALSE()) -> 51 | AI36: =VLOOKUP(Таблица310[[#This Row],[№ акта]],$AQ$1:$AT$594,2,FALSE()) -> А-44 | AJ36: =Таблица310[[#This Row],[Регистратор.Номенклатура]] -> Оскар | AK36: =VLOOKUP(Таблица310[[#This Row],[№ акта]],$AQ$1:$AT$594,4,FALSE()) -> ГРК собственные семена (богара) | AL36: =VLOOKUP(Таблица310[[#This Row],[№ акта]],$AQ$1:$AT$594,3,FALSE()) -> 4.6404397 | AM36: =IF(Таблица310[[#This Row],[Площадь уборки, га]]=Таблица310[[#This Row],[Площадь уборки до корр]],"нет","да") -> нет | AN36: =Таблица310[[#This Row],[Площадь уборки до корр]]-Таблица310[[#This Row],[Площадь уборки, га]] -> 0 | AQ36: 93 | AR36: А-44 | AS36: 4.6404397 | AT36: ГРК собственные семена (богара)
A37: Степень зрелости | B37: 10252.5 | C37: 53 | D37: 94 | E37: 45809 | F37: 28810 | G37: 13670 | H37: 15140 | I37: 10252.5 | J37: Кубань УОХ | K37: Преладо | L37: 2/4 | M37: Долгих Николай Петрович | N37: 23:13:05 | O37: 4:20:42 | Q37: 233,034,434,234,035,435 | R37: У726ЕР | T37: 2/4 | U37: =Таблица310[[#This Row],[Регистратор.Номенклатура]] -> Преладо | V37: =27*Таблица310[[#This Row],[Регистратор.Вес нетто]]/137050 -> 2.6931047 | W37: Учхоз Кубань (богара) | X37: богара | Y37: 3 | Z37: 45809 | AC37: 53-63 | AD37: высший | AE37: 94 | AF37: 45809 | AG37: 65919 | AH37: =VLOOKUP(Таблица310[[#This Row],[№ акта]],'Степень зрелости 2025'!$H$13:$I$583,2,FALSE()) -> 53 | AI37: =VLOOKUP(Таблица310[[#This Row],[№ акта]],$AQ$1:$AT$594,2,FALSE()) -> 2/4 | AJ37: =Таблица310[[#This Row],[Регистратор.Номенклатура]] -> Преладо | AK37: =VLOOKUP(Таблица310[[#This Row],[№ акта]],$AQ$1:$AT$594,4,FALSE()) -> Учхоз Кубань (богара) | AL37: =VLOOKUP(Таблица310[[#This Row],[№ акта]],$AQ$1:$AT$594,3,FALSE()) -> 2.6931047 | AM37: =IF(Таблица310[[#This Row],[Площадь уборки, га]]=Таблица310[[#This Row],[Площадь уборки до корр]],"нет","да") -> нет | AN37: =Таблица310[[#This Row],[Площадь уборки до корр]]-Таблица310[[#This Row],[Площадь уборки, га]] -> 0 | AQ37: 94 | AR37: 2/4 | AS37: 2.6931047 | AT37: Учхоз Кубань (богара)
A38: Степень зрелости | B38: 10472.8 | C38: 53 | D38: 96 | E38: 45810 | F38: 28330 | G38: 13780 | H38: 14550 | I38: 10472.8 | J38: Кубань УОХ | K38: Преладо | L38: 2/4 | M38: Вафин В | N38: 0:39:44 | O38: 9:01:17 | Q38: 235,036,236,037,436,237 | R38: У383РЕ | T38: 2/4 | U38: =Таблица310[[#This Row],[Регистратор.Номенклатура]] -> Преладо | V38: =27*Таблица310[[#This Row],[Регистратор.Вес нетто]]/137050 -> 2.7147756 | W38: Учхоз Кубань (богара) | X38: богара | Y38: 3 | Z38: 45809 | AC38: 53-63 | AD38: высший | AE38: 96 | AF38: 45810 | AG38: 65920 | AH38: =VLOOKUP(Таблица310[[#This Row],[№ акта]],'Степень зрелости 2025'!$H$13:$I$583,2,FALSE()) -> 53 | AI38: =VLOOKUP(Таблица310[[#This Row],[№ акта]],$AQ$1:$AT$594,2,FALSE()) -> 2/4 | AJ38: =Таблица310[[#This Row],[Регистратор.Номенклатура]] -> Преладо | AK38: =VLOOKUP(Таблица310[[#This Row],[№ акта]],$AQ$1:$AT$594,4,FALSE()) -> Учхоз Кубань (богара) | AL38: =VLOOKUP(Таблица310[[#This Row],[№ акта]],$AQ$1:$AT$594,3,FALSE()) -> 2.7147756 | AM38: =IF(Таблица310[[#This Row],[Площадь уборки, га]]=Таблица310[[#This Row],[Площадь уборки до корр]],"нет","да") -> нет | AN38: =Таблица310[[#This Row],[Площадь уборки до корр]]-Таблица310[[#This Row],[Площадь уборки, га]] -> 0 | AQ38: 96 | AR38: 2/4 | AS38: 2.7147756 | AT38: Учхоз Кубань (богара)
A39: Степень зрелости | B39: 10728.2 | C39: 52 | D39: 97 | E39: 45810 | F39: 28370 | G39: 13580 | H39: 14790 | I39: 10728.2 | J39: Кубань УОХ | K39: Преладо | L39: 2/4 | M39: Огнев Максим Викторович | N39: 1:29:47 | O39: 11:04:29 | Q39: 038,238,437,039,438,239 | R39: Р755НН | S39: РА5550 | T39: 2/4 | U39: =Таблица310[[#This Row],[Регистратор.Номенклатура]] -> Преладо | V39: =27*Таблица310[[#This Row],[Регистратор.Вес нетто]]/137050 -> 2.675374 | W39: Учхоз Кубань (богара) | X39: богара | Y39: 3 | Z39: 45809 | AC39: 40-52 | AD39: высший | AE39: 97 | AF39: 45810 | AG39: 65921 | AH39: =VLOOKUP(Таблица310[[#This Row],[№ акта]],'Степень зрелости 2025'!$H$13:$I$583,2,FALSE()) -> 52 | AI39: =VLOOKUP(Таблица310[[#This Row],[№ акта]],$AQ$1:$AT$594,2,FALSE()) -> 2/4 | AJ39: =Таблица310[[#This Row],[Регистратор.Номенклатура]] -> Преладо | AK39: =VLOOKUP(Таблица310[[#This Row],[№ акта]],$AQ$1:$AT$594,4,FALSE()) -> Учхоз Кубань (богара) | AL39: =VLOOKUP(Таблица310[[#This Row],[№ акта]],$AQ$1:$AT$594,3,FALSE()) -> 2.675374 | AM39: =IF(Таблица310[[#This Row],[Площадь уборки, га]]=Таблица310[[#This Row],[Площадь уборки до корр]],"нет","да") -> нет | AN39: =Таблица310[[#This Row],[Площадь уборки до корр]]-Таблица310[[#This Row],[Площадь уборки, га]] -> 0 | AQ39: 97 | AR39: 2/4 | AS39: 2.675374 | AT39: Учхоз Кубань (богара)
A40: Степень зрелости | B40: 10404.4 | C40: 51 | D40: 98 | E40: 45810 | F40: 28660 | G40: 13690 | H40: 14970 | I40: 10404.4 | J40: Кубань УОХ | K40: Преладо | L40: 2/4 | M40: Лазаренко Вятчеслав Владимирович | N40: 3:20:56 | O40: 10:41:54 | Q40: 040,440,240,439,041,241 | R40: Т239УС | S40: ЕС6637 | T40: 2/4 | U40: =Таблица310[[#This Row],[Регистратор.Номенклатура]] -> Преладо | V40: =27*Таблица310[[#This Row],[Регистратор.Вес нетто]]/137050 -> 2.6970449 | W40: Учхоз Кубань (богара) | X40: богара | Y40: 3 | Z40: 45809 | AC40: 40-52 | AD40: высший | AE40: 98 | AF40: 45810 | AG40: 65922 | AH40: =VLOOKUP(Таблица310[[#This Row],[№ акта]],'Степень зрелости 2025'!$H$13:$I$583,2,FALSE()) -> 51 | AI40: =VLOOKUP(Таблица310[[#This Row],[№ акта]],$AQ$1:$AT$594,2,FALSE()) -> 2/4 | AJ40: =Таблица310[[#This Row],[Регистратор.Номенклатура]] -> Преладо | AK40: =VLOOKUP(Таблица310[[#This Row],[№ акта]],$AQ$1:$AT$594,4,FALSE()) -> Учхоз Кубань (богара) | AL40: =VLOOKUP(Таблица310[[#This Row],[№ акта]],$AQ$1:$AT$594,3,FALSE()) -> 2.6970449 | AM40: =IF(Таблица310[[#This Row],[Площадь уборки, га]]=Таблица310[[#This Row],[Площадь уборки до корр]],"нет","да") -> нет | AN40: =Таблица310[[#This Row],[Площадь уборки до корр]]-Таблица310[[#This Row],[Площадь уборки, га]] -> 0 | AQ40: 98 | AR40: 2/4 | AS40: 2.6970449 | AT40: Учхоз Кубань (богара)
A41: Степень зрелости | B41: 7625.4 | C41: 52 | D41: 99 | E41: 45810 | F41: 24560 | G41: 10740 | H41: 13820 | I41: 7625.4 | J41: Грин Рэй Кубань ООО (Овощеводство) | K41: Оскар | L41: А-44 | M41: Богучарский А. И. | N41: 0:13:03 | O41: 5:29:03 | Q41: 924,925,734,733,926 | R41: Е404УС | S41: ЕТ0909 | T41: А-44 | U41: =Таблица310[[#This Row],[Регистратор.Номенклатура]] -> Оскар | V41: =26*Таблица310[[#This Row],[Регистратор.Вес нетто]]/69140 -> 4.0387619 | W41: ГРК собственные семена (богара) | X41: богара | Y41: 4 | Z41: 45809 | AC41: 40-52 | AD41: высший | AE41: 99 | AF41: 45810 | AG41: 18 | AH41: =VLOOKUP(Таблица310[[#This Row],[№ акта]],'Степень зрелости 2025'!$H$13:$I$583,2,FALSE()) -> 52 | AI41: =VLOOKUP(Таблица310[[#This Row],[№ акта]],$AQ$1:$AT$594,2,FALSE()) -> А-44 | AJ41: =Таблица310[[#This Row],[Регистратор.Номенклатура]] -> Оскар | AK41: =VLOOKUP(Таблица310[[#This Row],[№ акта]],$AQ$1:$AT$594,4,FALSE()) -> ГРК собственные семена (богара) | AL41: =VLOOKUP(Таблица310[[#This Row],[№ акта]],$AQ$1:$AT$594,3,FALSE()) -> 4.0387619 | AM41: =IF(Таблица310[[#This Row],[Площадь уборки, га]]=Таблица310[[#This Row],[Площадь уборки до корр]],"нет","да") -> нет | AN41: =Таблица310[[#This Row],[Площадь уборки до корр]]-Таблица310[[#This Row],[Площадь уборки, га]] -> 0 | AQ41: 99 | AR41: А-44 | AS41: 4.0387619 | AT41: ГРК собственные семена (богара)
A42: Степень зрелости | B42: 10252.5 | C42: 49 | D42: 100 | E42: 45810 | F42: 28060 | G42: 13670 | H42: 14390 | I42: 10252.5 | J42: Кубань УОХ | K42: Преладо | L42: 2/4 | M42: Магадиев Александр Сайлаувич | N42: 4:24:32 | O42: 13:02:01 | Q42: 242,042,441,043,243,442 | R42: У184НО | S42: МН7302 | T42: 2/4 | U42: =Таблица310[[#This Row],[Регистратор.Номенклатура]] -> Преладо | V42: =10*Таблица310[[#This Row],[Регистратор.Вес нетто]]/54770 -> 2.4958919 | W42: Учхоз Кубань (богара) | X42: богара | Y42: 4 | Z42: 45810 | AC42: 40-52 | AD42: высший | AE42: 100 | AF42: 45810 | AG42: 65923 | AH42: =VLOOKUP(Таблица310[[#This Row],[№ акта]],'Степень зрелости 2025'!$H$13:$I$583,2,FALSE()) -> 49 | AI42: =VLOOKUP(Таблица310[[#This Row],[№ акта]],$AQ$1:$AT$594,2,FALSE()) -> 2/4 | AJ42: =Таблица310[[#This Row],[Регистратор.Номенклатура]] -> Преладо | AK42: =VLOOKUP(Таблица310[[#This Row],[№ акта]],$AQ$1:$AT$594,4,FALSE()) -> Учхоз Кубань (богара) | AL42: =VLOOKUP(Таблица310[[#This Row],[№ акта]],$AQ$1:$AT$594,3,FALSE()) -> 2.4958919 | AM42: =IF(Таблица310[[#This Row],[Площадь уборки, га]]=Таблица310[[#This Row],[Площадь уборки до корр]],"нет","да") -> нет | AN42: =Таблица310[[#This Row],[Площадь уборки до корр]]-Таблица310[[#This Row],[Площадь уборки, га]] -> 0 | AQ42: 100 | AR42: 2/4 | AS42: 2.4958919 | AT42: Учхоз Кубань (богара)
A43: Степень зрелости | B43: 10273.5 | C43: 52 | D43: 101 | E43: 45810 | F43: 28740 | G43: 13790 | H43: 14950 | I43: 10273.5 | J43: Кубань УОХ | K43: Преладо | L43: 2/4 | M43: Ревенко Андрей Вячеславович | N43: 6:03:58 | O43: 13:08:09 | Q43: 244,044,045,245,443,046 | R43: А781РР | S43: ЕХ4187 | T43: 2/4 | U43: =Таблица310[[#This Row],[Регистратор.Номенклатура]] -> Преладо | V43: =10*Таблица310[[#This Row],[Регистратор.Вес нетто]]/54770 -> 2.5178017 | W43: Учхоз Кубань (богара) | X43: богара | Y43: 4 | Z43: 45810 | AC43: 53-63 | AD43: высший | AE43: 101 | AF43: 45810 | AG43: 65924 | AH43: =VLOOKUP(Таблица310[[#This Row],[№ акта]],'Степень зрелости 2025'!$H$13:$I$583,2,FALSE()) -> 52 | AI43: =VLOOKUP(Таблица310[[#This Row],[№ акта]],$AQ$1:$AT$594,2,FALSE()) -> 2/4 | AJ43: =Таблица310[[#This Row],[Регистратор.Номенклатура]] -> Преладо | AK43: =VLOOKUP(Таблица310[[#This Row],[№ акта]],$AQ$1:$AT$594,4,FALSE()) -> Учхоз Кубань (богара) | AL43: =VLOOKUP(Таблица310[[#This Row],[№ акта]],$AQ$1:$AT$594,3,FALSE()) -> 2.5178017 | AM43: =IF(Таблица310[[#This Row],[Площадь уборки, га]]=Таблица310[[#This Row],[Площадь уборки до корр]],"нет","да") -> нет | AN43: =Таблица310[[#This Row],[Площадь уборки до корр]]-Таблица310[[#This Row],[Площадь уборки, га]] -> 0 | AQ43: 101 | AR43: 2/4 | AS43: 2.5178017 | AT43: Учхоз Кубань (богара)
A44: Степень зрелости | B44: 9796 | C44: 50 | D44: 102 | E44: 45810 | F44: 26590 | G44: 12400 | H44: 14190 | I44: 9796 | J44: Грин Рэй Кубань ООО (Овощеводство) | K44: Оскар | L44: А-44 | M44: Сайко Василий Викторович | N44: 7:03:43 | O44: 15:36:46 | Q44: 735,927,736,928,737,929 | R44: А816ЕВ | S44: ЕС2898 | T44: А-44 | U44: =Таблица310[[#This Row],[Регистратор.Номенклатура]] -> Оскар | V44: =18*Таблица310[[#This Row],[Регистратор.Вес нетто]]/72040 -> 3.0982787 | W44: ГРК собственные семена (богара) | X44: богара | Y44: 5 | Z44: 45810 | AC44: 40-52 | AD44: высший | AE44: 102 | AF44: 45810 | AG44: 19 | AH44: =VLOOKUP(Таблица310[[#This Row],[№ акта]],'Степень зрелости 2025'!$H$13:$I$583,2,FALSE()) -> 50 | AI44: =VLOOKUP(Таблица310[[#This Row],[№ акта]],$AQ$1:$AT$594,2,FALSE()) -> А-44 | AJ44: =Таблица310[[#This Row],[Регистратор.Номенклатура]] -> Оскар | AK44: =VLOOKUP(Таблица310[[#This Row],[№ акта]],$AQ$1:$AT$594,4,FALSE()) -> ГРК собственные семена (богара) | AL44: =VLOOKUP(Таблица310[[#This Row],[№ акта]],$AQ$1:$AT$594,3,FALSE()) -> 3.0982787 | AM44: =IF(Таблица310[[#This Row],[Площадь уборки, га]]=Таблица310[[#This Row],[Площадь уборки до корр]],"нет","да") -> нет | AN44: =Таблица310[[#This Row],[Площадь уборки до корр]]-Таблица310[[#This Row],[Площадь уборки, га]] -> 0 | AQ44: 102 | AR44: А-44 | AS44: 3.0982787 | AT44: ГРК собственные семена (богара)
A45: Степень зрелости | B45: 10564.6 | C45: 49 | D45: 103 | E45: 45810 | F45: 28190 | G45: 13810 | H45: 14380 | I45: 10564.6 | J45: Кубань УОХ | K45: Преладо | L45: 2/4 | M45: Жданов Андрей Иванович | N45: 7:51:31 | O45: 15:58:34 | Q45: 246,047,247,048,248,049 | R45: С707ОУ | S45: ЕТ8716 | T45: 2/4 | U45: =Таблица310[[#This Row],[Регистратор.Номенклатура]] -> Преладо | V45: =10*Таблица310[[#This Row],[Регистратор.Вес нетто]]/54770 -> 2.5214534 | W45: Учхоз Кубань (богара) | X45: богара | Y45: 4 | Z45: 45810 | AB45: По отчету ВА - 01.06.2025 | AC45: 40-52 | AD45: высший | AE45: 103 | AF45: 45810 | AG45: 65927 | AH45: =VLOOKUP(Таблица310[[#This Row],[№ акта]],'Степень зрелости 2025'!$H$13:$I$583,2,FALSE()) -> 49 | AI45: =VLOOKUP(Таблица310[[#This Row],[№ акта]],$AQ$1:$AT$594,2,FALSE()) -> 2/4 | AJ45: =Таблица310[[#This Row],[Регистратор.Номенклатура]] -> Преладо | AK45: =VLOOKUP(Таблица310[[#This Row],[№ акта]],$AQ$1:$AT$594,4,FALSE()) -> Учхоз Кубань (богара) | AL45: =VLOOKUP(Таблица310[[#This Row],[№ акта]],$AQ$1:$AT$594,3,FALSE()) -> 2.5214534 | AM45: =IF(Таблица310[[#This Row],[Площадь уборки, га]]=Таблица310[[#This Row],[Площадь уборки до корр]],"нет","да") -> нет | AN45: =Таблица310[[#This Row],[Площадь уборки до корр]]-Таблица310[[#This Row],[Площадь уборки, га]] -> 0 | AQ45: 103 | AR45: 2/4 | AS45: 2.5214534 | AT45: Учхоз Кубань (богара)
A46: Степень зрелости | B46: 10462.5 | C46: 52 | D46: 104 | E46: 45810 | F46: 28300 | G46: 13500 | H46: 14800 | I46: 10462.5 | J46: Кубань УОХ | K46: Преладо | L46: 2/4 | M46: Кудря Евгений | N46: 10:50:53 | O46: 17:24:37 | Q46: 050,249,052,251,051,250 | R46: А719ОО | S46: ЕУ8087 | T46: 2/4 | U46: =Таблица310[[#This Row],[Регистратор.Номенклатура]] -> Преладо | V46: =10*Таблица310[[#This Row],[Регистратор.Вес нетто]]/54770 -> 2.464853 | W46: Учхоз Кубань (богара) | X46: богара | Y46: 4 | Z46: 45810 | AC46: 40-52 | AD46: высший | AE46: 104 | AF46: 45810 | AG46: 65928 | AH46: =VLOOKUP(Таблица310[[#This Row],[№ акта]],'Степень зрелости 2025'!$H$13:$I$583,2,FALSE()) -> 52 | AI46: =VLOOKUP(Таблица310[[#This Row],[№ акта]],$AQ$1:$AT$594,2,FALSE()) -> 2/4 | AJ46: =Таблица310[[#This Row],[Регистратор.Номенклатура]] -> Преладо | AK46: =VLOOKUP(Таблица310[[#This Row],[№ акта]],$AQ$1:$AT$594,4,FALSE()) -> Учхоз Кубань (богара) | AL46: =VLOOKUP(Таблица310[[#This Row],[№ акта]],$AQ$1:$AT$594,3,FALSE()) -> 2.464853 | AM46: =IF(Таблица310[[#This Row],[Площадь уборки, га]]=Таблица310[[#This Row],[Площадь уборки до корр]],"нет","да") -> нет | AN46: =Таблица310[[#This Row],[Площадь уборки до корр]]-Таблица310[[#This Row],[Площадь уборки, га]] -> 0 | AQ46: 104 | AR46: 2/4 | AS46: 2.464853 | AT46: Учхоз Кубань (богара)
A47: Степень зрелости | B47: 10542.5 | C47: 49 | D47: 105 | E47: 45810 | F47: 28400 | G47: 13430 | H47: 14970 | I47: 10542.5 | J47: Кубань УОХ | K47: Изюминка | L47: 2/4 | M47: Бербеницкий Сергей Николаевич | N47: 16:59:38 | O47: 20:29:39 | Q47: 445,306,107,444,106,305 | R47: С400РР | S47: ЕО0811 | T47: 2/4 | U47: =Таблица310[[#This Row],[Регистратор.Номенклатура]] -> Изюминка | V47: =12*Таблица310[[#This Row],[Регистратор.Вес нетто]]/71490 -> 2.2543013 | W47: Учхоз Кубань (богара) | X47: богара | Y47: 4 | Z47: 45810 | AC47: 40-52 | AD47: высший | AE47: 105 | AF47: 45810 | AG47: 65929 | AH47: =VLOOKUP(Таблица310[[#This Row],[№ акта]],'Степень зрелости 2025'!$H$13:$I$583,2,FALSE()) -> 49 | AI47: =VLOOKUP(Таблица310[[#This Row],[№ акта]],$AQ$1:$AT$594,2,FALSE()) -> 2/4 | AJ47: =Таблица310[[#This Row],[Регистратор.Номенклатура]] -> Изюминка | AK47: =VLOOKUP(Таблица310[[#This Row],[№ акта]],$AQ$1:$AT$594,4,FALSE()) -> Учхоз Кубань (богара) | AL47: =VLOOKUP(Таблица310[[#This Row],[№ акта]],$AQ$1:$AT$594,3,FALSE()) -> 2.2543013 | AM47: =IF(Таблица310[[#This Row],[Площадь уборки, га]]=Таблица310[[#This Row],[Площадь уборки до корр]],"нет","да") -> нет | AN47: =Таблица310[[#This Row],[Площадь уборки до корр]]-Таблица310[[#This Row],[Площадь уборки, га]] -> 0 | AQ47: 105 | AR47: 2/4 | AS47: 2.2543013 | AT47: Учхоз Кубань (богара)
A48: Степень зрелости | B48: 10625.5 | C48: 56 | D48: 106 | E48: 45810 | F48: 32140 | G48: 13450 | H48: 18690 | I48: 10625.5 | J48: Кубань УОХ | K48: Изюминка | L48: 2/4 | M48: Погуляй А.Б. | N48: 20:23:59 | O48: 21:04:28 | Q48: 447,109,446,308,108,307 | R48: О824ТХ | S48: ЕН1867 | T48: 2/4 | U48: =Таблица310[[#This Row],[Регистратор.Номенклатура]] -> Изюминка | V48: =12*Таблица310[[#This Row],[Регистратор.Вес нетто]]/71490 -> 2.2576584 | W48: Учхоз Кубань (богара) | X48: богара | Y48: 4 | Z48: 45810 | AC48: 53-63 | AD48: высший | AE48: 106 | AF48: 45810 | AG48: 65940 | AH48: =VLOOKUP(Таблица310[[#This Row],[№ акта]],'Степень зрелости 2025'!$H$13:$I$583,2,FALSE()) -> 56 | AI48: =VLOOKUP(Таблица310[[#This Row],[№ акта]],$AQ$1:$AT$594,2,FALSE()) -> 2/4 | AJ48: =Таблица310[[#This Row],[Регистратор.Номенклатура]] -> Изюминка | AK48: =VLOOKUP(Таблица310[[#This Row],[№ акта]],$AQ$1:$AT$594,4,FALSE()) -> Учхоз Кубань (богара) | AL48: =VLOOKUP(Таблица310[[#This Row],[№ акта]],$AQ$1:$AT$594,3,FALSE()) -> 2.2576584 | AM48: =IF(Таблица310[[#This Row],[Площадь уборки, га]]=Таблица310[[#This Row],[Площадь уборки до корр]],"нет","да") -> нет | AN48: =Таблица310[[#This Row],[Площадь уборки до корр]]-Таблица310[[#This Row],[Площадь уборки, га]] -> 0 | AQ48: 106 | AR48: 2/4 | AS48: 2.2576584 | AT48: Учхоз Кубань (богара)
A49: Степень зрелости | B49: 11246.9 | C49: 56 | D49: 107 | E49: 45810 | F49: 28920 | G49: 13310 | H49: 15610 | I49: 11246.9 | J49: Кубань УОХ | K49: Изюминка | L49: 2/4 | M49: Пугачев Сергей Викторович | N49: 21:36:54 | O49: 22:19:44 | Q49: 310,449,309,111,448,110 | R49: Р258УХ | S49: МО9466 | T49: 2/4 | U49: =Таблица310[[#This Row],[Регистратор.Номенклатура]] -> Изюминка | V49: =12*Таблица310[[#This Row],[Регистратор.Вес нетто]]/71490 -> 2.2341586 | W49: Учхоз Кубань (богара) | X49: богара | Y49: 4 | Z49: 45810 | AC49: 53-63 | AD49: высший | AE49: 107 | AF49: 45810 | AG49: 65925 | AH49: =VLOOKUP(Таблица310[[#This Row],[№ акта]],'Степень зрелости 2025'!$H$13:$I$583,2,FALSE()) -> 56 | AI49: =VLOOKUP(Таблица310[[#This Row],[№ акта]],$AQ$1:$AT$594,2,FALSE()) -> 2/4 | AJ49: =Таблица310[[#This Row],[Регистратор.Номенклатура]] -> Изюминка | AK49: =VLOOKUP(Таблица310[[#This Row],[№ акта]],$AQ$1:$AT$594,4,FALSE()) -> Учхоз Кубань (богара) | AL49: =VLOOKUP(Таблица310[[#This Row],[№ акта]],$AQ$1:$AT$594,3,FALSE()) -> 2.2341586 | AM49: =IF(Таблица310[[#This Row],[Площадь уборки, га]]=Таблица310[[#This Row],[Площадь уборки до корр]],"нет","да") -> нет | AN49: =Таблица310[[#This Row],[Площадь уборки до корр]]-Таблица310[[#This Row],[Площадь уборки, га]] -> 0 | AQ49: 107 | AR49: 2/4 | AS49: 2.2341586 | AT49: Учхоз Кубань (богара)
A50: Степень зрелости | B50: 7714.8 | C50: 55 | D50: 108 | E50: 45810 | F50: 23520 | G50: 9130 | H50: 14390 | I50: 7714.8 | J50: Грин Рэй Кубань ООО (Овощеводство) | K50: Оскар | L50: А-44 | M50: Чигрин Н.А. | N50: 23:14:32 | O50: 23:46:16 | Q50: 747,936,746,745 | R50: А819ЕВ | S50: ЕС2899 | T50: А-44 | U50: =Таблица310[[#This Row],[Регистратор.Номенклатура]] -> Оскар | V50: =18*Таблица310[[#This Row],[Регистратор.Вес нетто]]/72040 -> 2.2812326 | W50: ГРК собственные семена (богара) | X50: богара | Y50: 5 | Z50: 45810 | AC50: 53-63 | AD50: высший | AE50: 108 | AF50: 45810 | AG50: 23 | AH50: =VLOOKUP(Таблица310[[#This Row],[№ акта]],'Степень зрелости 2025'!$H$13:$I$583,2,FALSE()) -> 55 | AI50: =VLOOKUP(Таблица310[[#This Row],[№ акта]],$AQ$1:$AT$594,2,FALSE()) -> А-44 | AJ50: =Таблица310[[#This Row],[Регистратор.Номенклатура]] -> Оскар | AK50: =VLOOKUP(Таблица310[[#This Row],[№ акта]],$AQ$1:$AT$594,4,FALSE()) -> ГРК собственные семена (богара) | AL50: =VLOOKUP(Таблица310[[#This Row],[№ акта]],$AQ$1:$AT$594,3,FALSE()) -> 2.2812326 | AM50: =IF(Таблица310[[#This Row],[Площадь уборки, га]]=Таблица310[[#This Row],[Площадь уборки до корр]],"нет","да") -> нет | AN50: =Таблица310[[#This Row],[Площадь уборки до корр]]-Таблица310[[#This Row],[Площадь уборки, га]] -> 0 | AQ50: 108 | AR50: А-44 | AS50: 2.2812326 | AT50: ГРК собственные семена (богара)
A51: Степень зрелости | B51: 10872.1 | C51: 55 | D51: 109 | E51: 45810 | F51: 28350 | G51: 13340 | H51: 15010 | I51: 10872.1 | J51: Кубань УОХ | K51: Изюминка | L51: 2/4 | M51: Никитась Сергей Анатольевич | N51: 23:23:17 | O51: 1:54:38 | Q51: 450,114,312,113,311,112 | R51: К570ЕО | S51: ЕС6735 | T51: 2/4 | U51: =Таблица310[[#This Row],[Регистратор.Номенклатура]] -> Изюминка | V51: =12*Таблица310[[#This Row],[Регистратор.Вес нетто]]/71490 -> 2.2391943 | W51: Учхоз Кубань (богара) | X51: богара | Y51: 4 | Z51: 45810 | AC51: 53-63 | AD51: высший | AE51: 109 | AF51: 45810 | AG51: 65926 | AH51: =VLOOKUP(Таблица310[[#This Row],[№ акта]],'Степень зрелости 2025'!$H$13:$I$583,2,FALSE()) -> 55 | AI51: =VLOOKUP(Таблица310[[#This Row],[№ акта]],$AQ$1:$AT$594,2,FALSE()) -> 2/4 | AJ51: =Таблица310[[#This Row],[Регистратор.Номенклатура]] -> Изюминка | AK51: =VLOOKUP(Таблица310[[#This Row],[№ акта]],$AQ$1:$AT$594,4,FALSE()) -> Учхоз Кубань (богара) | AL51: =VLOOKUP(Таблица310[[#This Row],[№ акта]],$AQ$1:$AT$594,3,FALSE()) -> 2.2391943 | AM51: =IF(Таблица310[[#This Row],[Площадь уборки, га]]=Таблица310[[#This Row],[Площадь уборки до корр]],"нет","да") -> нет | AN51: =Таблица310[[#This Row],[Площадь уборки до корр]]-Таблица310[[#This Row],[Площадь уборки, га]] -> 0 | AQ51: 109 | AR51: 2/4 | AS51: 2.2391943 | AT51: Учхоз Кубань (богара)
A52: Степень зрелости | B52: =Таблица310[[#This Row],[Регистратор.Вес чистый]] -> 7282.2 | C52: 55 | D52: 110 | E52: 45811 | F52: 23950 | G52: 9160 | H52: 14790 | I52: 7282.2 | J52: Грин Рэй Кубань ООО (Овощеводство) | K52: Оскар | L52: А-44 | M52: Кудря Евгений | R52: А719ОО | T52: А-44 | U52: =Таблица310[[#This Row],[Регистратор.Номенклатура]] -> Оскар | V52: =8.6*Таблица310[[#This Row],[Регистратор.Вес нетто]]/26740 -> 2.9459985 | W52: ГРК собственные семена (богара) | X52: богара | Y52: 5 | Z52: 45810 | AC52: 53-63 | AD52: высший | AE52: 110 | AF52: 45811 | AG52: 24 | AH52: =VLOOKUP(Таблица310[[#This Row],[№ акта]],'Степень зрелости 2025'!$H$13:$I$583,2,FALSE()) -> 55 | AI52: =VLOOKUP(Таблица310[[#This Row],[№ акта]],$AQ$1:$AT$594,2,FALSE()) -> А-44 | AJ52: =Таблица310[[#This Row],[Регистратор.Номенклатура]] -> Оскар | AK52: =VLOOKUP(Таблица310[[#This Row],[№ акта]],$AQ$1:$AT$594,4,FALSE()) -> ГРК собственные семена (богара) | AL52: =VLOOKUP(Таблица310[[#This Row],[№ акта]],$AQ$1:$AT$594,3,FALSE()) -> 2.2887285 | AM52: =IF(Таблица310[[#This Row],[Площадь уборки, га]]=Таблица310[[#This Row],[Площадь уборки до корр]],"нет","да") -> да | AN52: =Таблица310[[#This Row],[Площадь уборки до корр]]-Таблица310[[#This Row],[Площадь уборки, га]] -> -0.65727002 | AQ52: 110 | AR52: А-44 | AS52: 2.2887285 | AT52: ГРК собственные семена (богара)
A53: Степень зрелости | B53: =Таблица310[[#This Row],[Регистратор.Вес чистый]] -> 7590 | C53: 55 | D53: 111 | E53: 45811 | F53: 23580 | G53: 9200 | H53: 14380 | I53: 7590 | J53: Грин Рэй Кубань ООО (Овощеводство) | K53: Оскар | L53: А-44 | M53: Чигрин Н.А. | R53: А819ЕВ | T53: А-44 | U53: =Таблица310[[#This Row],[Регистратор.Номенклатура]] -> Оскар | V53: =8.6*Таблица310[[#This Row],[Регистратор.Вес нетто]]/26740 -> 2.9588631 | W53: ГРК собственные семена (богара) | X53: богара | Y53: 5 | Z53: 45810 | AC53: 53-63 | AD53: высший | AE53: 111 | AF53: 45811 | AG53: 26 | AH53: =VLOOKUP(Таблица310[[#This Row],[№ акта]],'Степень зрелости 2025'!$H$13:$I$583,2,FALSE()) -> 55 | AI53: =VLOOKUP(Таблица310[[#This Row],[№ акта]],$AQ$1:$AT$594,2,FALSE()) -> А-44 | AJ53: =Таблица310[[#This Row],[Регистратор.Номенклатура]] -> Оскар | AK53: =VLOOKUP(Таблица310[[#This Row],[№ акта]],$AQ$1:$AT$594,4,FALSE()) -> ГРК собственные семена (богара) | AL53: =VLOOKUP(Таблица310[[#This Row],[№ акта]],$AQ$1:$AT$594,3,FALSE()) -> 2.2987229 | AM53: =IF(Таблица310[[#This Row],[Площадь уборки, га]]=Таблица310[[#This Row],[Площадь уборки до корр]],"нет","да") -> да | AN53: =Таблица310[[#This Row],[Площадь уборки до корр]]-Таблица310[[#This Row],[Площадь уборки, га]] -> -0.66014019 | AQ53: 111 | AR53: А-44 | AS53: 2.2987229 | AT53: ГРК собственные семена (богара)
A54: Степень зрелости | B54: =Таблица310[[#This Row],[Регистратор.Вес чистый]] -> 6114.4 | C54: 56 | D54: 112 | E54: 45810 | F54: 17590 | G54: 7060 | H54: 10530 | I54: 6114.4 | J54: Грин Рэй Кубань ООО (Овощеводство) | K54: Оскар | L54: А-44 | M54: Сурнин А.В | N54: 15:30:45 | O54: 13:55:17 | Q54: 738,930,739 | R54: В415ТТ | S54: МВ6101 | T54: А-44 | U54: =Таблица310[[#This Row],[Регистратор.Номенклатура]] -> Оскар | V54: =18*Таблица310[[#This Row],[Регистратор.Вес нетто]]/72040 -> 1.76402 | W54: ГРК собственные семена (богара) | X54: богара | Y54: 5 | Z54: 45810 | AA54: =Таблица310[[#This Row],[Регистратор.Вес нетто]] -> 7060 | AB54: Юнона | AC54: 53-63 | AD54: высший | AE54: 112 | AF54: 45810 | AG54: 20 Юнона продажаОтвес№1 | AH54: =VLOOKUP(Таблица310[[#This Row],[№ акта]],'Степень зрелости 2025'!$H$13:$I$583,2,FALSE()) -> 0 | AI54: =VLOOKUP(Таблица310[[#This Row],[№ акта]],$AQ$1:$AT$594,2,FALSE()) -> А-44 | AJ54: =Таблица310[[#This Row],[Регистратор.Номенклатура]] -> Оскар | AK54: =VLOOKUP(Таблица310[[#This Row],[№ акта]],$AQ$1:$AT$594,4,FALSE()) -> ГРК собственные семена (богара) | AL54: =VLOOKUP(Таблица310[[#This Row],[№ акта]],$AQ$1:$AT$594,3,FALSE()) -> 1.76402 | AM54: =IF(Таблица310[[#This Row],[Площадь уборки, га]]=Таблица310[[#This Row],[Площадь уборки до корр]],"нет","да") -> нет | AN54: =Таблица310[[#This Row],[Площадь уборки до корр]]-Таблица310[[#This Row],[Площадь уборки, га]] -> 0 | AQ54: 112 | AR54: А-44 | AS54: 1.76402 | AT54: ГРК собственные семена (богара)
A55: Степень зрелости | B55: =Таблица310[[#This Row],[Регистратор.Вес чистый]] -> 8787 | C55: 56 | D55: 113 | E55: 45810 | F55: 27260 | G55: 10180 | H55: 17080 | I55: 8787 | J55: Грин Рэй Кубань ООО (Овощеводство) | K55: Оскар | L55: А-44 | M55: Сидоренко Евгений Сергеевич | N55: 17:39:45 | O55: 15:13:12 | Q55: 740,931,741,932 | R55: М697ХВ | S55: ма4170 | T55: А-44 | U55: =Таблица310[[#This Row],[Регистратор.Номенклатура]] -> Оскар | V55: =18*Таблица310[[#This Row],[Регистратор.Вес нетто]]/72040 -> 2.5435869 | W55: ГРК собственные семена (богара) | X55: богара | Y55: 5 | Z55: 45810 | AA55: =Таблица310[[#This Row],[Регистратор.Вес нетто]] -> 10180 | AB55: Юнона | AC55: 53-63 | AD55: высший | AE55: 113 | AF55: 45810 | AG55: 21Юнона продажаОтвес№2 | AH55: =VLOOKUP(Таблица310[[#This Row],[№ акта]],'Степень зрелости 2025'!$H$13:$I$583,2,FALSE()) -> 0 | AI55: =VLOOKUP(Таблица310[[#This Row],[№ акта]],$AQ$1:$AT$594,2,FALSE()) -> А-44 | AJ55: =Таблица310[[#This Row],[Регистратор.Номенклатура]] -> Оскар | AK55: =VLOOKUP(Таблица310[[#This Row],[№ акта]],$AQ$1:$AT$594,4,FALSE()) -> ГРК собственные семена (богара) | AL55: =VLOOKUP(Таблица310[[#This Row],[№ акта]],$AQ$1:$AT$594,3,FALSE()) -> 2.5435869 | AM55: =IF(Таблица310[[#This Row],[Площадь уборки, га]]=Таблица310[[#This Row],[Площадь уборки до корр]],"нет","да") -> нет | AN55: =Таблица310[[#This Row],[Площадь уборки до корр]]-Таблица310[[#This Row],[Площадь уборки, га]] -> 0 | AQ55: 113 | AR55: А-44 | AS55: 2.5435869 | AT55: ГРК собственные семена (богара)
A56: Степень зрелости | B56: =Таблица310[[#This Row],[Регистратор.Вес чистый]] -> 12905.6 | C56: 55 | D56: 114 | E56: 45810 | F56: 32700 | G56: 14910 | H56: 17790 | I56: 12905.6 | J56: Грин Рэй Кубань ООО (Овощеводство) | K56: Оскар | L56: А-44 | M56: Дмитриев Николай Александрович | N56: 21:20:18 | O56: 16:30:01 | Q56: 744,935,934,743,742,933 | R56: М202СХ | S56: МВ0464 | T56: А-44 | U56: =Таблица310[[#This Row],[Регистратор.Номенклатура]] -> Оскар | V56: =18*Таблица310[[#This Row],[Регистратор.Вес нетто]]/72040 -> 3.7254303 | W56: ГРК собственные семена (богара) | X56: богара | Y56: 5 | Z56: 45810 | AA56: =Таблица310[[#This Row],[Регистратор.Вес нетто]] -> 14910 | AB56: Юнона | AC56: 53-63 | AD56: высший | AE56: 114 | AF56: 45810 | AG56: 22Юнона продажаОтвес№3 | AH56: =VLOOKUP(Таблица310[[#This Row],[№ акта]],'Степень зрелости 2025'!$H$13:$I$583,2,FALSE()) -> 0 | AI56: =VLOOKUP(Таблица310[[#This Row],[№ акта]],$AQ$1:$AT$594,2,FALSE()) -> А-44 | AJ56: =Таблица310[[#This Row],[Регистратор.Номенклатура]] -> Оскар | AK56: =VLOOKUP(Таблица310[[#This Row],[№ акта]],$AQ$1:$AT$594,4,FALSE()) -> ГРК собственные семена (богара) | AL56: =VLOOKUP(Таблица310[[#This Row],[№ акта]],$AQ$1:$AT$594,3,FALSE()) -> 3.7254303 | AM56: =IF(Таблица310[[#This Row],[Площадь уборки, га]]=Таблица310[[#This Row],[Площадь уборки до корр]],"нет","да") -> нет | AN56: =Таблица310[[#This Row],[Площадь уборки до корр]]-Таблица310[[#This Row],[Площадь уборки, га]] -> 0 | AQ56: 114 | AR56: А-44 | AS56: 3.7254303 | AT56: ГРК собственные семена (богара)
A57: Степень зрелости | B57: =Таблица310[[#This Row],[Регистратор.Вес чистый]] -> 16610 | C57: 47 | D57: 115 | E57: 45810 | F57: 34160 | G57: 17960 | H57: 16200 | I57: 16610 | J57: Кубань УОХ | K57: Изюминка | L57: 2/4 | M57: Мормуль А.Е. | Q57: 744,935,934,743,742,933 | R57: х474 ке | S57: МВ0464 | T57: 2/4 | U57: =Таблица310[[#This Row],[Регистратор.Номенклатура]] -> Изюминка | V57: =12*Таблица310[[#This Row],[Регистратор.Вес нетто]]/71490 -> 3.0146874 | W57: Учхоз Кубань (богара) | X57: богара | Y57: 4 | Z57: 45810 | AA57: =Таблица310[[#This Row],[Регистратор.Вес нетто]] -> 17960 | AB57: Пищевик | AC57: 40-52 | AD57: высший | AE57: 115 | AF57: 45810 | AG57: 65931 Пищевик продажа | AH57: =VLOOKUP(Таблица310[[#This Row],[№ акта]],'Степень зрелости 2025'!$H$13:$I$583,2,FALSE()) -> 0 | AI57: =VLOOKUP(Таблица310[[#This Row],[№ акта]],$AQ$1:$AT$594,2,FALSE()) -> 2/4 | AJ57: =Таблица310[[#This Row],[Регистратор.Номенклатура]] -> Изюминка | AK57: =VLOOKUP(Таблица310[[#This Row],[№ акта]],$AQ$1:$AT$594,4,FALSE()) -> Учхоз Кубань (богара) | AL57: =VLOOKUP(Таблица310[[#This Row],[№ акта]],$AQ$1:$AT$594,3,FALSE()) -> 3.0146874 | AM57: =IF(Таблица310[[#This Row],[Площадь уборки, га]]=Таблица310[[#This Row],[Площадь уборки до корр]],"нет","да") -> нет | AN57: =Таблица310[[#This Row],[Площадь уборки до корр]]-Таблица310[[#This Row],[Площадь уборки, га]] -> 0 | AQ57: 115 | AR57: 2/4 | AS57: 3.0146874 | AT57: Учхоз Кубань (богара)
A58: Степень зрелости | B58: 4764.1 | C58: 55 | D58: 132 | E58: 45811 | F58: 29230 | G58: 6710 | H58: 22520 | I58: 4764.1 | J58: Грин Рэй Кубань ООО (Овощеводство) | K58: Оскар | L58: А-46 | M58: Сайко Василий Викторович | N58: 14:16:24 | O58: 14:44:07 | Q58: 756,947,755 | R58: А816ЕВ | S58: ЕС2898 | T58: А-46 | U58: =Таблица310[[#This Row],[Регистратор.Номенклатура]] -> Оскар | V58: =20.5*Таблица310[[#This Row],[Регистратор.Вес нетто]]/68840 -> 1.9981842 | W58: ГРК собственные семена (богара) | X58: богара | Y58: 6 | Z58: 45811 | AC58: 53-63 | AD58: высший | AE58: 132 | AF58: 45811 | AG58: 30 | AH58: =VLOOKUP(Таблица310[[#This Row],[№ акта]],'Степень зрелости 2025'!$H$13:$I$583,2,FALSE()) -> 55 | AI58: =VLOOKUP(Таблица310[[#This Row],[№ акта]],$AQ$1:$AT$594,2,FALSE()) -> А-46 | AJ58: =Таблица310[[#This Row],[Регистратор.Номенклатура]] -> Оскар | AK58: =VLOOKUP(Таблица310[[#This Row],[№ акта]],$AQ$1:$AT$594,4,FALSE()) -> ГРК собственные семена (богара) | AL58: =VLOOKUP(Таблица310[[#This Row],[№ акта]],$AQ$1:$AT$594,3,FALSE()) -> 2.4216225 | AM58: =IF(Таблица310[[#This Row],[Площадь уборки, га]]=Таблица310[[#This Row],[Площадь уборки до корр]],"нет","да") -> да | AN58: =Таблица310[[#This Row],[Площадь уборки до корр]]-Таблица310[[#This Row],[Площадь уборки, га]] -> 0.42343827 | AQ58: 132 | AR58: А-46 | AS58: 2.4216225 | AT58: ГРК собственные семена (богара)
A59: Степень зрелости | B59: 6368.8 | C59: 51 | D59: 136 | E59: 45811 | F59: 22520 | G59: 8380 | H59: 14140 | I59: 6368.8 | J59: Грин Рэй Кубань ООО (Овощеводство) | K59: Оскар | L59: А-44 | M59: Сайко Василий Викторович | N59: 14:45:20 | O59: 15:12:54 | Q59: 946,945,944,943 | R59: А816ЕВ | S59: ЕС2898 | T59: А-44 | U59: =Таблица310[[#This Row],[Регистратор.Номенклатура]] -> Оскар | V59: =8.6*Таблица310[[#This Row],[Регистратор.Вес нетто]]/26740 -> 2.6951384 | W59: ГРК собственные семена (богара) | X59: богара | Y59: 6 | Z59: 45811 | AC59: 40-52 | AD59: высший | AE59: 136 | AF59: 45811 | AG59: 30 | AH59: =VLOOKUP(Таблица310[[#This Row],[№ акта]],'Степень зрелости 2025'!$H$13:$I$583,2,FALSE()) -> 51 | AI59: =VLOOKUP(Таблица310[[#This Row],[№ акта]],$AQ$1:$AT$594,2,FALSE()) -> А-44 | AJ59: =Таблица310[[#This Row],[Регистратор.Номенклатура]] -> Оскар | AK59: =VLOOKUP(Таблица310[[#This Row],[№ акта]],$AQ$1:$AT$594,4,FALSE()) -> ГРК собственные семена (богара) | AL59: =VLOOKUP(Таблица310[[#This Row],[№ акта]],$AQ$1:$AT$594,3,FALSE()) -> 1.6343247 | AM59: =IF(Таблица310[[#This Row],[Площадь уборки, га]]=Таблица310[[#This Row],[Площадь уборки до корр]],"нет","да") -> да | AN59: =Таблица310[[#This Row],[Площадь уборки до корр]]-Таблица310[[#This Row],[Площадь уборки, га]] -> -1.0608136 | AQ59: 136 | AR59: А-44 | AS59: 1.6343247 | AT59: ГРК собственные семена (богара)
A60: Степень зрелости | B60: 3215.4 | C60: 50 | D60: 137 | E60: 45811 | F60: 14110 | G60: 4660 | H60: 9450 | I60: 3215.4 | J60: Грин Рэй Кубань ООО (Овощеводство) | K60: Оскар | L60: А-46 | M60: Сайко Василий Викторович | N60: 16:10:25 | O60: 16:28:03 | Q60: 948.757 | R60: А816ЕВ | T60: А-46 | U60: =Таблица310[[#This Row],[Регистратор.Номенклатура]] -> Оскар | V60: =20.5*Таблица310[[#This Row],[Регистратор.Вес нетто]]/68840 -> 1.3877106 | W60: ГРК собственные семена (богара) | X60: богара | Y60: 6 | Z60: 45811 | AC60: 40-52 | AD60: высший | AE60: 137 | AF60: 45811 | AG60: 30 | AH60: =VLOOKUP(Таблица310[[#This Row],[№ акта]],'Степень зрелости 2025'!$H$13:$I$583,2,FALSE()) -> 50 | AI60: =VLOOKUP(Таблица310[[#This Row],[№ акта]],$AQ$1:$AT$594,2,FALSE()) -> А-46 | AJ60: =Таблица310[[#This Row],[Регистратор.Номенклатура]] -> Оскар | AK60: =VLOOKUP(Таблица310[[#This Row],[№ акта]],$AQ$1:$AT$594,4,FALSE()) -> ГРК собственные семена (богара) | AL60: =VLOOKUP(Таблица310[[#This Row],[№ акта]],$AQ$1:$AT$594,3,FALSE()) -> 1.6817825 | AM60: =IF(Таблица310[[#This Row],[Площадь уборки, га]]=Таблица310[[#This Row],[Площадь уборки до корр]],"нет","да") -> да | AN60: =Таблица310[[#This Row],[Площадь уборки до корр]]-Таблица310[[#This Row],[Площадь уборки, га]] -> 0.29407189 | AQ60: 137 | AR60: А-46 | AS60: 1.6817825 | AT60: ГРК собственные семена (богара)
A61: Степень зрелости | B61: 11018.8 | C61: 53 | D61: 138 | E61: 45811 | F61: 34390 | G61: 13520 | H61: 20870 | I61: 11018.8 | J61: Кубань УОХ | K61: Преладо | L61: 2/4 | M61: Мудрак Вадим Васильевич | N61: 15:41:07 | O61: 16:53:44 | Q61: 252,053,451,501,253,054 | R61: Х514ОК | S61: ЕУ4356 | T61: 2/4 | U61: =Таблица310[[#This Row],[Регистратор.Номенклатура]] -> Преладо | V61: =33*Таблица310[[#This Row],[Регистратор.Вес нетто]]/201670 -> 2.2123271 | W61: Учхоз Кубань (богара) | X61: богара | Y61: 5 | Z61: 45811 | AC61: 53-63 | AD61: высший | AE61: 138 | AF61: 45811 | AG61: 65933 | AH61: =VLOOKUP(Таблица310[[#This Row],[№ акта]],'Степень зрелости 2025'!$H$13:$I$583,2,FALSE()) -> 53 | AI61: =VLOOKUP(Таблица310[[#This Row],[№ акта]],$AQ$1:$AT$594,2,FALSE()) -> 2/4 | AJ61: =Таблица310[[#This Row],[Регистратор.Номенклатура]] -> Преладо | AK61: =VLOOKUP(Таблица310[[#This Row],[№ акта]],$AQ$1:$AT$594,4,FALSE()) -> Учхоз Кубань (богара) | AL61: =VLOOKUP(Таблица310[[#This Row],[№ акта]],$AQ$1:$AT$594,3,FALSE()) -> 2.2123271 | AM61: =IF(Таблица310[[#This Row],[Площадь уборки, га]]=Таблица310[[#This Row],[Площадь уборки до корр]],"нет","да") -> нет | AN61: =Таблица310[[#This Row],[Площадь уборки до корр]]-Таблица310[[#This Row],[Площадь уборки, га]] -> 0 | AQ61: 138 | AR61: 2/4 | AS61: 2.2123271 | AT61: Учхоз Кубань (богара)
A62: Степень зрелости | B62: 11356 | C62: 56 | D62: 139 | E62: 45811 | F62: 28460 | G62: 13600 | H62: 14860 | I62: 11356 | J62: Кубань УОХ | K62: Преладо | L62: 2/4 | M62: Егоян Артем Владимирович | N62: 16:56:15 | O62: 18:47:54 | Q62: 057,056,255,452,055,254 | R62: А701СН | S62: ЕН9185 | T62: 2/4 | U62: =Таблица310[[#This Row],[Регистратор.Номенклатура]] -> Преладо | V62: =33*Таблица310[[#This Row],[Регистратор.Вес нетто]]/201670 -> 2.2254178 | W62: Учхоз Кубань (богара) | X62: богара | Y62: 5 | Z62: 45811 | AC62: 53-63 | AD62: высший | AE62: 139 | AF62: 45811 | AG62: 65935 | AH62: =VLOOKUP(Таблица310[[#This Row],[№ акта]],'Степень зрелости 2025'!$H$13:$I$583,2,FALSE()) -> 56 | AI62: =VLOOKUP(Таблица310[[#This Row],[№ акта]],$AQ$1:$AT$594,2,FALSE()) -> 2/4 | AJ62: =Таблица310[[#This Row],[Регистратор.Номенклатура]] -> Преладо | AK62: =VLOOKUP(Таблица310[[#This Row],[№ акта]],$AQ$1:$AT$594,4,FALSE()) -> Учхоз Кубань (богара) | AL62: =VLOOKUP(Таблица310[[#This Row],[№ акта]],$AQ$1:$AT$594,3,FALSE()) -> 2.2254178 | AM62: =IF(Таблица310[[#This Row],[Площадь уборки, га]]=Таблица310[[#This Row],[Площадь уборки до корр]],"нет","да") -> нет | AN62: =Таблица310[[#This Row],[Площадь уборки до корр]]-Таблица310[[#This Row],[Площадь уборки, га]] -> 0 | AQ62: 139 | AR62: 2/4 | AS62: 2.2254178 | AT62: Учхоз Кубань (богара)
A63: Степень зрелости | B63: 11660.2 | C63: 55 | D63: 140 | E63: 45811 | F63: 37510 | G63: 13480 | H63: 24030 | I63: 11660.2 | J63: Кубань УОХ | K63: Преладо | L63: 2/4 | M63: Мудрак Игорь Вадимович | N63: 17:57:40 | O63: 20:37:14 | Q63: 256,058,257,453,059,258 | R63: С198УЕ | S63: ЕУ4355 | T63: 2/4 | U63: =Таблица310[[#This Row],[Регистратор.Номенклатура]] -> Преладо | V63: =33*Таблица310[[#This Row],[Регистратор.Вес нетто]]/201670 -> 2.2057817 | W63: Учхоз Кубань (богара) | X63: богара | Y63: 5 | Z63: 45811 | AC63: 53-63 | AD63: высший | AE63: 140 | AF63: 45811 | AG63: 65936 | AH63: =VLOOKUP(Таблица310[[#This Row],[№ акта]],'Степень зрелости 2025'!$H$13:$I$583,2,FALSE()) -> 55 | AI63: =VLOOKUP(Таблица310[[#This Row],[№ акта]],$AQ$1:$AT$594,2,FALSE()) -> 2/4 | AJ63: =Таблица310[[#This Row],[Регистратор.Номенклатура]] -> Преладо | AK63: =VLOOKUP(Таблица310[[#This Row],[№ акта]],$AQ$1:$AT$594,4,FALSE()) -> Учхоз Кубань (богара) | AL63: =VLOOKUP(Таблица310[[#This Row],[№ акта]],$AQ$1:$AT$594,3,FALSE()) -> 2.2057817 | AM63: =IF(Таблица310[[#This Row],[Площадь уборки, га]]=Таблица310[[#This Row],[Площадь уборки до корр]],"нет","да") -> нет | AN63: =Таблица310[[#This Row],[Площадь уборки до корр]]-Таблица310[[#This Row],[Площадь уборки, га]] -> 0 | AQ63: 140 | AR63: 2/4 | AS63: 2.2057817 | AT63: Учхоз Кубань (богара)
A64: Степень зрелости | B64: 3582.2 | C64: 55 | D64: 141 | E64: 45811 | F64: 13910 | G64: 4450 | H64: 9460 | I64: 3582.2 | J64: Грин Рэй Кубань ООО (Овощеводство) | K64: Оскар | L64: А-46 | M64: Сайко Василий Викторович | N64: 20:08:25 | O64: 21:02:26 | Q64: 949.761 | R64: А816ЕВ | T64: А-46 | U64: =Таблица310[[#This Row],[Регистратор.Номенклатура]] -> Оскар | V64: =20.5*Таблица310[[#This Row],[Регистратор.Вес нетто]]/68840 -> 1.3251743 | W64: ГРК собственные семена (богара) | X64: богара | Y64: 6 | Z64: 45811 | AC64: 53-63 | AD64: высший | AE64: 141 | AF64: 45811 | AG64: 31 | AH64: =VLOOKUP(Таблица310[[#This Row],[№ акта]],'Степень зрелости 2025'!$H$13:$I$583,2,FALSE()) -> 55 | AI64: =VLOOKUP(Таблица310[[#This Row],[№ акта]],$AQ$1:$AT$594,2,FALSE()) -> А-46 | AJ64: =Таблица310[[#This Row],[Регистратор.Номенклатура]] -> Оскар | AK64: =VLOOKUP(Таблица310[[#This Row],[№ акта]],$AQ$1:$AT$594,4,FALSE()) -> ГРК собственные семена (богара) | AL64: =VLOOKUP(Таблица310[[#This Row],[№ акта]],$AQ$1:$AT$594,3,FALSE()) -> 1.605994 | AM64: =IF(Таблица310[[#This Row],[Площадь уборки, га]]=Таблица310[[#This Row],[Площадь уборки до корр]],"нет","да") -> да | AN64: =Таблица310[[#This Row],[Площадь уборки до корр]]-Таблица310[[#This Row],[Площадь уборки, га]] -> 0.28081972 | AQ64: 141 | AR64: А-46 | AS64: 1.605994 | AT64: ГРК собственные семена (богара)
A65: Степень зрелости | B65: 11508 | C65: 55 | D65: 142 | E65: 45811 | F65: 28520 | G65: 13700 | H65: 14820 | I65: 11508 | J65: Кубань УОХ | K65: Преладо | L65: 2/4 | M65: Фомин Николай Григорьевич | N65: 20:47:31 | O65: 21:42:51 | Q65: 063,261,262,064,263,065 | R65: А731ВА | S65: МО8130 | T65: 2/4 | U65: =Таблица310[[#This Row],[Регистратор.Номенклатура]] -> Преладо | V65: =33*Таблица310[[#This Row],[Регистратор.Вес нетто]]/201670 -> 2.2417811 | W65: Учхоз Кубань (богара) | X65: богара | Y65: 5 | Z65: 45811 | AC65: 53-63 | AD65: высший | AE65: 142 | AF65: 45811 | AG65: 65937 | AH65: =VLOOKUP(Таблица310[[#This Row],[№ акта]],'Степень зрелости 2025'!$H$13:$I$583,2,FALSE()) -> 55 | AI65: =VLOOKUP(Таблица310[[#This Row],[№ акта]],$AQ$1:$AT$594,2,FALSE()) -> 2/4 | AJ65: =Таблица310[[#This Row],[Регистратор.Номенклатура]] -> Преладо | AK65: =VLOOKUP(Таблица310[[#This Row],[№ акта]],$AQ$1:$AT$594,4,FALSE()) -> Учхоз Кубань (богара) | AL65: =VLOOKUP(Таблица310[[#This Row],[№ акта]],$AQ$1:$AT$594,3,FALSE()) -> 2.2417811 | AM65: =IF(Таблица310[[#This Row],[Площадь уборки, га]]=Таблица310[[#This Row],[Площадь уборки до корр]],"нет","да") -> нет | AN65: =Таблица310[[#This Row],[Площадь уборки до корр]]-Таблица310[[#This Row],[Площадь уборки, га]] -> 0 | AQ65: 142 | AR65: 2/4 | AS65: 2.2417811 | AT65: Учхоз Кубань (богара)
A66: Степень зрелости | B66: 10904 | C66: 57 | D66: 143 | E66: 45811 | F66: 28750 | G66: 13630 | H66: 15120 | I66: 10904 | J66: Кубань УОХ | K66: Преладо | L66: 2/4 | M66: Извеков Владимир Владимирович | N66: 21:53:32 | O66: 23:06:17 | Q66: 264,457,265,458,459,066 | R66: Н378ХЕ | S66: ЕР7829 | T66: 2/4 | U66: =Таблица310[[#This Row],[Регистратор.Номенклатура]] -> Преладо | V66: =33*Таблица310[[#This Row],[Регистратор.Вес нетто]]/201670 -> 2.2303268 | W66: Учхоз Кубань (богара) | X66: богара | Y66: 5 | Z66: 45811 | AC66: 53-63 | AD66: высший | AE66: 143 | AF66: 45811 | AG66: 65938 | AH66: =VLOOKUP(Таблица310[[#This Row],[№ акта]],'Степень зрелости 2025'!$H$13:$I$583,2,FALSE()) -> 57 | AI66: =VLOOKUP(Таблица310[[#This Row],[№ акта]],$AQ$1:$AT$594,2,FALSE()) -> 2/4 | AJ66: =Таблица310[[#This Row],[Регистратор.Номенклатура]] -> Преладо | AK66: =VLOOKUP(Таблица310[[#This Row],[№ акта]],$AQ$1:$AT$594,4,FALSE()) -> Учхоз Кубань (богара) | AL66: =VLOOKUP(Таблица310[[#This Row],[№ акта]],$AQ$1:$AT$594,3,FALSE()) -> 2.2303268 | AM66: =IF(Таблица310[[#This Row],[Площадь уборки, га]]=Таблица310[[#This Row],[Площадь уборки до корр]],"нет","да") -> нет | AN66: =Таблица310[[#This Row],[Площадь уборки до корр]]-Таблица310[[#This Row],[Площадь уборки, га]] -> 0 | AQ66: 143 | AR66: 2/4 | AS66: 2.2303268 | AT66: Учхоз Кубань (богара)
A67: Степень зрелости | B67: 11029 | C67: 57 | D67: 144 | E67: 45811 | F67: 28870 | G67: 13450 | H67: 15420 | I67: 11029 | J67: Кубань УОХ | K67: Преладо | L67: 2/4 | M67: Емец Р.А. | N67: 23:11:59 | O67: 23:58:13 | Q67: 067,068,461,266,460,069 | R67: У315НХ | S67: ЕУ4649 | T67: 2/4 | U67: =Таблица310[[#This Row],[Регистратор.Номенклатура]] -> Преладо | V67: =33*Таблица310[[#This Row],[Регистратор.Вес нетто]]/201670 -> 2.2008727 | W67: Учхоз Кубань (богара) | X67: богара | Y67: 5 | Z67: 45811 | AC67: 53-63 | AD67: высший | AE67: 144 | AF67: 45811 | AG67: 65939 | AH67: =VLOOKUP(Таблица310[[#This Row],[№ акта]],'Степень зрелости 2025'!$H$13:$I$583,2,FALSE()) -> 57 | AI67: =VLOOKUP(Таблица310[[#This Row],[№ акта]],$AQ$1:$AT$594,2,FALSE()) -> 2/4 | AJ67: =Таблица310[[#This Row],[Регистратор.Номенклатура]] -> Преладо | AK67: =VLOOKUP(Таблица310[[#This Row],[№ акта]],$AQ$1:$AT$594,4,FALSE()) -> Учхоз Кубань (богара) | AL67: =VLOOKUP(Таблица310[[#This Row],[№ акта]],$AQ$1:$AT$594,3,FALSE()) -> 2.2008727 | AM67: =IF(Таблица310[[#This Row],[Площадь уборки, га]]=Таблица310[[#This Row],[Площадь уборки до корр]],"нет","да") -> нет | AN67: =Таблица310[[#This Row],[Площадь уборки до корр]]-Таблица310[[#This Row],[Площадь уборки, га]] -> 0 | AQ67: 144 | AR67: 2/4 | AS67: 2.2008727 | AT67: Учхоз Кубань (богара)
A68: Степень зрелости | B68: 10953.6 | C68: 58 | D68: 145 | E68: 45811 | F68: 28210 | G68: 13440 | H68: 14770 | I68: 10953.6 | J68: Кубань УОХ | K68: Преладо | L68: 2/4 | M68: Кулик О В | N68: 23:52:02 | O68: 1:27:53 | Q68: 267,070,463,071,462,268 | R68: К403ЕМ | S68: ЕС6095 | T68: 2/4 | U68: =Таблица310[[#This Row],[Регистратор.Номенклатура]] -> Преладо | V68: =33*Таблица310[[#This Row],[Регистратор.Вес нетто]]/201670 -> 2.1992364 | W68: Учхоз Кубань (богара) | X68: богара | Y68: 5 | Z68: 45811 | AC68: 53-63 | AD68: высший | AE68: 145 | AF68: 45811 | AG68: 65941 | AH68: =VLOOKUP(Таблица310[[#This Row],[№ акта]],'Степень зрелости 2025'!$H$13:$I$583,2,FALSE()) -> 58 | AI68: =VLOOKUP(Таблица310[[#This Row],[№ акта]],$AQ$1:$AT$594,2,FALSE()) -> 2/4 | AJ68: =Таблица310[[#This Row],[Регистратор.Номенклатура]] -> Преладо | AK68: =VLOOKUP(Таблица310[[#This Row],[№ акта]],$AQ$1:$AT$594,4,FALSE()) -> Учхоз Кубань (богара) | AL68: =VLOOKUP(Таблица310[[#This Row],[№ акта]],$AQ$1:$AT$594,3,FALSE()) -> 2.1992364 | AM68: =IF(Таблица310[[#This Row],[Площадь уборки, га]]=Таблица310[[#This Row],[Площадь уборки до корр]],"нет","да") -> нет | AN68: =Таблица310[[#This Row],[Площадь уборки до корр]]-Таблица310[[#This Row],[Площадь уборки, га]] -> 0 | AQ68: 145 | AR68: 2/4 | AS68: 2.1992364 | AT68: Учхоз Кубань (богара)
A69: Степень зрелости | B69: 10483.2 | C69: 58 | D69: 146 | E69: 45812 | F69: 29090 | G69: 13440 | H69: 15650 | I69: 10483.2 | J69: Кубань УОХ | K69: Преладо | L69: 2/4 | M69: Грищенко Александр Александрович | N69: 0:51:31 | O69: 1:48:09 | Q69: 269,072,464,465,270,073 | R69: К416ТН | S69: МС8480 | T69: 2/4 | U69: =Таблица310[[#This Row],[Регистратор.Номенклатура]] -> Преладо | V69: =33*Таблица310[[#This Row],[Регистратор.Вес нетто]]/201670 -> 2.1992364 | W69: Учхоз Кубань (богара) | X69: богара | Y69: 5 | Z69: 45811 | AC69: 53-63 | AD69: высший | AE69: 146 | AF69: 45812 | AG69: 65930 | AH69: =VLOOKUP(Таблица310[[#This Row],[№ акта]],'Степень зрелости 2025'!$H$13:$I$583,2,FALSE()) -> 58 | AI69: =VLOOKUP(Таблица310[[#This Row],[№ акта]],$AQ$1:$AT$594,2,FALSE()) -> 2/4 | AJ69: =Таблица310[[#This Row],[Регистратор.Номенклатура]] -> Преладо | AK69: =VLOOKUP(Таблица310[[#This Row],[№ акта]],$AQ$1:$AT$594,4,FALSE()) -> Учхоз Кубань (богара) | AL69: =VLOOKUP(Таблица310[[#This Row],[№ акта]],$AQ$1:$AT$594,3,FALSE()) -> 2.1992364 | AM69: =IF(Таблица310[[#This Row],[Площадь уборки, га]]=Таблица310[[#This Row],[Площадь уборки до корр]],"нет","да") -> нет | AN69: =Таблица310[[#This Row],[Площадь уборки до корр]]-Таблица310[[#This Row],[Площадь уборки, га]] -> 0 | AQ69: 146 | AR69: 2/4 | AS69: 2.1992364 | AT69: Учхоз Кубань (богара)
A70: Степень зрелости | B70: 11356.8 | C70: 57 | D70: 147 | E70: 45812 | F70: 28130 | G70: 13440 | H70: 14690 | I70: 11356.8 | J70: Кубань УОХ | K70: Преладо | L70: 2/4 | M70: Сероштан Станислав Викторович | N70: 1:35:43 | O70: 3:49:35 | Q70: 074,466,271,075,272,076, | R70: Е758РЕ | S70: ЕХ4191 | T70: 2/4 | U70: =Таблица310[[#This Row],[Регистратор.Номенклатура]] -> Преладо | V70: =33*Таблица310[[#This Row],[Регистратор.Вес нетто]]/201670 -> 2.1992364 | W70: Учхоз Кубань (богара) | X70: богара | Y70: 5 | Z70: 45811 | AC70: 53-63 | AD70: высший | AE70: 147 | AF70: 45812 | AG70: 65942 | AH70: =VLOOKUP(Таблица310[[#This Row],[№ акта]],'Степень зрелости 2025'!$H$13:$I$583,2,FALSE()) -> 57 | AI70: =VLOOKUP(Таблица310[[#This Row],[№ акта]],$AQ$1:$AT$594,2,FALSE()) -> 2/4 | AJ70: =Таблица310[[#This Row],[Регистратор.Номенклатура]] -> Преладо | AK70: =VLOOKUP(Таблица310[[#This Row],[№ акта]],$AQ$1:$AT$594,4,FALSE()) -> Учхоз Кубань (богара) | AL70: =VLOOKUP(Таблица310[[#This Row],[№ акта]],$AQ$1:$AT$594,3,FALSE()) -> 2.1992364 | AM70: =IF(Таблица310[[#This Row],[Площадь уборки, га]]=Таблица310[[#This Row],[Площадь уборки до корр]],"нет","да") -> нет | AN70: =Таблица310[[#This Row],[Площадь уборки до корр]]-Таблица310[[#This Row],[Площадь уборки, га]] -> 0 | AQ70: 147 | AR70: 2/4 | AS70: 2.1992364 | AT70: Учхоз Кубань (богара)
A71: Степень зрелости | B71: 10645 | C71: 58 | D71: 148 | E71: 45812 | F71: 28070 | G71: 13390 | H71: 14680 | I71: 10645 | J71: Кубань УОХ | K71: Преладо | L71: 2/4 | M71: Огнев Максим Викторович | N71: 2:31:56 | O71: 3:57:53 | Q71: 273,467,077,468,274,078 | R71: Р755НН | S71: РА5550 | T71: 2/4 | U71: =Таблица310[[#This Row],[Регистратор.Номенклатура]] -> Преладо | V71: =33*Таблица310[[#This Row],[Регистратор.Вес нетто]]/201670 -> 2.1910547 | W71: Учхоз Кубань (богара) | X71: богара | Y71: 5 | Z71: 45811 | AC71: 53-63 | AD71: высший | AE71: 148 | AF71: 45812 | AG71: 65943 | AH71: =VLOOKUP(Таблица310[[#This Row],[№ акта]],'Степень зрелости 2025'!$H$13:$I$583,2,FALSE()) -> 58 | AI71: =VLOOKUP(Таблица310[[#This Row],[№ акта]],$AQ$1:$AT$594,2,FALSE()) -> 2/4 | AJ71: =Таблица310[[#This Row],[Регистратор.Номенклатура]] -> Преладо | AK71: =VLOOKUP(Таблица310[[#This Row],[№ акта]],$AQ$1:$AT$594,4,FALSE()) -> Учхоз Кубань (богара) | AL71: =VLOOKUP(Таблица310[[#This Row],[№ акта]],$AQ$1:$AT$594,3,FALSE()) -> 2.1910547 | AM71: =IF(Таблица310[[#This Row],[Площадь уборки, га]]=Таблица310[[#This Row],[Площадь уборки до корр]],"нет","да") -> нет | AN71: =Таблица310[[#This Row],[Площадь уборки до корр]]-Таблица310[[#This Row],[Площадь уборки, га]] -> 0 | AQ71: 148 | AR71: 2/4 | AS71: 2.1910547 | AT71: Учхоз Кубань (богара)
A72: Степень зрелости | B72: 5545.8 | C72: 56 | D72: 149 | E72: 45812 | F72: 16470 | G72: 7020 | H72: 9450 | I72: 5545.8 | J72: Грин Рэй Кубань ООО (Овощеводство) | K72: Оскар | L72: А-46 | M72: Сайко Василий Викторович | N72: 4:19:52 | O72: 5:06:09 | Q72: 959,768,961 | R72: А816ЕВ | T72: А-46 | U72: =Таблица310[[#This Row],[Регистратор.Номенклатура]] -> Оскар | V72: =29.2*Таблица310[[#This Row],[Регистратор.Вес нетто]]/69890 -> 2.9329518 | W72: ГРК собственные семена (богара) | X72: богара | Y72: 6 | Z72: 45811 | AC72: 53-63 | AD72: высший | AE72: 149 | AF72: 45812 | AG72: 34 | AH72: =VLOOKUP(Таблица310[[#This Row],[№ акта]],'Степень зрелости 2025'!$H$13:$I$583,2,FALSE()) -> 56 | AI72: =VLOOKUP(Таблица310[[#This Row],[№ акта]],$AQ$1:$AT$594,2,FALSE()) -> А-46 | AJ72: =Таблица310[[#This Row],[Регистратор.Номенклатура]] -> Оскар | AK72: =VLOOKUP(Таблица310[[#This Row],[№ акта]],$AQ$1:$AT$594,4,FALSE()) -> ГРК собственные семена (богара) | AL72: =VLOOKUP(Таблица310[[#This Row],[№ акта]],$AQ$1:$AT$594,3,FALSE()) -> 2.5335007 | AM72: =IF(Таблица310[[#This Row],[Площадь уборки, га]]=Таблица310[[#This Row],[Площадь уборки до корр]],"нет","да") -> да | AN72: =Таблица310[[#This Row],[Площадь уборки до корр]]-Таблица310[[#This Row],[Площадь уборки, га]] -> -0.39945108 | AQ72: 149 | AR72: А-46 | AS72: 2.5335007 | AT72: ГРК собственные семена (богара)
A73: Степень зрелости | B73: 11030.2 | C73: 58 | D73: 150 | E73: 45812 | F73: 28240 | G73: 13370 | H73: 14870 | I73: 11030.2 | J73: Кубань УОХ | K73: Преладо | L73: 2/4 | M73: Лазаренко Вятчеслав Владимирович | N73: 4:45:31 | O73: 6:19:03 | Q73: 275,079,470,276,469,080 | R73: Т239УС | S73: ЕС6637 | T73: 2/4 | U73: =Таблица310[[#This Row],[Регистратор.Номенклатура]] -> Преладо | V73: =33*Таблица310[[#This Row],[Регистратор.Вес нетто]]/201670 -> 2.187782 | W73: Учхоз Кубань (богара) | X73: богара | Y73: 5 | Z73: 45811 | AC73: 53-63 | AD73: высший | AE73: 150 | AF73: 45812 | AG73: 65947 | AH73: =VLOOKUP(Таблица310[[#This Row],[№ акта]],'Степень зрелости 2025'!$H$13:$I$583,2,FALSE()) -> 58 | AI73: =VLOOKUP(Таблица310[[#This Row],[№ акта]],$AQ$1:$AT$594,2,FALSE()) -> 2/4 | AJ73: =Таблица310[[#This Row],[Регистратор.Номенклатура]] -> Преладо | AK73: =VLOOKUP(Таблица310[[#This Row],[№ акта]],$AQ$1:$AT$594,4,FALSE()) -> Учхоз Кубань (богара) | AL73: =VLOOKUP(Таблица310[[#This Row],[№ акта]],$AQ$1:$AT$594,3,FALSE()) -> 2.187782 | AM73: =IF(Таблица310[[#This Row],[Площадь уборки, га]]=Таблица310[[#This Row],[Площадь уборки до корр]],"нет","да") -> нет | AN73: =Таблица310[[#This Row],[Площадь уборки до корр]]-Таблица310[[#This Row],[Площадь уборки, га]] -> 0 | AQ73: 150 | AR73: 2/4 | AS73: 2.187782 | AT73: Учхоз Кубань (богара)
